Workbook
Name \0: #REF!
Name \a: #REF!
Name \aq: #REF!
Name \b: #REF!
Name \C: #REF!
Name \e: #REF!
Name \f: #REF!
Name \l: #REF!
Name \p: #REF!
Name \q: #REF!
Name \S: #REF!
Name \w: #REF!
Name \x: #REF!
Name \z: #N/A
Name _________________________________________________________________________________________b111121: #REF!
Name _________________________________________________________________________________________Ki1: #REF!
Name _________________________________________________________________________________________Ki2: #REF!
Name ________________________________________________________________________________________b111121: #REF!
Name ________________________________________________________________________________________Ki1: #REF!
Name ________________________________________________________________________________________Ki2: #REF!
Name _______________________________________________________________________________________b111121: #REF!
Name _______________________________________________________________________________________Ki1: #REF!
Name _______________________________________________________________________________________Ki2: #REF!
Name _______________________________________________________________________________________MAN1: #REF!
Name _______________________________________________________________________________________PB1: #REF!
Name _______________________________________________________________________________________TB2: #REF!
Name ______________________________________________________________________________________b111121: #REF!
Name ______________________________________________________________________________________Ki1: #REF!
Name ______________________________________________________________________________________Ki2: #REF!
Name ______________________________________________________________________________________MAN1: #REF!
Name ______________________________________________________________________________________PB1: #REF!
Name ______________________________________________________________________________________TB2: #REF!
Name _____________________________________________________________________________________b111121: #REF!
Name _____________________________________________________________________________________Ki1: #REF!
Name _____________________________________________________________________________________Ki2: #REF!
Name _____________________________________________________________________________________MAN1: #REF!
Name _____________________________________________________________________________________PB1: #REF!
Name _____________________________________________________________________________________TB2: #REF!
Name ____________________________________________________________________________________b111121: #REF!
Name ____________________________________________________________________________________Ki1: #REF!
Name ____________________________________________________________________________________Ki2: #REF!
Name ____________________________________________________________________________________MAN1: #REF!
Name ____________________________________________________________________________________PB1: #REF!
Name ____________________________________________________________________________________TB2: #REF!
Name ___________________________________________________________________________________b111121: #REF!
Name ___________________________________________________________________________________Ki1: #REF!
Name ___________________________________________________________________________________Ki2: #REF!
Name ___________________________________________________________________________________MAN1: #REF!
Name ___________________________________________________________________________________PB1: #REF!
Name ___________________________________________________________________________________TB2: #REF!
Name __________________________________________________________________________________b111121: #REF!
Name __________________________________________________________________________________Ki1: #REF!
Name __________________________________________________________________________________Ki2: #REF!
Name __________________________________________________________________________________MAN1: #REF!
Name __________________________________________________________________________________PB1: #REF!
Name __________________________________________________________________________________TB2: #REF!
Name _________________________________________________________________________________b111121: #REF!
Name _________________________________________________________________________________Ki1: #REF!
Name _________________________________________________________________________________Ki2: #REF!
Name _________________________________________________________________________________MAN1: #REF!

Sheet MAIN SUMMARY
B1: PHOTON - DLF CYBER CITY - HYDERABAD UNPRICED BOQ FOR INTERIOR AND MEP SERVICES
A3: BOQ SUMMARY
A4: S.NO | B4: PACKAGE | C4: AMOUNT( Rs)
A5: 1 | B5: INTERIOR WORKS | C5: =INTERIOR!G224 -> 20485551
A6: 2 | B6: RESTROOM FINISHES | C6: ='REST ROOM'!H32 -> 2511037.1
A7: 3 | B7: HVAC | C7: ='HVAC SUMMARY'!E10 -> 4698772.7
A8: 4 | B8: LT ELECTRICAL WORKS | C8: =ELEC_Summary!C39 -> 8595785.9
A9: 5 | B9: UPS
A10: 6 | B10: FIRE SAFETY AND SECURITY SYSTEMS BOQ | C10: ='FAS AND PA SUMMARY'!E14 -> 6358576.8
A11: 7 | B11: PHE SYSTEM BOQ | C11: =PHE!C5 -> 2134411
B12: TOTAL ( EXCLUDING TAXES) | C12: =SUM(C5:C11) -> 44784135
B13: BOCW @1% extra.
B14: The above BOQ does not included the following
A15: 1 | B15: cost of power and water during construction
A16: 2 | B16: Cost of PCC screed
A17: 3 | B17: cost of ISP, EPABX & Network active components
A18: 4 | B18: cost of white goods and office equipment's , Kitchen equipements and appliances , Plants and planter boxes
A19: 5 | B19: cost of AV equipment's
A20: 6 | B20: cost of power feeders , AHU, Rising main, VFD, IBMS system and base building infrastructure works

Sheet INTERIOR
A1: INTERIOR WORKS
A2: S.N0 | B2: Description of Item | C2: Specification | D2: Unit | E2: Total Qty | F2: Rate ( Supply+ Installation) | G2: Amount | H2: JLL Remarks
C4: Notes:
C5: Below mentioned points are under Civil & Interior works vendors scope
C6: All unnecessary holes, gaps, openings in the walls, gyp ceiling / partitions, floor etc to be filled / closed by joinery vendor. AHU room and external wall / shaft to be sealed with Aerocon wall. All external wall gap to be sealed with Fire stop / Acoustical sealant as specified.
C7: Joinery vendor to be responsible for labor toilets – maintenance etc. (for all the agencies).
C8: Scrapping of flooring & cleaning the floor before carpet installation. (Floor to be wet mobbed & handed over to carpet installation team).
C9: Cleaning / painting of lobby & other builder areas which will be used by the agencies while execution.
C10: Touch up & finishing of all the existing doors which are handed over by builder while taking the possession.
C11: All unnecessary holes, gaps, openings in the walls, gyp ceiling / partitions, floor etc to be filled / closed by joinery vendor (in the AHU rooms, unnecessary opening of walls to be closed only by building wall & not using any other material like ply or gyp board etc).
C12: Housekeeping ( Including housekeeping on daily basis) to be part of your quotation and will not be paid extra. General housekeeping for all other packages to be in joinery vendor scope which is indicated as separate item in BOQ
C13: Electrical vendor to provide temp lighting for fitout execution period . Power junction boxes to be placed at every 10 meter distance with all safety norms recommended by the base builder /PM.
C14: Note: *Vendors are requested to visit the site and quote accordingly. *Vendor shall follow safety, barricading needs to be done as per PM /Architect instruction *Site should be left clean and broom finish once work complete and every day morning before 10AM *vendors are requested to visit the site and check the availability of water, power, service lift, debris dumping yard, lighting and quote accordingly for the works mentioned below. *Vendor to the check the work timings permitted from client / builder. *Quoted rates should includes shifting, lifting, loading, unloading of materials. *Quoted rates should includes scaffolding at all heights.
C15: All the Basic price exclusive of all the taxes,transportation charges and wastage etc..
... C26: The project timeline for completion is 75 days from the date of project kick-off. The vendor must provide a milestone schedule and resource details specific to this project.
A29: A | B29: DEMOLITION WORKS
A30: 1 | B30: Breaking of wall ( Toilet Work and other services) | C30: Demolition of existing wall of any thickness inclusive of removal of existing brick wall , Aerocon wall , RCC lintels, RCC slabs, cleaning etc, & disposal of debris from building premises as per base builders guidelines. ( Existing rest room walls and counter , internal plumbing lines to be removed and debris to be cleared from the building premises) | D30: Sqm | E30: 220 | F30: 371 | G30: =IFERROR(E30*F30,0) -> 81620
A31: 2 | B31: Breaking of Existing d base PCC screed | C31: Breaking of existing Tile Flooring and base PCC screed ( up to 70-90mm Avg depth) and cleaning & disposal of debris from building premises as per base builders guidelines | D31: Sqm | E31: 250 | F31: 318 | G31: =IFERROR(E31*F31,0) -> 79500
A32: 3 | B32: Floor grinding | C32: Existing screed floor (where the undulations are more than 3-5mm) to be levelled with floor grinding machine as per site condition. Cost inclusive of cleaning the screed floor and clear debris from building premises as per PM directions after completion of work. | D32: sqm | E32: 100 | F32: 265 | G32: =IFERROR(E32*F32,0) -> 26500
A33: B | B33: ANTI TERMITE TREATMENT | F33: 0 | G33: =IFERROR(E33*F33,0) -> 0
A34: 1 | B34: Anti Termite Treatment | C34: Providing Pest control and Anti-termite treatment by appointing a specialised agency as per the specifications mentioned by the Bureau of Indian Standards and Agencies specifications (whichever is higher), for General Civil, Plumbing,/ Drainage and timber/ Carpentry works, Gypsum related work, including a 5-year guarantee under suitable undertaking on stamp paper etc, complete as directed. (Mode of measurement to be on carpet-area of floor and not the area of surface treated.) . three rounds of pest control in all areas, first round to be executed at the time of commencement of fit-out, balance to be executed during fit-out as per PM directions. | D34: Sqm | E34: 1275 | F34: 90.1 | G34: =IFERROR(E34*F34,0) -> 114877.5
F35: 0 | G35: =IFERROR(E35*F35,0) -> 0
A36: C | B36: CIVIL & WET WORKS | F36: 0 | G36: =IFERROR(E36*F36,0) -> 0
A37: 1 | B37: POP punning | C37: Providing and applying POP punning to walls of avg. 12mm - 15mm thickness and above to line level and plumb; required punning to be undertaken and completed in workman-like manner, to ensure desired finishing standards, as per approval(s) of the Architects. The final finish should be of a uniform and neat finish to the satisfaction of the Architect. | D37: Sqm | E37: =300 -> 300 | F37: 445.2 | G37: =IFERROR(E37*F37,0) -> 133560
A38: 2 | B38: PCC Screed - 70-80 mm thk | C38: Providing and laying PCC screed up to 70-80 mm avg Ht. of cement concrete ratio 1:3:6 (1unit cement, 3units- sand, 6units- course aggregate) in necessary level & slope, finished smoothly with 6-8mm thick. Layer of cement mortar of 1:1 mix (1unit- cement, 1unit- Fine screened sand) in power float finish with proper curing by logging water or sprinkling water or by laying wet gunny bags etc complete as directed. The cost includes Scaffolding all ancillary works as per base builders guidelines and as per site condition . | D38: Sqm | E38: 250 | F38: 795 | G38: =IFERROR(E38*F38,0) -> 198750
A39: 3 | B39: Cement plaster ( To correct External wall undulations) | C39: Providing and applying in one coat, 15mm thick plaster on internal surface of RCC / brick/block walls/ column in cement mortar 1:4, finished rough to take on POP punning. Rate shall include for scaffolding, making grooves, sills, pattas, curing, surface preparation before the application of plaster, providing galvanized chicken mesh to a width of 150 mm at the junctions of masonry and concrete works including tying in position by using suitable nails / clamps / screws and as directed etc. complete at all levels. The contractor shall make good the grooves, pockets etc. after the scaffolding is removed.. Make - Coromandel, L&T, Steel : TATA/ Jindal | D39: Sqm | E39: 100 | F39: 424 | G39: =IFERROR(E39*F39,0) -> 42400
A40: 4 | B40: 150mm thick Aerocon wall - Intermediate wall - Future Exp Area & Handwash, Plate wash,server room,Battery ups room,Cafeteria | C40: Providing & constructing of AAC wall set in adhesive 5mm to 10mm thick / 1:4 cement mortar, inclusive of single coat rough Cement Plaster on both sides of wall in 1:4 , with minimum 2 nos of 6mm dia MS bars (Including tie bars) with 75mm height cement concrete at every 5 courses. Rates to include scaffolding, curing, RCC Lintel, at all heights, constructed to true line & plumb, etc., complete as per the Architect's instructions. Note : Rate should be inclusive of Masking for fixtures & wooden frames. Wall to be built till true ceiling. Rate to include RCC lintel (Lintel overlap length - 300mm to 450mm both ends -length vary based on door size) at necessary heights for doors (Lintel - door bottom & top). Curing of blocks to be done till the satisfactory of PM's. At the junction of RCC structure & block walls, Necessary Wall hacking and cement slurry to be considered on existing structure joints overlap and finished with POP Punning. * Density - 550-700 kg/m3 * Compressive strength - 30 - 50 kg/cm2 * Fire Resistant - Highly fire resistant & able to withstand the standard fire for 240minutes under load. * ISI Mark & Norms - products have ISI (BIS) norms and marking and are conforming to Indian standards. Blocks are conforming to IS 2185 (part 3). * Sound Absorption - Sound absorbency of air borne sound for 3" & 4" walls is 38 to 40 db. Mode of Measurement : Wall will be measured on one side (i.e. Total length of the wall x height of wall {LxH}) | D40: Sqm | E40: =58*4 -> 232 | F40: 2597 | G40: =IFERROR(E40*F40,0) -> 602504
A41: 5 | B41: 100mm thick Aerocon wall - AHU Opening closure | C41: Providing & constructing of AAC wall set in adhesive 5mm to 10mm thick / 1:4 cement mortar, inclusive of single coat rough Cement Plaster on both sides of wall in 1:4 , with minimum 2 nos of 6mm dia MS bars (Including tie bars) with 75mm height cement concrete at every 5 courses. Rates to include scaffolding, curing, RCC Lintel, at all heights, constructed to true line & plumb, etc., complete as per the Architect's instructions. Note : Rate should be inclusive of Masking for fixtures & wooden frames. Wall to be built till true ceiling. Rate to include RCC lintel (Lintel overlap length - 300mm to 450mm both ends -length vary based on door size) at necessary heights for doors (Lintel - door bottom & top). Curing of blocks to be done till the satisfactory of PM's. At the junction of RCC structure & block walls, Necessary Wall hacking and cement slurry to be considered on existing structure joints overlap and finished with POP Punning. * Density - 550-700 kg/m3 * Compressive strength - 30 - 50 kg/cm2 * Fire Resistant - Highly fire resistant & able to withstand the standard fire for 240minutes under load. * ISI Mark & Norms - products have ISI (BIS) norms and marking and are conforming to Indian standards. Blocks are conforming to IS 2185 (part 3). * Sound Absorption - Sound absorbency of air borne sound for 3" & 4" walls is 38 to 40 db. Mode of Measurement : Wall will be measured on one side (i.e. Total length of the wall x height of wall {LxH}) | D41: Sqm | E41: 10 | F41: 2491 | G41: =IFERROR(E41*F41,0) -> 24910
A42: 6 | B42: Self Levelling | C42: Providing and laying of Ardex Commercial levelling cementitious flooring system Surface preparation: Removing all existing weak, un sound CC floor to reach the strong substrate, cleaning the floor area to make it free from all contaminants and complete as per manufacturer's specification. Providing and applying Ardex P 51 primer to the base substrate and allow it to dry completely. Providing and mixing of CL 11, commercial levelling compound consisting of high quality special cement and selected fillers, with water at rate of 5.5-6 Ltr for 25 Kg bag of CL 11, installing at required 3mm to 5mm thickness using suitable pin rake trowel and notch trowel, finally rolling the surface with spike roller and allowed to dry completely, installing vinyl /LVT flooring as per client's requirement, etc and complete as per manufacturer's specification. [ The properties shall confirm to:- Bulk density of powder: Approx. 1.3 kg / Ltr; Weight of fresh mortar: Approx. 2.0 kg / Ltr; Working time: Approx. 25 min; Flow life: Approx. 15 min; Initial set (Vicat): Approx. 40 min; Final set (Vicat) Approx. 1 hr; Ball impact hardness: 6.5mm; Scratch hardness: 1.6mm; Compressive strength: 20 N / Up to 3mm thk self levelling) | D42: Sqm | E42: 925 | F42: 477 | G42: =IFERROR(E42*F42,0) -> 441225
A43: D | B43: PARTITION & PANELLING | F43: 0 | G43: =IFERROR(E43*F43,0) -> 0 | I43: Final Measurement Qty | J43: Amount
A44: 1 | B44: Double glazed partition - up to 2400mm - Black color frame -Double glass- Sandwitch Glass | C44: Supply and fixing of Double glazed Partition - GD-105W+ Geze Dela Partition system - Black Anodized: Supply and Fixing of Geze Dela System GD-105W+ i.e., Double glazed modular system consist of Aluminium section of 30x105x1.5mm thick. All sections duly anodised up to 20–25 microns with 6063-T6 grade and required accessories i.e. glass to glass aluminium I/H sections, T section & 90 degree L sections & Glass packing to adjust the floor level. Ceiling profile, Floor profile and wall profile are 30 mm visible face and 105 mm wide with 11.52mm laminated glass + Air Gap + 11.52 mm laminated glass with insertion of Thermoplastic gasket to adhere the glass firm & airtight. Make: GEZE / Eq from JEB / Alloy | D44: Sqm | E44: =40*2.6 -> 104 | F44: 14808.2 | G44: =IFERROR(E44*F44,0) -> 1540052.8 | H44: Alloy Make considered | I44: 92.18 | J44: =I44*F44 -> 1365019.9
A45: 2 | B45: Full Ht. Single Glazed partitions - 2400 mm Height . - - Black colour frame | C45: Supply and installation of full height Single glazed partitions formed out of the following components. Fabricating and Fixing of Glazed Partition with Anodized Aluminium Partition System of 100 x 25/35 mm thick section type placed both horizontally & vertically, Finish of frame : Anodized aluminium with black powder coated as approved by architect. The glazing to be formed out of 10 mm thick toughened glass as per details. The glass to be butt jointed with 2 to 3 mm edge chamfer & edge polishing all around. The butt joint of the glass shall have the aluminium profile & sealed using 3M glass to glass joint tape. Rate to include necessary 12mm thick MDF support finished with approved paint at the junction of false ceiling/solid partition & glass partition as per details .Rate to include 12mm thk MDF strip between modular frame and gypsum partitions all round and finished with paint as per details . Only visible glass surface will be measured and paid for this item. Fixing to be followed as per manufacturers specification. The height of glass partition to be 2.6mtr . Make : GEZE /JEB / Alloy | D45: QRO-Sqm | F45: 6148 | G45: =IFERROR(E45*F45,0) -> 0 | H45: Alloy Make considered
A46: 3 | B46: Partition above Glass partition - 100 mm thk (2+2 Layers Gypsum) - Gyproc - 100mm (50mmX25 mm Alu. Box section- 12.5mm thk plain board . Outer skin - 13 mm thk rigiroc Gypsum Board - 2+2 skin ( 100 mm thk) | C46: Providing and fixing baffle partition above glazed partition and doors of overall thickness of 100mm with the following components. The Frame work consist of 25mm x 50mm x 1.2mm thick extruded Aluminium box section framework at spacing not exceeding 600mm both ways (horizontal and vertical). The framework shall be secured at floor, structural ceiling and sill/ Lintel level. Framework to be secured to Floor / Walls / Columns / Ceiling / Beams using 75mm metal screws and dowels as per details.The framework to be cladded inner layer 12.5 mm thk plain Gypsum board & Outer layer of 13mm thick RIGIROC Gypboard, conforming to IS 2095 Part 1:2011, having flexural strength – {Longitudinal > 500N & transverse > 180N} on either side of the framing on either side of the framing from False ceiling level up to true ceiling level in line and level screw fixed with 25mm & 35mm drywall screws at 300mm centre to centre (150mm C/C at Floor & True Ceiling level) with staggered joints to avoid through joints. The board shall be jointed and finished to have a flushed look by filling and finishing with proprietary supplied jointing tape & compound and Two coats of Dry wall coat as per manufacturer's specification. Joints to be sand papered to achieve a smooth and seamless finish as per architects approval. Gypsum surface to be fully treated and finished to receive the Paint . Includes Putty , Primer etc., As an acoustic requirement, the cavity between the Boards shall be placed with 50mm thick Rock wool of density 48kg/m3, blanket wrapped in RP tissue suitably affixed to partition framework using where necessary GI binding wire, duct tape as indicated in the drawing. Note : Rock Wool with RP.Tissue packing of size 600 x 600mm/ 1200X600 mm . The junction of the partition with masonry & all penetration through the partition has to be treated with Hilti CP 606/ Hilti CP 620 / Pyroplex 2WT3IOP fire and acoustic sealant. Note : Aluminium section / plywood support to be provided wherever required for extra support to fix aluminium skirting, doors, storages, writing boards, glass boards, soft boards, projection screens, LED, paintings, artifacts, display, light fixtures, niches, glazed partition, mirrors, reader panel as per architects instructions. Meeting rooms with LED mounts to have sufficient aluminium & plywood support to house the bracket / mount. The partition cost should include Borer / Antitermite treatment for salwood and plywood as per architects instructions and dwg. Also cost to include making cut outs for AC ducts / Electrical works / Security systems / other services works / Switches / Sockets etc., complete. Wherever required by contractors and on completion of ducting, wiring work, the opening / cutouts to be closed as not to allow any transmission of sound or air as per architect's / PM's instructions. Partition installation to be done as per Gyproc/USG standard Installation process . One 4 pax meeting room full mock up to be done and approved by gyproc/USG Technical team /PM/ Architect . | D46: Sqm | E46: =68*1.6 -> 108.8 | F46: 4108.3639 | G46: =IFERROR(E46*F46,0) -> 446989.99
A47: 4 | B47: 100 mm thk Double Skin Gypsum partition - Make: Gyproc - Inner skin - 12.5mm thk plain board . Outer skin - 13 mm thk rigiroc Gypsum Board - 2+2 skin ( 100 mm thk) | C47: Providing and fixing 100 mm thk double skin gypsum partition - FRAME WORK: To be formed of cold rolled GI studs of size 48mm (0.5mm thk having one flange of 34mm and another flange of 36mm made of GI Steel), placed at 600mm centre to centre fixed onto the floor channels. The GI channels of size 50mm x 0.55mm (section thick) to be fixed on the floor to hold GI studs as per details. Also to have an additional 19mm thick ply supports /rigid salwood frame (wherever required) as spacer at the false ceiling level and as sub frames for doors and glazed openings as per details or as per architects instruction. INSULATION: As an acoustic requirement, contractor to affix 50mm thick Rock Wool of density 48 kg/m3 wrapped in RP tissues suitably affixed to partition framework using necessary GI binding wire, duct tape as indicated in the drawing. CLADDING: The inner layer to be finished with 12.5 mm thk tapered edge gypsum board (IS-2095 Part 1:2011) and the outer layer 13mm thk RIGIROC Gypsum board (from Finished floor level to till false ceiling) of in line and level screw fixed with 25mm drywall flat head screws @ 300mm c/c with staggered joints to avoid through joints and finished with proprietary supplied jointing tape and compound as per manufacturer's specification. Joints to be sand papered to achieve a smooth and seamless finish. Care must be taken that the plasterboards are raised 3mm from the floor and in this gap, chauking compound is injected, for successive layers and similarly for the ceiling channel/sections. Gypsum partition to be installed as per manufacturer specifications.To have 12mm ply to receive the skirting but Rate NOT to include skirting. The junction between partition & ceiling to be provided with 'L' shaped channel as per details. Finishes: Gypsum surface till the false ceiling on both sides - 2 coats of primer to be applied onto the gypsum surface. Surface to be smoothened using chalk putty as directed. Surfaces are then sandpapered to achieve a smooth surface and primer to be applied to receive paint . Make: GYPROC/USG . Note : Rock Wool with RP.Tissue packing of size 600 x 600mm / 600X1200 mm . The junction of the partition with masonry & all penetration through the partition has to be treated with Hilti CP 606/ Hilti CP 620 / Pyroplex 2WT3IOP fire and acoustic sealant. Gypsum surface to be fully treated and finished to receive the Paint . Includes Putty , Primer etc., Note : Aluminium section / plywood support to be provided wherever required for extra support to fix aluminium skirting, doors, storages, writing boards, glass boards, soft boards, projection screens, LED, LED, paintings, artifacts, display, light fixtures, niches, glazed partition, mirrors, reader panel as per architects instructions. Meeting rooms with LED mounts to have sufficient aluminium & plywood support to house the bracket / mount. The partition cost should include Borer / Ant termite treatment for salwood and plywood as per architects instructions and dwg. Also cost to include making cut outs for AC ducts / Electrical works / Security systems / other services works / Switches / Sockets etc., complete. Wherever required by contractors and on completion of ducting, wiring work, the opening / cut-outs to be closed as not to allow any transmission of sound or air as per architect's / PM's instructions. Partition installation to be done as per USG/ Gyproc standard Installation process . One mock up to be done and approved by gyproc/USG Technical team /PM/ Architect . Gypsum surface to be fully treated and finished to receive the Paint . One 4 pax meeting room full mock up to be done and approved by gyproc/USG Technical team /PM/ Architect . | D47: Sqm | E47: =70*4 -> 280 | F47: 3720.2012 | G47: =IFERROR(E47*F47,0) -> 1041656.3
A48: 5 | B48: Single Skin Gypsum partition - Store room - Plain Gypsum Board - 75mm thk (1+1) | C48: Providing and fixing 75 mm thk single skin gypsum partition - FRAME WORK: To be formed of cold rolled GI studs of size 48mm (0.5mm thk having one flange of 34mm and another flange of 36mm made of GI Steel), placed at 600mm centre to centre fixed onto the floor channels. The GI channels of size 50mm x 0.55mm (section thick) to be fixed on the floor to hold GI studs as per details. Also to have an additional 19mm thick ply supports /rigid salwood frame (wherever required) as spacer at the false ceiling level and as sub frames for doors and glazed openings as per details or as per architects instruction. INSULATION:As an acoustic requirement, contractor to affix 50mm thick glass wool of density 48kg/m3 wrapped in RP tissues suitably affixed to partition framework using necessary GI binding wire, duct tape as indicated in the drawing.. CLADDING: The framework to be cladded on both sides with single layer (from Finished floor level to till false ceiling) of 12.5 mm thk tapered edge gypsum board (IS-2095 Part 1:2011) in line and level screw fixed with 25mm drywall flat head screws @ 300mm c/c with staggered joints to avoid through joints and finished with proprietary supplied jointing tape and compound as per manufacturer's specification. Joints to be sand papered to achieve a smooth and seamless finish. Care must be taken that the plasterboards are raised 3mm from the floor and in this gap, chauking compound is injected, for successive layers and similarly for the ceiling channel/sections. Gypsum partition to be installed as per manufacturer specifications.To have 12mm ply to receive the skirting but Rate NOT to include skirting. The junction between partition & ceiling to be provided with 'L' shaped channel as per details. FInishes: Gypsum surface till the false ceiling on both sides - 2 coats of primer to be applied onto the gypsum surface. Surface to be smoothened using chalk putty as directed. Surfaces are then sandpapered to achieve a smooth surface and cost to include 3 coats of Plastic emulsion Paint of approved shade to be applied. Make: GYPROC / USG . Note : Glass Wool with RP.Tissue packing of size 600 x 600mm. The junction of the partition with masonry & all penetration through the partition has to be treated with Hilti CP 606/Pyroplex 2WT3IOP fire and acoustic sealant. Note : Aluminium section / plywood support to be provided wherever required for extra support to fix aluminum skirting, doors, storages, writing boards, glass boards, soft boards, projection screens, LCD, Plasma, paintings, artifacts, display, light fixtures, niches, glazed partition, mirrors, reader panel as per architects instructions. Meeting rooms with LCD mounts to have sufficient aluminium & plywood support to house the bracket / mount. The partition cost should include Borer / Antitermite treatment for salwood and plywood as per architects instructions and dwg. Also cost to include making cut outs for AC ducts / Electrical works / Security systems / other services works / Switches / Sockets etc., complete. Wherever required by contractors and on completion of ducting, wiring work, the opening / cutouts to be closed as not to allow any transmission of sound or air as per architect's / PM's instructions. | D48: Sqm | E48: 25 | F48: 2161.3888 | G48: =IFERROR(E48*F48,0) -> 54034.72
A49: 6 | B49: Fire rated Gypsum partition ( Server , UPS and Battery Room) | C49: 122mm thick - C-stud partition which includes double layer of tapered edge 12.5mm thick - Fireline of size 1219x2438mm is screw fixed to C-stud. 70x0.5mm C-stud placed at 610mm c/c in 72x0.5mm Floor and Ceiling channel. Floor & Ceiling channel is anchored to the floor & true ceiling using - Rawl plug Ø8x45mm /Hilti X-GN20MX anchor fasteners at 600mm c/c in zig zag manner. Floor channel to be wrapped with 70μ Self Adhesive LDPE moisture barrier film to further improve corrosion resistance performance. 12.5mm thick - Fireline board strip of 72mm width is placed between ceiling channel and RCC ceiling slab when deflection is more than 10mm & fire rating is more than 30min. Noggin channel of 70x0.5mm width has to be provided at the horizontal joints of the two boards. First layer of - boards to be screw fixed with - Drywall screws of 25mm at minimum spacing of 600mm at centre and 600mm at periphery. Second layer to be screw fixed - Drywall screws of 35mm at minimum spacing of 300mm at centre and 300mm at periphery. 50mm glasswool slab of density 24kg/m³ shall be placed in metal framework. Glasswool holding clip should be used to hold glasswool slab in its position. Finally square and tapered edges of the boards are to be jointed and finished so as to have a flush look which includes filling and finishing with - Pro-Fill Jointing compound, - Joint Paper tape or fibre tape. The junction of the partition with masonry & all penetration through the partition has to be treated with Hilti/Pyroplex fire and acoustic sealant. All other detailing and specifications to be followed as per approved shop drawing. Cost Includes 12mm thk bison board backing inside server room to mount Power panels and Distribution boards. The junction of the partition with masonry & all penetration through the partition has to be treated with Hilti CP 606/Pyroplex 2WT3IOP fire and acoustic sealant. Make- Gyproc/ USG - 2 Hr fire line board and sections . All detailing and specifications to be followed as per approved drawing of Gyproc. Contractors should strictly adehre manufacturers guidelines for installation . After completion of work , Manufacturers technical team to inspect the installation and provide certificate for 2HR fire rating . Make: GYPROC / Eq. USG | D49: Sqm | E49: 10 | F49: 4134.2414 | G49: =IFERROR(E49*F49,0) -> 41342.414
A50: 7 | B50: Aluminium frame work - 50X50 mm - Only Frame work | C50: Providing and fixing partitions consisting of 50mm x 25mm x 1.2mm Aluminum sections framework with all necessary reinforcements required of wood/aluminum, at spacing not exceeding 600mm bothways. ( horizontal & vertical) Partition framework to be provided with bracing/angular supports & secured to structural ceiling & nearest structural member using 75mm galvanized metal screws & wooden dowels. Cost to include provision of cut outs for duct and cable tray routing above ceiling at locations indicated on the drawings or as instructed by the architects. | D50: Sqm | E50: 25 | F50: 1296.9565 | G50: =IFERROR(E50*F50,0) -> 32423.913 | H50: Aluminium frame work - 50X25 mm as per the query response.
A51: 8 | B51: Aluminium frame work - 25X25 mm - Only Frame work | C51: Providing and fixing partitions consisting of 25mm x 25mm x 1.2mm Aluminum sections framework with all necessary reinforcements required of wood/aluminum, at spacing not exceeding 600mm bothways. ( horizontal & vertical) Partition framework to be provided with bracing/angular supports & secured to structural ceiling & nearest structural member using 75mm galvanized metal screws & wooden dowels. Cost to include provision of cut outs for duct and cable tray routing above ceiling at locations indicated on the drawings or as instructed by the architects. | D51: Sqm | E51: 10 | F51: 1102.8751 | G51: =IFERROR(E51*F51,0) -> 11028.751
A52: 9 | B52: One skin Gypsum on Aluminium/ GI frame work | C52: Installaing one skin gypsum board on Aluminium / GI frame work . Only Gypsum board supply and installation cost to be quoted (Excluding Frame work) | D52: Sqm | E52: 10 | F52: 410.65155 | G52: =IFERROR(E52*F52,0) -> 4106.5155
A53: 10 | B53: Two skins Gypsum on Aluminium/ GI frame work | C53: Installaing two skins gypsum board on Aluminium / GI frame work . Only Gypsum board supply and installation cost to be quoted (Excluding Frame work) | D53: Sqm | E53: 10 | F53: 821.3031 | G53: =IFERROR(E53*F53,0) -> 8213.031
F54: 0
A55: E | B55: DOORS | F55: 0
A56: 1 | B56: 1050x 2600 mm Aluminium Door Frame & Style Shutter - Double Glazed Stile Shutter Door(Cabin and Conference) | C56: Door Jamb : 100mm X 25mm Proprietary anodised aluminium section with anodised finish Action : Single Swing . 100X25X2600 mm Ht . Door frame to be grouted to the PCC Floor with suitable Brackets as per manufacturers specification. Door vertical frame to be fixed to the adjucent gypsum partition with suitable Ply backing as per manufacturers guidelines . Shutter Construction : 6mm +6 mm Double glazed Toughened Glass with 70 mm x 45mm anodized aluminium frame stile shutter of size 1050mm X 2600mm Hinge Type : 5 Nos Hinges . Dorma / Geze 5" Flush suitable to style shutte Lockset : Dorma 952 Narrow style lock / GEZE 8134002 Door Handle : D Type offset handle 450 mm high Door Closer: - Dorma TS 91 cam action Door Closer with hold-open slide arm / GEZE TS 3000 V; Door Stopper : Dorma / Geze Seals: Drop down sealsSecurity system: provide provision for magnetic access control. Door frame make: Alloy / Geze / JEB Glass- Saint Gobain . | D56: Nos | E56: 2 | F56: 98050 | G56: =IFERROR(E56*F56,0) -> 196100 | H56: Door Frame - Alloy make considered Hardware - Gaze make considered | I56: 2 | J56: =I56*F56 -> 196100
A57: 2 | B57: 1200x 2550 mm Aluminium Door Frame & Style Shutter | C57: Door Jamb : 100 /105 mm X 25 mm Proprietary anodised aluminium section with black powder coated finish.. Black anodised . Action : Single Swing . 100X25X2550 mm Ht . Door frame to be grouted to the PCC Floor with suitable Brackets as per manufacturers specification. Door vertical frame to be fixed to the adjacent gypsum partition with suitable Ply backing as per manufacturers guidelines . Black anodised Shutter Construction : 10mm thick Toughened Glass with 70 mm x 45mm anodized aluminium frame stile shutter of size 1200mm X 2550mm . Black anodised Hinge Type : 5 Nos Hinges . Dorma / Gaze 5" Flush suitable to style shutter Lockset : Dorma 952 Narrow style lock / GEZE 8134002 Door Handle : D Type offset handle 450 mm high . Black anodised Door Closer: - Dorma TS 91 cam action Door Closer with hold-open slide arm / GEZE TS 3000 V; Black anodised Door Stopper : Geze / Dorma Seals: Drop down seals Dorma / Geze - Gap b.w finished floor and Door shutter should not exceed 4mm . Security system: provide provision for magnetic access control. Door frame and shutter make: GEZE / Alloy / JEB .. Glass- Saint Gobain . . Note: Individual measurements to be taken for all doors and shop dwg to be submitted for approval . One Mock up to be done with all hardwares with in 7 days from the project start date . | D57: Nos | E57: 1 | F57: 59667.4 | G57: =IFERROR(E57*F57,0) -> 59667.4 | H57: Door Frame - Alloy make considered Hardware - Gaze make considered | I57: 1 | J57: =I57*F57 -> 59667.4
A58: 3 | B58: 1050x 2550 mm Aluminium Door Frame & Style Shutter | C58: Door Jamb : 100mm X 25mm Proprietary anodised aluminium section with black powder coated finish.. Black anodised Action : Single Swing . 100X25X2550 mm Ht . Door frame to be grouted to the PCC Floor with suitable Brackets as per manufacturers specification. Door vertical frame to be fixed to the adjacent gypsum partition with suitable Ply backing as per manufacturers guidelines . Black anodised Shutter Construction : 10mm thick Toughened Glass with 70 mm x 45mm anodized aluminium frame stile shutter of size 1050mm X 2550mm . Black anodised Hinge Type : 5 Nos Hinges . Dorma / Gaze 5" Flush suitable to style shutter Lockset : Dorma 952 Narrow style lock / GEZE 8134002 Door Handle : D Type offset handle 450 mm high . Black anodised Door Closer: - Dorma TS 91 cam action Door Closer with hold-open slide arm / GEZE TS 3000 V; Black anodised Door Stopper : Geze / Dorma Seals: Drop down seals Security system: provide provision for magnetic access control. Door frame and shutter make: GEZE / Alloy / JEB .. Glass- Saint Gobain . | D58: Nos | E58: 8 | F58: 58607.4 | G58: =IFERROR(E58*F58,0) -> 468859.2 | H58: Door Frame - Alloy make considered Hardware - Gaze make considered | I58: 8 | J58: =I58*F58 -> 468859.2
A59: 4 | B59: 900x 2550 mm Aluminium Door Frame & Style Shutter | C59: Door Jamb : 100mm X 25mm Proprietary anodised aluminium section with black powder coated finish.. Black anodised Action : Single Swing . 100X25X2550 mm Ht . Door frame to be grouted to the PCC Floor with suitable Brackets as per manufacturers specification. Door vertical frame to be fixed to the adjacent gypsum partition with suitable Ply backing as per manufacturers guidelines . Black anodised Shutter Construction : 10mm thick Toughened Glass with 70 mm x 45mm anodized aluminium frame stile shutter of size 900mm X 2550mm . Black anodised Hinge Type : 5 Nos Hinges . Dorma / Gaze 5" Flush suitable to style shutter Lockset : Dorma 952 Narrow style lock / GEZE 8134002 Door Handle : D Type offset handle 450 mm high . Black anodised Door Closer: - Dorma TS 91 cam action Door Closer with hold-open slide arm / GEZE TS 3000 V; Black anodised Door Stopper : Geze / Dorma Seals: Drop down seals Security system: provide provision for magnetic access control. Door frame and shutter make: GEZE / Alloy / JEB .. Glass- Saint Gobain . | D59: Nos | E59: 2 | F59: 58607.4 | G59: =IFERROR(E59*F59,0) -> 117214.8 | H59: Door Frame - Alloy make considered Hardware - Gaze make considered | I59: 3 | J59: =I59*F59 -> 175822.2
A60: 5 | B60: 900 x 2550 mm Aluminium Door Frame & Flush door with Full Ht (Store room-01,02 and IT Store) | C60: Door Jamb : 100mm X 25mm Proprietary anodised aluminium section with black powder coated finish.. Black anodised Action : Single Swing . 100X25X2550 mm Ht . Door frame to be grouted to the PCC Floor with suitable Brackets as per manufacturers specification. Door vertical frame to be fixed to the adjacent gypsum partition with suitable Ply backing as per manufacturers guidelines . Black anodised Shutter Construction : 32mm thk Flush door in laminate finish with vision panel as per detail dwg Hinge Type : 4 Nos Hinges . Dorma / Gaze 5" Flush suitable to style shutter Lockset : Dorma 952 Narrow style lock / GEZE 8134002 Door Handle : D Type offset handle 450 mm high . Black anodised Door Closer: - Dorma TS 71 Door Closer / Eq GEZE Door Stopper : NA Vision panel : 300 x200mm Security system: provide provision for magnetic access control. Door frame and shutter make: GEZE / Alloy / JEB .. Glass- Saint Gobain . | D60: Nos | E60: 3 | F60: 49979 | G60: =IFERROR(E60*F60,0) -> 149937 | H60: Door Frame - Alloy make considered Hardware - Gaze make considered | I60: 2 | J60: =I60*F60 -> 99958
A61: 6 | B61: 750 x 2550 mm Aluminium Door Frame & Flush door with Full Ht | C61: Door Jamb : 100mm X 25mm Proprietary anodised aluminium section with black powder coated finish.. Black anodised Action : Single Swing . 100X25X2550 mm Ht . Door frame to be grouted to the PCC Floor with suitable Brackets as per manufacturers specification. Door vertical frame to be fixed to the adjacent gypsum partition with suitable Ply backing as per manufacturers guidelines . Black anodised Shutter Construction : 32mm thk Flush door in laminate finish with vision panel as per detail dwg Hinge Type : 4 Nos Hinges . Dorma / Gaze 5" Flush suitable to style shutter Lockset : Dorma 952 Narrow style lock / GEZE 8134002 Door Handle : D Type offset handle 450 mm high . Black anodised Door Closer: - Dorma TS 71 Door Closer / Eq GEZE Door Stopper : NA Vision panel : 300 x200mm Security system: provide provision for magnetic access control. Door frame and shutter make: GEZE / Alloy / JEB .. Glass- Saint Gobain . | D61: Nos | E61: 1 | F61: 49979 | G61: =IFERROR(E61*F61,0) -> 49979 | H61: Door Frame - Alloy make considered Hardware - Gaze make considered | I61: 1 | J61: =I61*F61 -> 49979
A62: 7 | B62: FRD - 1200x 2400mm (Server /UPS ) | C62: Providing and fixing of 2 Hr Fire rated metal door Single shutter made of 1.6mm thk galvanized steel frames of size 140x57 mm with rebate and 1.2mm thk galvanized steel of 46mm thk double skin shutter with necessary infill materials and glue/sealant fixed in all respect including poly urethane paint with protective film coating and all accessories like hinges, lock, handles, door closers, with 6mm thk Toughened fire glass vision panel (without mesh) etc., as per the specifications. (Make - Dorma) (Note - Before ordering Cross Check the site for Dimension & get the approval from the architect with shop drawing) Make : RNB / Shakthi /HADID . make: Door Closer - Dorma TS 91 cam action Door Closer with hold-open slide arm / GEZE TS 3000 V; Handle: Dorma / Geze - 450 mm High "D" type Handle; Hinges - Dorma / Geze suitable to 2HR fire door ; | D62: Nos | E62: 2 | F62: 57240 | G62: =IFERROR(E62*F62,0) -> 114480 | H62: Shakthi Make considered | J62: =I62*F62 -> 0
A63: 8 | B63: FRD - 1050x 2100mm ( Battery room) | C63: Providing and fixing of 2 Hr Fire rated metal door Single shutter made of 1.6mm thk galvanized steel frames of size 140x57 mm with rebate and 1.2mm thk galvanized steel of 46mm thk double skin shutter with necessary infill materials and glue/sealant fixed in all respect including poly urethane paint with protective film coating and all accessories like hinges, lock, handles, door closers, with 6mm thk Toughened fire glass vision panel (without mesh) etc., as per the specifications. (Make - Dorma) (Note - Before ordering Cross Check the site for Dimension & get the approval from the architect with shop drawing) Make : RNB / Shakthi/ HADID . make: Door Closer - Dorma TS 91 cam action Door Closer with hold-open slide arm / GEZE TS 3000 V; Handle: Dorma / Geze - 450 mm High "D" type Handle; Hinges - Dorma / Geze suitable to 2HR fire door ; | D63: Nos | E63: 1 | F63: 55120 | G63: =IFERROR(E63*F63,0) -> 55120 | H63: Shakthi Make considered | J63: =I63*F63 -> 0
A64: 9 | B64: FRD - 1000x 2400mm ( Fire exit) | C64: Providing and fixing of 2 Hr Fire rated metal door Single shutter made of 1.6mm thk galvanized steel frames of size 140x57 mm with rebate and 1.2mm thk galvanized steel of 46mm thk double skin shutter with necessary infill materials and glue/sealant fixed in all respect including poly urethane paint with protective film coating and all accessories like hinges, lock, handles, door closers, with 6mm thk Toughened fire glass vision panel (without mesh) etc., as per the specifications. (Make - Dorma) (Note - Before ordering Cross Check the site for Dimension & get the approval from the architect with shop drawing) Make : RNB / Shakthi/HADID . make: Door Closer - Dorma TS 91 cam action Door Closer with hold-open slide arm / GEZE TS 3000 V; Handle: Dorma / Geze - 450 mm High "D" type Handle; Hinges - Dorma / Geze suitable to 2HR fire door ; | D64: Nos | E64: 1 | F64: 55120 | G64: =IFERROR(E64*F64,0) -> 55120 | H64: Shakthi Make considered | J64: =I64*F64 -> 0
A65: 10 | B65: Aluminium profile Boxing | C65: Providing and fixing 0f 200 X100/105 mm Aluminium boxing to install access reader / switches as per manufacturers specification. Boxing to be installed adjacent to door frame as per detail design . Make: GEZE /JEB /Alloy | D65: Nos | E65: 12 | F65: 21681.818 | G65: =IFERROR(E65*F65,0) -> 260181.82 | H65: Alloy Make considered | I65: 14 | J65: =I65*F65 -> 303545.45
A66: 11 | B66: Firerated shaft shutters | C66: Replacing of existing Laminate shutters with fire-rated shutters. | D66: Nos | E66: 4 | F66: 16430 | G66: =IFERROR($F66*E66,0) -> 65720 | H66: Size: 1200 X1200MM (As per the query response)
A67: 12 | B67: Reception Main Entry door - 2 HR FIRE RATED GLASS DOOR _ SAINTGOBAIN | C67: Providing and fixing of tested fully glazed steel fire rated double leaf door with 120 minutes of integrity and radiation control and partial insulation (EW=120 and EI=20) with symmetrical (Bi-Directional) fire protection. The system shall be tested as per EN 1634-1 standard in an accredited international laboratory. The glass shall be CONTRAFLAM LITE (14mm) clear, non-wired, toughened, interlayered, 120 minutes fire-rated glass for integrity and radiation control (EW 120) and insulation (I 20) with a light transmission of 86% and a sound reduction of 38 dB and manufactured in UL & TUV audited facility and including UL-EU Certification and compliant to class 1(B)1 category of Impact Resistance as per EN 12600. The glass shall be tested for 5000 hours of UV resistance as per EN ISO 12543-4. The glass shall be EPD (Environmental Production Declaration) verified in accordance to EN 15804 and ISO 14025 in which its life cycle assessment is performed considering Cradle to Gate system boundaries. The glass must produce a recycled content declaration committing to a pre-consumer cullet of up to 11% and post-consumer cullet less than 1%. The glass shall provide bi-directional (symmetrical) fire protection. The door frames are manufactured from 1.6 mm galvanized steel sheet pressed to form a profile of 35 mm x 60 mm on the vertical sides and 50 x 60 mm on the horizontal side. The door shutter would have a top rail and side rail 60 mm x 60 mm and a bottom rail of 110 mm x 60 mm. The glass should be held in its place with the help of 1.6 mm GI beading and a special ceramic tape with cross section of 5 x 20 mm as per the test evidence. Beading should be attached using 4 mm x 35 mm SS screws at a distance of 75 mm from the edges and 150 mm c/c henceforth. The shutters should be fixed to the frame using Dorma SS Ball Bearing Hinges of size 100 mm x 89 mm and 3 mm thickness or equivalent. The door should be fitted with necessary hardware including TS 3000V or TS 73V, lock, 900mm offset handle and tower bolt from Dorma / Geze / equivalent. The test report will be considered valid only if it contains the stamp and signature of the authorized signatory from Saint-Gobain Glass India Ltd | F67: 0 | G67: =IFERROR($F67*E67,0) -> 0 | H67: Fire Rated Glass - Vetrotech Saint-Gobain make considered. Hardware - Gaze make considered.
A68: A | B68: Size - 2000 X2400 mm | C68: Door size- 2000 X 2600 mm ( Double Shutter) | D68: Nos | E68: 1 | F68: 432533.98 | G68: =IFERROR(E68*F68,0) -> 432533.98 | I68: 1 | J68: =I68*F68 -> 432533.98
A69: B | B69: Size - 1200 X2400 mm | C69: Door size- 1200 X 2600 mm ( Single Shutter) | D69: QRO-Nos | F69: 268183.18 | G69: =IFERROR(E69*F69,0) -> 0
A70: 13 | B70: 120 MINUTES FULLY GLAZED VDS® FIRE RESISTANT FIXED NON LOAD BEARING PARTITION | C70: 120 MINUTES FULLY GLAZED VDS® FIRE RESISTANT FIXED NON LOAD BEARING PARTITION SYSTEM PROVIDING INTEGRITY AND RADIATION CONTROL (EW) Supply and installation of tested Vetrotech Saint-Gobain VDS® fully glazed fire rated fixed partition with 120 minutes of integrity and radiation control (EW 120) with symmetrical (bi-directional) fire protection. The frames shall be made with imported cold rolled profiles. The frames are cold rolled from 1.5 mm steel sheet to form a profile of 50 mm x 50 mm on all sides. The system shall be tested as per EN 1364-1 in an international accredited laboratory. The glass should be CONTRAFLAM LITE (14mm) clear, non-wired, toughened, interlayered, 120 minutes fire-rated glass for integrity and radiation control (EW 120) and insulation (I 20) with a light transmission of 86% and a sound reduction of 38 dB and manufactured in UL & TUV audited facility and including UL-EU Certification (File number R38101) and compliant to class 1(B)1 category of Impact Resistance as per EN 12600. The glass shall be tested for 5000 hours of UV resistance as per EN ISO 12543-4. The glass shall be EPD (Environmental Production Declaration) verified in accordance to EN 15804 and ISO 14025 in which its life cycle assessment is performed considering Cradle to Gate system boundaries. The glass must produce a recycled content declaration committing to a pre-consumer cullet of up to 11% and post-consumer cullet less than 1%. The glass shall provide bi-directional (symmetrical) fire protection. The glass should be held in its place with the help of 1.5 mm cold rolled steel beading and Kerafix 2000 ceramic tape with cross section of 4 x 15 mm as per the test evidence. The beading shall be clipped on using stainless steel self-tapping screws fixed at a distance of 70 mm from the edges and 150 mm c/c henceforth. The glass panes are to be supported on noncombustible 6 mm thick calcium silicate setting blocks. The maximum glazing size shall be as per the test certification. The profile has to be fixed to the supporting construction by means of M10 or bigger steel bolts at every 150 mm from the edges and every 500 mm (approx.) c/c. The partitions shall offer C4 level of wind resistance when tested as per EN12211 and shall provide class 4 level of air permeability as per EN 1026. The partitions shall also be tested for class 5 of impact resistance when tested as per EN 13049. The partitions shall also be tested for class 4 level of mechanical strength when tested as per EN13115. The partitions shall have water tightness level of 8A when tested as per EN 1027. Test evidence: The test report will be considered valid only if it contains the stamp and signature of the authorized signatory from Vetrotech Saint-Gobain. | D70: QRO-Nos | F70: 64185.12 | G70: =F70*E70 -> 0 | H70: Fire Rated Glass - Vetrotech Saint-Gobain make considered. Hardware - Gaze make considered.
A71: F | B71: CEILING WORKS | F71: 0
A72: 1 | B72: Modular false ceiling - 0.5/0.6 NRC ( Store rooms , Server, UPS , Battery , BMS ) | C72: Providing and fixing in true horizontal level modular false ceiling using hot dipped galvanised steel sections. Exposed surface chemically cleaned capping prefinished in baked polyester paint. Shallotte/ Black Reveal grids and approved Shadow line wall angle of size 3000mmx19mmx19mm used in the periphery of the ceiling fixed to the partition, R.C.C.columnand walls using screws at 600mm c/c. Main runner of size15mmx32mmx3000mm suspended at 1200 c/c, using 2mm/3mm dia.GI butterfly wire hanger safely fixed to the structural soffit of the RCC slab using 6mm anchor fastener at every 1200mm c/c (max.) and 1200mm long cross tee of size 15mmx27mmx1200mm to be interlocked between main runner at 600mm c/c (max.) to form a grid of 600mx600mm. Tile to have 0.55 / .6 NRC sound. Tile sample to be approved by ARCHITECT WHILE quoting. Make - Armstrong- Dune max / Eq in Daiken . | D72: Sqm | E72: 60 | F72: 1643 | G72: =IFERROR(E72*F72,0) -> 98580
A73: 2 | B73: Modular false ceiling - 0.9 NRC | C73: Providing and fixing in true horizontal level modular false ceiling using hot dipped galvanised steel sections. Exposed surface chemically cleaned capping prefinished in baked polyester paint. Shallotte/ Black Reveal grids and approved Shadow line wall angle of size 3000mmx19mmx19mm used in the periphery of the ceiling fixed to the partition, R.C.C.columnand walls using screws at 600mm c/c. Main runner of size15mmx32mmx3000mm suspended at 1200 c/c, using 2mm/3mm dia.GI butterfly wire hanger safely fixed to the structural soffit of the RCC slab using 6mm anchor fastener at every 1200mm c/c (max.) and 1200mm long cross tee of size 15mmx27mmx1200mm to be interlocked between main runner at 600mm c/c (max.) to form a grid of 600mx600mm. Tile to have .9 NRC sound. Tile sample to be approved by ARCHITECT WHILE quoting. Make - Armstrong- 0.9 NRC - Mineral Fibre Tile - Sample to be submitted for Approval | D73: Sqm | E73: 380 | F73: 1961 | G73: =IFERROR(E73*F73,0) -> 745180
A74: 3 | B74: Metal grid ceiling(Handwash and plate wash) | C74: Providing and fixing 600X600 mm Aluminium perforated false ceiling using 24 mm GI & steel grid . Basic Price -1800 / sqm Nextior / Armstrong / Fameline | D74: Sqm | E74: 45 | F74: 2301.048 | G74: =E74*F74 -> 103547.16
A75: 4 | B75: Gypsum false ceiling | C75: Providing and fixing Gypsum False Ceiling which includes G.I.Perimeter Channels of size .55mm thick (having One Flange of 20mm. and another flange of 30mm and a web of 27mm) along with perimeter of ceiling, screw fixed to brick wall / partition with the help of Nylon sleeves and screws at 610mm centres. Then suspending G.I. intermediate channels of size 45mm (0.9mm thick with 2 flanges of 15mm each) from the soffit at 1220mm centres with ceiling angle of width 25mm X 10mm X 0.55mm thick fixed to soffit with G.I. cleat and steel expansion fasteners. Ceiling section of 0.55mm thick having knurled web of 51.5mm and 2 flanges of 26mm each with lips of 10.5mm are then fixed to the intermediate channel with the help of connecting clips and in direction perpendicular to the intermediate channel at 450 mm centres Cost inclusive of one coat of primer and 3 coats of emulsion paint. Make of Stud & Channel - Gyproc /USG . Make of gypsum - Gyproc/USG . Installation to be done as per manufacturers installation guidelines . Cost includes 150 mm high vertical band and cove light provision. | D75: Sqm | E75: 400 | F75: 1272 | G75: =IFERROR(E75*F75,0) -> 508800
A76: 5 | B76: Gyp false ceiling for Open ceiling area - (to be fixed at True ceiling to achieve smooth finish) | C76: Providing and fixing Gypsum False Ceiling which includes 12.5 mm thk gypsum board , GI Ceiling section to be fixed to the true ceiling with suitable frame work. sections to be fixed at 600 mm c/c centre as per dwg . Cost inclusive of providing scaffolding for open office ceiling and one coat of primer and 3 coats of approved emulsion paint. Note : Marking of Electrical, Fire Alarm & Air-conditioning & co-ordination with marking of fixtures to be considered. Necessary cut-outs shall be provided for taking of light cables, Fire and safety cables which shall be neatly finished after fixing of equipment's thereby leaving no gaps, etc., complete Measurement to be along the horizontal surface of the ceiling Make Frames : Gyproc /USG ; make Gypsum - Gyproc /USG | D76: Sqm | E76: 50 | F76: 1272 | G76: =IFERROR(E76*F76,0) -> 63600
A77: 6 | B77: Knauf - Danoline- Random perforation ceiling | C77: Providing and fixing suspended false ceiling-Knauf Danoline - Strato panel random dia perforated G8/15/20 of size 600x600x12.5mm: Regular round perforation which includes providing and fixing GI perimeter channels of size 0.55 mm. Thk. having one flange of 20 mm and another flange of 30 mm and web of 27 mm along the perimeter of the ceiling, screw fixed to brick wall/ partition with help of nylon sleeves and screws, at 610 mm centers. The suspended GI intermediate channels of size 45 mm,0.9mm thk with two flanges of 15 mm each from the soffit at 900 mm centers with ceiling angle of width 25mm x 10mm x 0.55mm thk fixed to soffit with GI cleat and steel expansion fasteners. Ceiling section of 0.55 mm thk fixed to the intermediate channels with help of connecting clips and in direction perpendicular to the intermediate channel with centers of 333 mm perforated gypboard is then screw fixed to ceiling section with 25 mm dry wall screws at 300 mm centers. Screw fixing is done mechanically either with screw driver or drilling machine with suitable attachment. (Cost to be quoted inclusive of wastages- Pl refer Dwg) . Make- Knauf | D77: Sqm | E77: 40 | F77: 3021 | G77: =IFERROR(E77*F77,0) -> 120840
A78: 7 | B78: Axiom Trim | C78: Providing & fixing 100mm wide axiom - extruded aluminium trim in curved length, finished powder coated in approved shade, installed complete with connector clips and C/C grid suspension distance all as per manufacturer's specifications. Make - USG, Arm strong, Daiken, Fameline | D78: Rmt | E78: 25 | F78: 583 | G78: =IFERROR(E78*F78,0) -> 14575
A79: 8 | B79: Baffle ceiling - Made of 12mm thk Eco board | F79: 0
B80: Huddle Space - Plain Eco board | C80: 12mm thk , 150 mm High Eco board baffle ceiling , c/c gap 100 mm to be suspended from Gypsum ceiling / True ceiling with suitable frame support . Cost includes necessary black color GI frame support and ply backing on Gypsum ceiling to hold the frame work . | D80: Sqm | E80: 5 | F80: 12076.175 | G80: =IFERROR(E80*F80,0) -> 60380.873 | H80: Basic price Rs.980/Sft considered as per the query response.
B81: Huddle Space - Printed Eco board | C81: 12mm thk , 200 mm High Printed Eco board baffle ceiling , c/c gap 100 mm to be suspended from Gypsum ceiling / True ceiling with suitable frame support . Cost includes necessary black color GI frame support and ply backing on Gypsum ceiling to hold the frame work . | D81: Sqm | E81: 25 | F81: 12076.175 | G81: =IFERROR(E81*F81,0) -> 301904.37 | H81: Basic price Rs.980/Sft considered as per the query response.
B82: Café - Printed Eco board | C82: 12mm thk , 300 mm High Printed Eco board baffle ceiling , c/c gap 100 mm to be suspended from Gypsum ceiling / True ceiling with suitable frame support . Cost includes necessary black color GI frame support and ply backing on Gypsum ceiling to hold the frame work . | D82: Sqm | E82: 50 | F82: 12076.175 | G82: =IFERROR(E82*F82,0) -> 603808.73 | H82: Basic price Rs.980/Sft considered as per the query response.
A83: 9 | B83: Extruded Aluminium Baffle Ceilings of size 25mm (Base) x 100mm (Height) x 1 mm (Thickness) - Wood Finish -Reception | C83: Supply and Installation of Baffle ceilings of size 100mm(Height) x Size 25mm(Base) x 1mm thick extruded aluminium 6063AA in Architect approved Wood Grain Finish suspended to a Multi-slotted baffle C Carrier made of 0.8mm thick Galvanised steel surface finished in Black colour powder Coated finish. The baffle is connected the Baffle Carrier at a centre to centre distance of 100 mm with a bolt/nut/Spring washer arrangement as per typical detail attached. The baffle C Carrier is suspended from the RCC True Ceiling at every 1m in general and at 150mm from Baffle Joints using an M6 Threaded Rod and suitable anchor fastener. The baffles come at a maximum size up to 6 m in length. The baffle end with an End Cap made in Aluminium and is with same finish as the baffle panel. Two baffle are connected by splice to make it run continuously or with a Gap of 20mm as per architect’s approval. The rate quoted for false ceiling system shall include providing necessary cut-outs/supports for all fixing light fixtures (all sizes) AC diffuser, AC dampers, AC linear grills, smoke detectors, speakers, etc. and any other openings to be made in false ceiling as directed. . Make: Armstrong / Hunter Douglas /Frameline / Nextior | D83: Sqm | E83: 50 | F83: 6777.445 | G83: =IFERROR(E83*F83,0) -> 338872.25 | H83: Fameline make considered.
A84: 10 | B84: Metal Ceiling (Triangular Aluminium cell ceiling) | C84: Providing and fixing of triangle patent ceiling with tiles made of .8 mm thk, 60 mm height aluminium with clip in system. Above ceiling services (ducts, tray, conduits) and true ceiling to be finished in black colour. Make: Frameline | D84: sqm | E84: 80 | F84: 5175.5034 | G84: =IFERROR(E84*F84,0) -> 414040.27 | H84: Fameline make considered. Aluminium Triangle cell ceilings with Cell ceilings sections A, B and C of size 25 mm (base) x 100 mm( Height) x 2500 mm ( Length ) , thickness 0.6mm. The sections are interlocked with each other to form a equilateral triangle cell of size 300 mm x 300 mm x 300 mm.
A85: 11 | B85: Metal Ceiling (Square Aluminium cell ceiling) | C85: Providing and fixing Metal Open cell ceiling consisting of 0.5mm thick extruded aluminium metal of approved height in 'U' bends mounted using 6mm thk GI threaded rod suspended from true ceiling through anchor fasteners and hardware. The size of Openings will be 100 mm x 100 mm. Tile size 600X600 mm . Tiles to be fixed on 25X25 Al Grid . The System to be provided along the fleece backing with felt.Above ceiling services (ducts, tray, conduits) and true ceiling to be finished in black colour. Complete as per drawing and as directed by Engineer. Rate shall also include providing of acoustic fleece above the ceiling. Make: Armstrong / Hunter Douglas /Frameline/ Metal matrix is considered | D85: sqm | E85: 25 | F85: 4682.5983 | G85: =IFERROR(E85*F85,0) -> 117064.96 | H85: Fameline make considered.
A86: 12 | B86: True Ceiling Treatment & Paint finish | C86: Providing and Applying Acrylic emulsion Paint of approved colour on the true ceiling surfaces of approved make, colour and shade in three coats , including preparing existing surfaces by scraping away and loose particles, dust etc., by washing and scrubbing, filling up with crack filler, binder; cleaning and making the surface dust-free, applying approved lambi-putty / POP punning and rubbing with sandpaper to make surface smooth to approval of the Project in-charge and applying a one primer coat and three coats of emulsion paint as recommended by approved paint manufacturer, including required scaffolding, cleaning and protecting till the handing over of site etc. all complete at all hei ghts and leads as per specifications or as directed by the Project in-charge to entire his satisfaction. All ceiling services to be painted and to be cleaned after completion of final coat painting . | D86: Sqm | E86: 80 | F86: 318 | G86: =IFERROR(E86*F86,0) -> 25440
A87: 13 | B87: Suspended Acostical pet panel board - Type-1 ( Café) | C87: Providing and fixing of 50 mm thk eco panel boards in Honeydue shape of size 900x900 / 1200x1200mm approx. with necessary 18 mm thk ply backing for rigidity suspended from ceiling with suitable clutch wire support system that are height adjustable. Eco boards to be cut and installed to achieve the pattern as per detail dwg provided by Architect. Colour and other specifications are to be as per architects approval. Basic rate of Eco board - 1500/ sqm | D87: Nos | E87: 30 | F87: 7748.0064 | G87: =IFERROR(E87*F87,0) -> 232440.19 | H87: Quoted for 50mm thick eco board (BR: Rs.1,500/Sqm) with 18mm thick ply backing considered suspended from True ceiling.
A88: 14 | B88: Suspended Cloud acoustical board ( Huddle space) | C88: Providing and fixing acoustical cloud panels -( 800 X800 mm) . Basic price- Rs-7,500 . Make: Art & Design , Sensus, Rockworth | D88: Nos | E88: 10 | F88: 5824.7424 | G88: =IFERROR(E88*F88,0) -> 58247.424 | H88: Quoted based on the given basic price - Acoustic panel basic price Rs.7,500/Sqm.
A89: 15 | B89: MS Work | C89: Supply, Fabrication and installation of MS Structural Works of approved size, sections and shape as per the detailed drawing.The cost should include painting the members with one coat of primer and two coats of enamel spray paint of colour approved by Architect. Huddle area- Ceiling . Refer 3D view and submit cost proposal. | D89: kg | E89: 100 | F89: 196.1 | G89: =IFERROR(E89*F89,0) -> 19610
A90: G | B90: FLOORING & DADO | F90: 0
A91: 1 | B91: LVT Flooring - | C91: Supply and laying of 5-6 mm thk LVT Flooring over on self levelled PCC Floor. Basic rate LVT Floor - 300/ sqft . LVT to be cut and installed as per the pattern given in the detail dwg /3D view. | D91: QRO-sqm | F91: 4682.5983 | G91: =IFERROR(E91*F91,0) -> 0
A92: 2 | B92: Anti-Static Raised Access Flooring With 600x600mm tiles (300 mm Height) ) - Server room, UPS & Battery room | C92: Supply, fabricating and erection of 300mm height Antistatic Raised access flooring of size of 600mm x 600mm above finished floor level to withstand load of 1260 Kg per Smt. and rolling loads with Snap Lock Grid System using Electro-galvanized adjustable jack made out of 25mm dia. bright bar and 2 hr fire rated removable flooring tiles made of steel with non-combustible cementious compound complete in all respect as per the specifications. b. Provision should made for satisfactory earthing for all floor tiles.Cost Inclusive of One tile Puller. Make - Unitile | D92: Sqm | E92: 40 | F92: 5141 | G92: =IFERROR(E92*F92,0) -> 205640
A93: 3 | B93: 3M Recessed panel with Mat (Entrance, Cafeteria) | C93: Providing and fixing floor Mat in nomad range of 3M make heavy duty Nomad range grey shade mat be fixed with Velcro. Basic price- Rs-6500/ sqm | D93: Sqm | E93: 10 | F93: 7441.2 | G93: =IFERROR(E93*F93,0) -> 74412
A94: 4 | B94: Granite Jambs | C94: Providing and fixing of granite jambs formed of 19mm thick & 300mm to 350mm wide pre polished granite jambs and jambs to be fixed using necessary 1:4 cement mortar or adhesive as per details. Rate to include nosing as per architects instruction. Basic rate of Granite - 1800 per Sq.mt. | D94: Rmt | E94: 25 | F94: 2884.896 | G94: =IFERROR(E94*F94,0) -> 72122.4
A95: 5 | B95: Vitrified Tile Flooring -Type-1 -1200X2400 mm | C95: Supply and laying of 1200 x 2400 mm Vitrified tiles laid over adequate thickness of cement mortar 1:4(1cement:4 coarse sand) without spacers , saint gobain weber epoxy grout , finished neat, allowing for necessary spacing for rubbing down the edges at corners..cost inclusive of removal of existing PCC screed floor and refill with PCC to match the tile floor level to Open office carpet floor . Includes protection with foam sheets with 2 layer of plastic cover after installation, deep cleaning before handover . Actual laid area shall be measured and paid for this item. Near door , Floor to be sunkened 12mm and finished with tile to install 3M Matt. Make- Kajaria / Asian - Basic price- 180 / sq ft . Make Epoxy Grout- Saint-Gobain Weber. | D95: Sqm | E95: 60 | F95: 3253.1736 | G95: =IFERROR(E95*F95,0) -> 195190.41
A96: 6 | B96: Vinyl flooring | C96: Providing & Laying of Vinyl Flooring over on cement plaster with smooth surface. Cost includes Self-Levelling Sub-Floor Cementitious floors of approved make, in thickness not less than 3mm, in approved colour shade with Surface preparation, Primer coat, Mixing, application, and properly designed joint treatment all as per manufacturer's specifications. Make: Armstrong Basic price- Rs-1500/ sqm. | D96: sqm | E96: 20 | F96: 2409.804 | G96: =IFERROR(E96*F96,0) -> 48196.08
A97: 7 | B97: Vitrified tiles flooring - Type-2 1200 x 600 mm / 600X600 mm - Café Passage , Handwash , Platewash | C97: Supply and laying of 1200 x 600 mm / 600X 600 mm Vitrified tiles laid over adequate thickness of cement mortar 1:4(1cement:4 coarse sand) without spacers , saint gobain weber epoxy grout , finished neat, allowing for necessary spacing for rubbing down the edges at corners..cost inclusive of removal of existing PCC screed floor and refill with PCC to match the tile floor level to Open office carpet floor . Includes protection with foam sheets with 2 layer of plastic cover after installation, deep cleaning before handover . Actual laid area shall be measured and paid for this item. Make- Kajaria - Basic price- 90 / sq ft . Make Epoxy Grout- Saintgobain Weber. | D97: Sqm | E97: 60 | F97: 2088.6853 | G97: =IFERROR(E97*F97,0) -> 125321.12
A98: 8 | B98: Vitrified tiles flooring - Type-3 300X 1200 mm - Cafeteria - Wooden Finish tile | C98: Supply and laying of 1200 X 300 mm Vitrified tiles laid over adequate thickness of cement mortar 1:4(1cement:4 coarse sand) without spacers , saint gobain weber epoxy grout , finished neat, allowing for necessary spacing for rubbing down the edges at corners..cost inclusive of removal of existing PCC screed floor and refill with PCC to match the tile floor level to Open office carpet floor . Includes protection with foam sheets with 2 layer of plastic cover after installation, deep cleaning before handover . Actual laid area shall be measured and paid for this item. Make- Kajaria - Basic price- 100 / sq ft . Make Epoxy Grout- Saintgobain Weber. | D98: Sqm | E98: 50 | F98: 2218.0729 | G98: =IFERROR(E98*F98,0) -> 110903.64
A99: 9 | B99: Rug | C99: Providing and fixing 13mm thk customised rug as per selection. Basic price- Rs-6000/ sq m | D99: Sqm | E99: 10 | F99: 7040.52 | G99: =IFERROR(E99*F99,0) -> 70405.2
F100: 0
A101: H | B101: SKIRTING & TRIMS | F101: 0
A102: 1 | B102: Aluminium skirting | C102: Providing and fixing 75mm high Aluminium skirting of 1.5mm thick 75mm high extruded anodized aluminium skirting to be fixed with 12mm thk ply backing as per manufacture spec. as per Architects approval. (Make- Walline / Bottom Line/ Hysis ) | D102: rmt | E102: 450 | F102: 307.4 | G102: =IFERROR(E102*F102,0) -> 138330 | H102: Make - Bottomline considered
A103: 2 | B103: Granite threshold-300mm | C103: Providing and installing 19mm thick polished Granite ledge of 300mm wide, the exposed edge of the ledge shall be ground to full round shall polished to gloss. The ledge formed shall be installed over a 1:3 cement mortar bedding of average 25mm thick set in cement slurry, the joints shall be grouted in approved matching colour epoxy grout. Price quoted shall be inclusive of lead, lift, required stagging, scaffolding etc., complete as per detail drawing.. Basic rate of Granite - 1800 per Sq.mt. | D103: rmt | E103: 10 | F103: 2843.6832 | G103: =IFERROR(E103*F103,0) -> 28436.832
A104: 3 | B104: Granite threshold-100mm | C104: Providing and installing 19mm thick polished Granite ledge of 100mm wide, the exposed edge of the ledge shall be ground to full round shall polished to gloss. The ledge formed shall be installed over a 1:3 cement mortar bedding of average 25mm thick set in cement slurry, the joints shall be grouted in approved matching colour epoxy grout. Price quoted shall be inclusive of lead, lift, required stagging, scaffolding etc., complete as per detail drawing.. Basic rate of Granite - 1800 per Sq.mt. | D104: rmt | E104: 20 | F104: 4739.472 | G104: =IFERROR(E104*F104,0) -> 94789.44
A105: 4 | B105: Aluminium corner guard | C105: Providing and installing 18mm X 18mm corner guard installed using approved double side adhesive tape of 3M make, complete as per detailed drawing. Height - 2700 mm . Make: Wall Line/ Bottom line/ Hysys | D105: Nos | E105: 50 | F105: 381.6 | G105: =IFERROR(E105*F105,0) -> 19080 | H105: Make - Bottomline considered
A106: 5 | B106: Window sill in prelam board finish | C106: Providing and fixing 150-300 mm wide and 150 mm high factory made window sill made of 12mm thk ply and finished with approved 1mm thk Top . Cost inclusive of providing necessary wood / ply backing supports as per site condition. (Basic rate of the laminate is Rs 500/sqm). Make of Ply-Greenply, Archid ply, Century (MR-IS:303 -1989) . Make of Laminate - Merino, Greenlam, Century | D106: rmt | E106: 45 | F106: 1325 | G106: =IFERROR(E106*F106,0) -> 59625
A107: 6 | B107: Aluminium transition profile | C107: Providing & fixing 8mm thk Aluminium Floor transition profile as per manufacturer specification. Sample to be submitted to Architect/Client for approval. Make : Wall Line / Bottom Line | D107: rmt | E107: 10 | F107: 381.6 | G107: =IFERROR(E107*F107,0) -> 3816 | H107: Make - Bottomline considered
A108: I | B108: FINISHES / PANELLING & BOXING | F108: 0
A109: 1 | B109: Laminate panelling | C109: Providing and fixing Commercial ply panelling, of 12mm thk. ply panelling finished in 1 mm thick. of approved shade laminate with 6X6mm Aluminium U channel section to be inserted to achieve uniform groove between gypsum and panelling . (Basic rate of the laminate is Rs 550/sqm) Make of Ply-Greenply, Archidply, Greenply, Archid ply (MR-IS:303 -1989), Century Make of Laminate - Merino , Greenlam, Century ( Excluding Frame work - Ply to be fixed over Gypsum partition / External wall ) | D109: Sqm | E109: 150 | F109: 2735.6232 | G109: =IFERROR(E109*F109,0) -> 410343.49
A110: 2 | B110: Lacquered glass panelling ( 12 mm thk ply + 6mm thk lac. Glass) | C110: Providing and fixing Commercial ply panelling,12 mm thk ply panelling finished with 6mm thk approved shade Lacquered Glass with suitable adhesive as per manufacturers specifications . 6X6 mm aluminium profile section to be inserted b.w lac glass and other finishes as per detail dwg. Make of Ply-Greenply, Archidply, Century (MR-IS 303 -1989). Make of Glass - Saint Gobain Ultra White Lac. Glass | D110: sqm | E110: 50 | F110: 4929 | G110: =IFERROR(E110*F110,0) -> 246450
A111: 3 | B111: Eco panel board - 12 mm thk. | C111: Supply and Installation of Modular acoustic panels /Tile (Eco Panel board) of size 1200mmx 2400mm. 12 mm thk Eco board to be fixed over on gypsum partition / Wall. Cost inclusive of providing 6X6 mm Aluminium "U" channel section to achieve uniform groove between gypsum and Eco board panelling. Eco boards to be cut and installed as per detail dwg provided by Architect. Basic Price - Rs.1650 / sqm. Make: Art & Design / Senses / Rock worth | D111: Sqm | E111: 25 | F111: 3920.5636 | G111: =IFERROR(E111*F111,0) -> 98014.091
A112: 4 | B112: Eco panel board - 9 mm thk. | C112: Supply and Installation of Modular acoustic panels /Tile (Eco Panel board) of size 1200mmx 2400mm. 9 mm thk Eco board to be fixed over on gypsum partition / Wall. Cost inclusive of providing 6X6 mm Aluminium "U" channel section to achieve uniform groove between gypsum and Eco board panelling. Eco boards to be cut and installed as per detail dwg provided by Architect. Basic Price - Rs.1250 / sqm. Make: Art & Design / Senses / Rock worth | D112: Sqm | E112: 25 | F112: 3291.5962 | G112: =IFERROR(E112*F112,0) -> 82289.905
A113: 5 | B113: CNC Eco panel board - 12 mm thk. | C113: Supply and Installation of CNC engraved Modular acoustic panels /Tile (Eco Panel board) of size 1200mmx 2400mm. 12 mm thk Eco board to be fixed over on gypsum partition / Wall. Cost inclusive of providing 6X6 mm Aluminium "U" channel section to achieve uniform groove between gypsum and Eco board panelling. Eco boards to be cut in CNC and installed to achieve the pattern as per detail dwg provided by Architect. Basic Price - Rs.2300 / sqm. Make: Art & Design / Senses / Rock worth | D113: Sqm | E113: 85 | F113: 5034.7345 | G113: =IFERROR(E113*F113,0) -> 427952.43
...

Sheet REST ROOM
A1: RESTROOM BOQ
A2: S.NO | B2: Item | C2: Specification | D2: Make | E2: Unit | F2: Total Qty | G2: Rate | H2: Amount | I2: JLL Remarks
A4: 1 | B4: 150mm thick Aerocon wall | C4: Making 150mm thick wall of Aerocon Block in 1:4 cement mortar, inclusive of 12 mm thick single coat rough Cement Plaster on both sides of wall in 1:6 Cement Mortar,with 2 nos. of 8 mm diameter steel reinforcement in every 4 layer & 2 nos. of hoop iron strips 25mm x 1.6mm, painted with anti-corrosive paint, RCC Lintel at 2400 mm Ht, properly bent and bonded at the end, inclusive of shuttering, scaffolding, Raking of joints and proper curing etc complete. The joints between the RCC and masonry will have hold fasts @ 600mm c/c, with joints finished in chicken mesh 20 gauge and finished with cement plaster | E4: Sqm | F4: 85 | G4: 2597 | H4: =F4*G4 -> 220745
A5: 2 | B5: 100mm thick Aerocon wall | C5: Making 100mm thick wall of Aerocon Block in 1:4 cement mortar, inclusive of 12 mm thick single coat rough Cement Plaster on both sides of wall in 1:6 Cement Mortar,with 2 nos. of 8 mm diameter steel reinforcement in every 4 layer & 2 nos. of hoop iron strips 25mm x 1.6mm, painted with anti-corrosive paint, RCC Lintel at 2400 mm Ht, properly bent and bonded at the end, inclusive of shuttering, scaffolding, Raking of joints and proper curing etc complete. The joints between the RCC and masonry will have hold fasts @ 600mm c/c, with joints finished in chicken mesh 20 gauge and finished with cement plaster | E5: Sqm | F5: 10 | G5: 2491 | H5: =F5*G5 -> 24910
A6: 3 | B6: Aerocon light weight blocks filling | C6: Aerocon Light weight blocks filling up to 200-300 mm depth. cost inclusive of Providing top layer in 50 mm thk Grano Flooring.to receive tile floor | E6: Sqm | F6: 50 | G6: 3074 | H6: =F6*G6 -> 153700
A7: 4 | B7: Cinder filling | C7: Providing and laying of raised floor 300mm deep with necessary cinder with 25-50mm thk 1:2:4 grade PCC concrete, curing 2 days and then finishing the surface with 10mm thk of 1:6 mortar to proper level and slope. Rate to include necessary steps and ramp as per architects instructions. | E7: Sqm | F7: 20 | G7: 2597 | H7: =F7*G7 -> 51940
A8: 5 | B8: Water proofing | C8: Providing, supplying, mixing and applying two coats of ready-to-use two-component acrylic polymer, modified cement base, flexible water-proofing slurry or approved equivalent to a thickness of 2 mm over the bottom and sides of the slab / sunken slab. Waterproofing to extend upto 600 on the preiphery walls. Cost to include checking of waterproofing for 48 hours with 300mm high water logged floor.Method Statement of water proofing to be submitted before execution. | E8: Sqm | F8: 100 | G8: 954 | H8: =F8*G8 -> 95400
A9: 6 | B9: 150mm thick Ledge wall | C9: Making 150mm thick ledge wall of Aerocon Block in 1:4 cement mortar, inclusive of 12 mm thick single coat rough Cement Plaster in 1:6 Cement Mortar | E9: Rmt | F9: 20 | G9: 2650 | H9: =IFERROR(F9*G9,0) -> 53000
A10: 7 | B10: Vitrified tiles flooring 1200x600 MM for toilet | C10: Supply and laying of 1200X600 mm Vitrified tiles laid over adequate thickness of cement mortar 1:4(1cement:4 coarse sand) with 3mm thk spacers , saint gobain weber epoxy grout , finished neat, allowing for necessary spacing for rubbing down the edges at corners.. Includes protection with foam sheets with 2 layer of plastic cover after installation, deep cleaning before handover . Actual laid area shall be measured and paid for this item. Make- Kajaria / Asian. Basic price - 900/ sqm . Make Epoxy Grout- Saintgobain Weber. | D10: Tile: Kajaria / Johnson / Somany/ Asian ; Epoxy Grout, Adhesive - Weber-Saintgobain | E10: Sqm | F10: 100 | G10: 1940.436 | H10: =IFERROR(F10*G10,0) -> 194043.6
A11: 8 | B11: Vitrified tiles wall dado 600 x 600 / 300X600 | C11: Supply and laying of 600X600mm / 300X600 mm Vitrified tiles laid over adequate thickness of cement mortar 1:4(1cement:4 coarse sand) with 2mm thk spacers filled with epoxy grout . Cost includes corner beading and ancillary works , Actual laid area shall be measured and paid for this item. Make- Kajaria / Asian. Basic price - 900/ sqm . Make Epoxy Grout- Saintgobain Weber. | D11: Tile: Kajaria / Johnson / Somany/ Asian ; Epoxy Grout,Adhesive - Weber-Saintgobain | E11: Sqm | F11: =61*2.6 -> 158.6 | G11: 1940.436 | H11: =IFERROR(F11*G11,0) -> 307753.15
A12: 9 | B12: Cement plastering | C12: Existing wall to be finished with 12 mm thick cement plaster in CM 1:5 to walls Internal in single coat at all levels to correct line to a maximum of 50 mm and level including scaffolding, if any, and rounding off or champhering of corners, cleaning of surface, raking out joints, chiseling the undulated surface wherever necessary and curing, etc., all materials and labour complete in all respects including all lead, lift and descent and as directed | D12: Make- Ultratech / Ramco | E12: Sqm | F12: =61*2.6 -> 158.6 | G12: 477 | H12: =IFERROR(F12*G12,0) -> 75652.2
A13: 10 | B13: Granite Ledge | C13: Providing and fixing thresholds of 18mm thick pre-polished granite slab of approved shade fixed along the doors (it shall be provided flush with finished edges of the wall as per the wall thickness) on a bed of average 35mm thick cement mortar 1:4, as per detailed design the width 100 to 300mm and as directed and shall be provided flush with adjoining flooring levels, with all exposed edges finished as per details and with machine mirror polishing. (Basic Cost of Granite - Rs. 250/- per sq.ft) All complete as per instruction & satisfaction of Project Managers. | E13: Rmt | F13: 30 | G13: 3029.3125 | H13: =IFERROR(F13*G13,0) -> 90879.376
A14: 11 | B14: Washbasin counter - Granite finish | C14: 600 mm wide counter for wash basin in 19mm thk granite finish . Powder coated MS angle frame support to be fixed to the brick wall and covered with 18mm thk PVC integral board. 19mm thk granite to be cladded over on PVC integral board as per the detail dwg . Includes 300 mm fascia below counter and 10 mm band above counter granite finish , c . Necessary cutouts to be taken in the counter to insert wash basin and trash bin . | E14: Rmt | F14: 10 | G14: 10070 | H14: =IFERROR(F14*G14,0) -> 100700
A15: 12 | B15: False Ceiling - Metal | C15: Providing & Fixing MetalWorks Lay in Perforated metal ceiling System consisting of 600mm x 600mm Lay in tiles of pre coated galvanized steel in 0.5 mm thickness in approved color with perforation of 2.5mm dia, 5.5mm square pitch & open area of 16% with Freudenberg Soundtex/ Owens Corning Acoustimax S acoustical fleece on the back of the tile to be laid on grid systems with black silhouette 15mm wide T - section flanges. The tiles should have Humidity Resistance (RH) of 95%, NRC of 0.70 (Soundtex C1986SP of Freudenberg or Acoustimax S of Owens Corning fleece inlay or as per detail drawing), Fire Performance A2-s1.d0 in module size of 600 X 600 mm, suitable for Green Building application, with Recycled content of 25%. Cross tees shall have staked XL clips that ensure a minimum pull off strength of 100 Kgs/joint. The Tile & Grid system used together should carry a 10 year warrantee. The rate should be inclusive of necessary cutouts for Services etc. Load test as per manufactures to be carried out on site and test certificate to be provided.. Make- Fameline / Daiken. Basic price - 1800 /Sqm | D15: Daiken / Fameline | E15: Sqm | F15: 100 | G15: 2332 | H15: =IFERROR(F15*G15,0) -> 233200
A16: 13 | B16: Gypsum Ceiling | C16: Providing & Fixing of 12.5mm thk MR Gypsum board false ceiling to G.I. framing in perfect level. Necessary offsets and grooves to be provided at the junction of ceiling & walls/columns/partitions etc., Cut out for light fittings A/C grills etc. Rate to include providing & fixing of necessary G.I./wooden/MS frame supports for the above fixtures & additional suspenders & the ceiling in AC duct area as per architects instructions. G.I.frame to consist of proprietary supplied frames & as per manufacturers recommendations suspended from dash fasteners anchored to structural slab by means of G.I.angles. Gypsum board fixed with proprietary supplied fixing devices & finished. The joint between the sheets of plasterboard are to be covered with jointing paper tape and flushed with UB 888 (all purposes jointing compound) to provide a smooth durable and professional finish. Suspension points and clips shall be able to take a minimum safe load of 50 kgs. including making grooves at the junction of ceiling & walls/columns/partitions etc. Cut-outs for light fittings, A/C grills etc. to be left wherever necessary. the ceiling profile shall be as per Architects instructions. The rate shall be inclusive of preparing the surface, providing and applying 2 coats of proper putty and primer and 3 coats of paint, roller applied Acrylic emulsion paint of approved quality / colour to Architect's approval. All complete including return air slits etc. & A/C boxing wherever indicated. Note : Marking of Electrical , Fire Alarm & Air-conditioning & co-ordination with marking of fixtures to be considered. Gypsum ceiling to be installed as per IGL specifications. Note : Marking of Electrical , Fire Alarm & Air-conditioning & co-ordination with marking of fixtures to be considered. Note: Measurement to be along the horizontal surface of the ceiling and the verticals (till 200mm ht) shall be included in arriving at cost. Rate quoted to include vertical drops (till 200mm ht) and all cut-outs required for light fixtures, smoke detectors and other services cut-outs complete as directed by Architect. Verticals above 200mm ht will be measured separately. Rate to include cove lighting provision as per detail drawings | D16: USG / Gyproc | E16: Sqm | F16: 20 | G16: 1462.8 | H16: =IFERROR(F16*G16,0) -> 29256
A17: 14 | B17: Rest room Signage | C17: 6 x 9 inch Restroom Sign in Stainless Steel Metal, Engraved, Door / Wall Mount Sign, Silver and Black | D17: SS | E17: Nos | F17: 5 | G17: 1537 | H17: =IFERROR(F17*G17,0) -> 7685
A18: 15 | B18: Rest room Cubicles- Top hung cubicle - Merino / Greenlam /Stylam | C18: Providing & fixing SS Top Hung module 12mm HPL partition with SS 304 Hardware & SS finish sections. standard dimension 1050/1200mm (Width) x1650 mm (L) X 2000mm Ht . -Thickness of Compact Laminate :12 mm Thick Size of Cubicle : Pl refer Rest room Floor plan and submit shop dwg Door Size for Cubicle : 600mm Bottom Gap - 100 mm . Cost includes taking necessary supports for the top hung cubicle from true ceiling . | D18: Greenlam Air collction Wind / Eq in Merino / I Space | E18: Nos | F18: 10 | G18: 30531.611 | H18: =IFERROR(F18*G18,0) -> 305316.11 | I18: Make - Merino & Model - ZMS SS Series considered.
A19: 16 | B19: HD - 1200 x 2400mm (For Handicap Toilet Entrance) - Sliding Door | C19: Providing and constructing single shutter sliding door of 1200 mm size made of 38mm thick blockboard of approved make with Haffle / Hettich sliding track profile , Shutter to be finished in 1mm thk glossy laminate of approved shade, inclusive of all hardwares , Recessed SS handle , Vaccant / Engaged lock , door floor stoppr as per detailed drawing complete. (Make Fittings - Haffle / Hettich) . Blockboard : Prestige/Greenply / Century , Make of Laminate - Merino, Greenlam, Century.Basic Price - Rs- 750 / sqm . Cost includes 200X400 mm powder coated ventilation grill and laminated pelmet above sliding track . | D19: (Make Fittings - Haffle / Hettich) . Blockboard : Prestige/Greenply / Century , Make of Laminate - Merino, Greenlam, Century.Basic Price - Rs- 750 / sqm | E19: Nos | F19: 1 | G19: 59413 | H19: =IFERROR(F19*G19,0) -> 59413
A20: 17 | B20: 1200 x 2400 mm Aluminium Door Frame & Flush door with Full Ht (Toilet) | C20: Door Jamb : 100mm X 25mm Proprietary anodised aluminium section with black powder coated finish.. Black anodised Action : Single Swing . 100X25X2400 mm Ht . Door frame to be grouted to the PCC Floor with suitable Brackets as per manufacturers specification. Black anodised Shutter Construction : 32mm thk Flush door in laminate finish with vision panel as per detail dwg . Cost includes 200X400 mm powder coated ventilation grill . Make - Greenply / Century Hinge Type : 4 Nos Hinges . Dorma / Gaze 5" Flush suitable to style shutter Lockset : Dorma 952 Narrow style lock / GEZE 8134002 Door Handle : D Type offset handle 450 mm high . Black anodised Door Closer: - Dorma TS 71 Door Closer / Eq GEZE Door Stopper : Dorma / Geze Door frame make: Alloy / Geze / JEB Glass- Saint Gobain . | D20: GEZE / Alloy / JEB . Glass - Saintgobain | E20: Nos | F20: 1 | G20: 53689 | H20: =IFERROR(F20*G20,0) -> 53689 | I20: Door Frame - Alloy make considered. Door Hardwares - Geze make considered.
A21: 18 | B21: 900 x 2100 mm Aluminium Door Frame & Flush door with Full Ht Restrooms) | C21: Door Jamb : 100mm X 25mm Proprietary anodised aluminium section with black powder coated finish.. Black anodised Action : Single Swing . 100X25X2400 mm Ht . Door frame to be grouted to the PCC Floor with suitable Brackets as per manufacturers specification. Black anodised Shutter Construction : 32mm thk Flush door in laminate finish with vision panel as per detail dwg . Cost includes 200X400 mm powder coated ventilation grill . Make - Greenply / Century Hinge Type : 4 Nos Hinges . Dorma / Gaze 5" Flush suitable to style shutter Lockset : Dorma 952 Narrow style lock / GEZE 8134002 Door Handle : D Type offset handle 450 mm high . Black anodised Door Closer: - Dorma TS 71 Door Closer / Eq GEZE Door Stopper : Dorma / geze Door frame make: Alloy / Geze / JEB Glass- Saint Gobain . | D21: GEZE / Alloy / JEB . Glass - Saintgobain | E21: Nos | F21: 2 | G21: 52629 | H21: =IFERROR(F21*G21,0) -> 105258 | I21: Door Frame - Alloy make considered. Door Hardwares - Geze make considered.
A22: 19 | B22: 750 x 2100 mm Aluminium Door Frame & Flush door with Full Ht (Shower room) | C22: Door Jamb : 100mm X 25mm Proprietary anodised aluminium section with black powder coated finish.. Black anodised Action : Single Swing . 100X25X2100 mm Ht . Door frame to be grouted to the PCC Floor with suitable Brackets as per manufacturers specification. Black anodised Shutter Construction : 32mm thk Flush door in laminate finish with vision panel as per detail dwg . Cost includes 200X400 mm powder coated ventilation grill . Make - Greenply / Century Hinge Type : 4 Nos Hinges . Dorma / Gaze 5" Flush suitable to style shutter Lockset : Dorma 952 Narrow style lock / GEZE 8134002 Door Handle : D Type offset handle 450 mm high . Black anodised Door Closer: - Dorma TS 71 Door Closer / Eq GEZE Door Stopper : Dorma / Geze Alloy / Geze / JEB Glass- Saint Gobain . | D22: GEZE / Alloy / JEB . Glass - Saintgobain | E22: Nos | F22: 1 | G22: 49916.364 | H22: =IFERROR(F22*G22,0) -> 49916.364 | I22: Door Frame - Alloy make considered. Door Hardwares - Geze make considered.
A23: 20 | B23: Shaft Door | C23: Providing and fixing Metal powder coated shaft door of size - 750 mm (W) X 1500 mm(Ht) . With Door frame , Recessed handle, Lock etc., | E23: QRO-Nos | G23: 25970
A24: 21 | B24: Luster paint | C24: Providing & applying of Luster painting for walls. Shall be applied with oil based primer coat after rubbing with sand paper onto the existing wall surface. Surface to be smoothened using chalk putty as directed. Uneven surfaces to be finished with 2 coats of chalk powder putty on the primer. Surfaces are then sandpapered to achieve a smooth surface and 3 coats of luster Paint of approved shade to be applied. The top coat should be 3 coats of 'Superfine' roller matt finish. The colour should be approved by Architect. Note : Rate should be inclusive of Masking for fixtures & wooden frames. | D24: Asian /Dulex | E24: Sqm | F24: 25 | G24: 318 | H24: =IFERROR(F24*G24,0) -> 7950
A25: 22 | B25: Mirror | C25: Providing and fixing of 6mm thick float mirror of approved make edge polished and without any defects, waves etc., shall be mounted on 12mm thick Marine ply (IS 710) backing with approved 3M Double sided tape / Adhesive as per details. To have aluminium U channel on Top and bottom to hold mirror as per details. Modiguard float mirror shall be considered. Rate including cove light provision and LED strip light all around mirror. | D25: Marine ply - Archid /Century . 3M | E25: Sqm | F25: 10 | G25: 4187 | H25: =IFERROR(F25*G25,0) -> 41870
A26: 23 | B26: Wash basin counter in corian finish | C26: 600 mm wide, 800 mm high wash basin counter made of 18mm thk WPC / PVC integral board , MS angle support finished with 12mm thk corian . Cost includes 100 mm high band above counter and 300 mm high front fascia as per detail dwg. Necessary cutout to be made in counter top to fix the counter sunk washbasins and sink . Basic price corian - 900/sqft . | E26: Sqm | F26: 3 | G26: 23850 | H26: =IFERROR(F26*G26,0) -> 71550
A27: 24 | B27: Vacant / non Vacant Knob | C27: Providing and fixing in position Vacant / non Vacant Indicator in toilets | D27: Kich | E27: Nos | F27: 2 | G27: 2650 | H27: =IFERROR(F27*G27,0) -> 5300
A28: 25 | B28: SS Grab bar | C28: Supply and Fixing of foldable type SS Grab bar for differently abled person toilet. | D28: Jaquar | E28: Nos | F28: 1 | G28: 1941.39 | H28: =IFERROR(F28*G28,0) -> 1941.39 | I28: Mode - AHS-CHR-1503 - As per the query response.
A29: 26 | B29: SS Grab bar | C29: Supply and Fixing of fixed type SS Grab bar for differently abled person toilet. | D29: Jaquar | E29: Nos | F29: 2 | G29: 8213.94 | H29: =IFERROR(F29*G29,0) -> 16427.88
A30: 27 | B30: Cockroach trap | C30: Providing and fixing in position of Cockroach trap | D30: Jaquar | E30: Nos | F30: 17 | G30: 2703 | H30: =F30*G30 -> 45951 | I30: Make : Chilli / ACO - As per the query response.
A31: 28 | B31: Janitor storage | C31: Providing and fixing janitor storage made of 18mm thk WPC / PVC integral board and finished with approved 1mm thk laminate . Height- 2100 mm . Depth- 450 mm. Cost includes adjustable vertical and horizontal shelves , Laminated shutters with finger groove handle , Lock etc., | D31: Greenply / Century | E31: sqm | F31: 7 | G31: 15370 | H31: =F31*G31 -> 107590
C32: TOTAL COST PER FLOOR ( EXCLUSIVE OF TAXES) | H32: =SUM(H4:H31) -> 2511037.1

Sheet HVAC SUMMARY
A1: HVAC BOQ SUMMARY
A2: S.No | B2: Description | C2: Supply Amount in INR | D2: Installation Amount in INR | E2: Total Amount INR
C3: PHASE-1 | D3: PHASE-1
A4: 1 | B4: HVAC LOW SIDE WORKS | C4: ='HVAC Lowside'!H179 -> 2237176 | D4: ='HVAC Lowside'!I179 -> 503202.1 | E4: =SUM(C4:D4) -> 2740378.1
A6: 2 | B6: VAV SYSTEM | C6: =VAV!H82 -> 58936 | D6: =VAV!I82 -> 7367 | E6: =SUM(C6:D6) -> 66303
A8: 3 | B8: VRF SYSTEM | C8: ='VRF SYSTEM'!H72 -> 1663767.6 | D8: ='VRF SYSTEM'!I72 -> 228324 | E8: =SUM(C8:D8) -> 1892091.6
B10: GRAND TOTAL (excluding taxes) | C10: =SUM(C4:C8) -> 3959879.6 | D10: =SUM(D4:D8) -> 738893.1 | E10: =SUM(E4:E8) -> 4698772.7

Sheet HVAC Lowside
A1: HVAC BOQ
A2: S.NO | B2: DESCRIPTION | C2: UNIT | D2: 1F | E2: TOTAL QTY | F2: IN INR | H2: IN INR
F3: SUPPLY RATE | G3: INSTALLATION RATE | H3: SUPPLY AMOUNT | I3: INSTALLATION AMOUNT
A5: A | B5: MECHANICAL SYSTEM
B6: AIR CONDITIONING WORKS
A8: 1 | B8: DOUBLE SKIN PLENUM for AHU's
B9: All Sheet metal cabinet type double skin air plenum section for air handling units supplied by Developer.The plenum shall be constructed using double-skinned acoustic panels with minimum 0.6 mm thick pre-coated GSS sheet for outer skin and & minimum 0.6 mm plain GSS sheet for inner skin of the unit. All the panels shall incorporate 50 mm thick PUF insulation sandwiched in between inner & outer skin.
A10: a | B10: Double skin Plenum with all supports suiting to site conditions. Plenum colour shall be similar to the existing AHU. | C10: Sqm | D10: 25 | E10: =SUM(D10:D10) -> 25 | F10: 3750 | G10: 400 | H10: =F10*E10 -> 93750 | I10: =G10*E10 -> 10000
F11: 0 | G11: 0
A12: 2 | B12: OUTDOOR MOUNT TYPE EXHAUST FAN' S | E12: =SUM(D12:D12) -> 0 | F12: 0 | G12: 0
B13: All fans shall have minimum 70% total efficiency. | F13: 0 | G13: 0
A14: a | B14: 600 Cfm - 35 mm external static double skin cabinet type Inline fan with all necessary supports. (café exhaust). Fan shall be provided with in built fan regulator. Outdoor Mount type | C14: Nos | D14: 1 | E14: =SUM(D14:D14) -> 1 | F14: 28090 | G14: 1590 | H14: =F14*E14 -> 28090 | I14: =G14*E14 -> 1590
A15: b | B15: 300 Cfm - 10 mm external static Double skin cabinet type explosion proof fan with all necessary supports. (Battery room exhaust). | C15: Nos | D15: 1 | E15: =SUM(D15:D15) -> 1 | F15: 20670 | G15: 1590 | H15: =F15*E15 -> 20670 | I15: =G15*E15 -> 1590
A16: c | B16: Supply fixing testing & commissioning of Hyderogen sensor with sequential timer suitable control panel to operate Battery room exhaust fan at regular 2hrs interval fan run 5.0 minutes and when increse the Hyderagen level above 1% switch ON the fan. Controller shall have bypass mode to switch ON / OFF manually with necessary control wiring. | C16: Nos | D16: 1 | E16: =SUM(D16:D16) -> 1 | F16: 58300 | G16: 1590 | H16: =F16*E16 -> 58300 | I16: =G16*E16 -> 1590
A17: d | B17: 500 Cfm -15mm external static cabinet type fresh air fan with prefilter & necessary supports Outdoor Mount type | C17: Nos | D17: 1 | E17: =SUM(D17:D17) -> 1 | F17: 20670 | G17: 1590 | H17: =F17*E17 -> 20670 | I17: =G17*E17 -> 1590
A18: e | B18: 1300 Cfm - 15 mm external static double skin cabinet type Inline fan with all necessary supports. (Toilet exhaust). Fan shall be provided with in built fan regulator. | C18: Nos | D18: 2 | E18: =SUM(D18:D18) -> 2 | F18: 58300 | G18: 2120 | H18: =F18*E18 -> 116600 | I18: =G18*E18 -> 4240
B19: Note: All Exhaust, Scrubber & Fresh air units should be compatible of third party BMS system integration & fire trippig should be consider in part Electrical vendor scope. HVAC vendor should be coordinate with Electrical & BMS vendor. | E19: =SUM(D19:D19) -> 0 | F19: 0 | G19: 0
E20: =SUM(D20:D20) -> 0 | F20: 0 | G20: 0
A21: 3 | B21: Sheet Metal Work using with Ductmate(TDF) Flanges for all sizes of the duct. Fabrication as per SMACNA Standards | E21: =SUM(D21:D21) -> 0 | F21: 0 | G21: 0
A22: 3.01 | B22: Galvanizing shall be Class VIII – light coating of zinc, nominal 120 gm / sqm surface area and Lock Forming Quality prime material alongwith mill test certificates. In addition, if deemed necessary, samples of raw material, selected at random by owner’s site representative shall be subject to approval and tested for thickness and zinc coating at contractor’s expense. | E22: =SUM(D22:D22) -> 0 | F22: 0 | G22: 0
B23: All duct construction and installation shall be in accordance with SMACNA standards. In addition ducts shall be factory fabricated utilizing the following machines to provide the requisite quality of ducts. | E23: =SUM(D23:D23) -> 0 | F23: 0 | G23: 0
B24: All ducts shall be fabricated and installed in workmanlike manner, conforming to relevant SMACNA codes. | E24: =SUM(D24:D24) -> 0 | F24: 0 | G24: 0
B25: Above 1000mm width duct bends Vanes to be considered every 300mm once cost inclusive of this items. | E25: =SUM(D25:D25) -> 0 | F25: 0 | G25: 0
B26: The Duct shall be supported with specified Supports at regular intervalas as mentioned in the technical specifications. (To ensure the air tightness, (All ducts shall be checked with third party Pressure test after completion of installation but before applying insulation) Report should be submit | E26: =SUM(D26:D26) -> 0 | F26: 0 | G26: 0
B27: Rectangular ducting | E27: =SUM(D27:D27) -> 0 | F27: 0 | G27: 0
B28: Sheet Metal Ducting As per Specification. Pressure 500 Pa | E28: =SUM(D28:D28) -> 0 | F28: 0 | G28: 0
A29: a | B29: 26 G Ducting with TDF flanges(0-550mm) | C29: Sqm | D29: 340 | E29: =SUM(D29:D29) -> 340 | F29: 750 | G29: 159 | H29: =F29*E29 -> 255000 | I29: =G29*E29 -> 54060
A30: b | B30: 24 G Ducting with TDF flanges(551-900mm) | C30: Sqm | D30: 150 | E30: =SUM(D30:D30) -> 150 | F30: 875 | G30: 159 | H30: =F30*E30 -> 131250 | I30: =G30*E30 -> 23850
A31: c | B31: 22 G Ducting with TDF flanges(901-1200mm) | C31: Sqm | D31: 75 | E31: =SUM(D31:D31) -> 75 | F31: 975 | G31: 159 | H31: =F31*E31 -> 73125 | I31: =G31*E31 -> 11925
A32: d | B32: 20 G Ducting with TDF flanges(1201-1600mm) | C32: Sqm | D32: 10 | E32: =SUM(D32:D32) -> 10 | F32: 1100 | G32: 159 | H32: =F32*E32 -> 11000 | I32: =G32*E32 -> 1590
A33: e | B33: 18 G Ducting with TDF flanges(1601 & above) | C33: Sqm | D33: 15 | E33: =SUM(D33:D33) -> 15 | F33: 1325 | G33: 159 | H33: =F33*E33 -> 19875 | I33: =G33*E33 -> 2385
A34: 3.02 | B34: Supply & applying of spray painting for exposed rectangular ducts(colour to confirmed by PMC/ARCH) -2 coats of primer to be considered as first level. Further based on finalized color one set of painting to be done. And final coat to be applied | C34: Sqmt | E34: =SUM(D34:D34) -> 0 | F34: 0 | G34: 0 | H34: =F34*E34 -> 0 | I34: =G34*E34 -> 0
F35: 0 | G35: 0
A36: 3.04 | B36: ELLIPTICAL DUCT | F36: 0 | G36: 0
B37: Supply and installations of factory made Sheet metal Flat oval Spiral ducting with (factory made internal thermal insulation -9 mm thick closed cell material to be considered cost of this shall be inclusive of this item) fittings, Wire supports, The factor of wire to suit to duct weight, with necessary anchor fasteners and hook arrangements with suitable rod thickness,etc., confirming SMACNA standards. Duct should be fabricated by using CNC machines, Including necessary civil works as per site condition. Exposed ducts color to match interior requirement. Colour shall be confirmed by Architect. The joints shall be 100% leak proof. The duct should be factory made internally insulated with 9mm thick antimicrobial nitrile rubber. (Light test need to considered for elliptical ducts) | F37: 0 | G37: 0
A38: a | B38: 24 G ( With Ductmate Flanges) | C38: Sqm | D38: 25 | E38: =SUM(D38:D38) -> 25 | F38: 1060 | G38: 212 | H38: =F38*E38 -> 26500 | I38: =G38*E38 -> 5300
A39: b | B39: 22 G ( With Ductmate Flanges) | C39: Sqm | D39: 30 | E39: =SUM(D39:D39) -> 30 | F39: 1219 | G39: 212 | H39: =F39*E39 -> 36570 | I39: =G39*E39 -> 6360
A40: c | B40: 20 G (With Ductmate Flanges) | C40: Sqm | D40: 10 | E40: =SUM(D40:D40) -> 10 | F40: 1378 | G40: 212 | H40: =F40*E40 -> 13780 | I40: =G40*E40 -> 2120
A41: d | B41: 18 G (With Ductmate Flanges) | C41: Sqm | E41: =SUM(D41:D41) -> 0 | F41: 0 | G41: 0 | H41: =F41*E41 -> 0 | I41: =G41*E41 -> 0
F42: 0 | G42: 0 | H42: =F42*E42 -> 0 | I42: =G42*E42 -> 0
A43: 4 | B43: Air Terminal Devices | E43: =SUM(D43:D43) -> 0 | F43: 0 | G43: 0 | H43: =F43*E43 -> 0 | I43: =G43*E43 -> 0
A44: 4.01 | B44: Linear Slot Diffusers - to be fixed in techzone ceiling | F44: 0 | G44: 0
B45: Adjustable curved slot diffuser with aesthetically shaped face section, suitable for installation in false ceiling system. Comprising face section with 1-4 slots, either with integral or additional slide on flanges, end caps (plates or angles) and with inset air control blades which can be used to provide any direction of air discharge. These blades are factory set but can be site adjusted by others to alter air discharge direction to meet local requirements. Complete with rear mounted plenum box fitted with side entry spigot and four suspension brackets to hang complete assembly from the ceiling. The slot diffuser has a variable neck length and depending on construction, the diffuser face section can be factory fitted to the plenum box or suplied superately for second fix on site. (colour to be confirmed by Architect before placing the order. | F45: 0 | G45: 0
B46: 3- Slot Linear Diffuser (16 mm wide Slot) - 150 mm wide | F46: 0 | G46: 0
A47: a | B47: Slot Diffuser as per specification but without plenum box & End Flanges | C47: RMT | D47: 10 | E47: =SUM(D47:D47) -> 10 | F47: 1484 | G47: 212 | H47: =F47*E47 -> 14840 | I47: =G47*E47 -> 2120
A48: b | B48: End Flanges suitable for above size | C48: Set | D48: 2 | E48: =SUM(D48:D48) -> 2 | F48: 477 | G48: 132.5 | H48: =F48*E48 -> 954 | I48: =G48*E48 -> 265
A49: c | B49: Hit & Miss Damper for above size | C49: Sqm | D49: 1 | E49: =SUM(D49:D49) -> 1 | F49: 3710 | G49: 371 | H49: =F49*E49 -> 3710 | I49: =G49*E49 -> 371
F50: 0 | G50: 0
A51: 4.02 | B51: Circular Diffusers (with out collar damper) | F51: 0 | G51: 0
B52: Powder coated, extruded aluminium, removable center core type, supply / return air diffusers without volume control dampers of aluminium construction of the following neck sizes. The diffuser shall be mounted in the GI box (not in scope), with inlet connector suitable for flexible duct. GI Box & Flexible duct quantified seperately. Measurement shall be based on outer to outer size of the air terminal device ( colour for the grill to b confirmed by Arch/ PMC team before placing the order) | F52: 0 | G52: 0
B53: 250mm dia | C53: Nos | D53: 1 | E53: =SUM(D53:D53) -> 1 | F53: 1378 | G53: 212 | H53: =F53*E53 -> 1378 | I53: =G53*E53 -> 212
B54: 315mm dia | C54: Nos | D54: 1 | E54: =SUM(D54:D54) -> 1 | F54: 1484 | G54: 212 | H54: =F54*E54 -> 1484 | I54: =G54*E54 -> 212
F55: 0 | G55: 0
A56: 4.03 | B56: Circular Diffusers (with collar damper) | F56: 0 | G56: 0
B57: Powder coated, extruded aluminium, removable center core type, supply / return air diffusers without volume control dampers of aluminium construction of the following neck sizes.Measurement shall be based on outer to outer size of the air terminal device (colour for the grill to b confirmed by Arch/ PMC team before placing the order) | F57: 0 | G57: 0
B58: 250mm dia | C58: Nos | D58: 1 | E58: =SUM(D58:D58) -> 1 | F58: 1696 | G58: 212 | H58: =F58*E58 -> 1696 | I58: =G58*E58 -> 212
B59: 315mm dia | C59: Nos | D59: 15 | E59: =SUM(D59:D59) -> 15 | F59: 1908 | G59: 212 | H59: =F59*E59 -> 28620 | I59: =G59*E59 -> 3180
F60: 0 | G60: 0
A61: 4.04 | B61: Powder coated, extruded aluminium, removable center core type, square tegular type diffusers of aluminium construction of the following neck sizes. The diffuser shall be mounted in the GI box (not in scope), with inlet connector suitable for flexible duct. GI Box & Flexible duct quantified seperately. ( colour to be confirmed by Arch/ PMC team before placing the order) | E61: =SUM(D61:D61) -> 0 | F61: 0 | G61: 0 | H61: =F61*E61 -> 0 | I61: =G61*E61 -> 0
B62: (All are of 600 x 600 MM Outer to Outer Size) | E62: =SUM(D62:D62) -> 0 | F62: 0 | G62: 0 | H62: =F62*E62 -> 0 | I62: =G62*E62 -> 0
A63: a | B63: 450 x 450 MM (Neck Size) | C63: Nos | D63: 30 | E63: =SUM(D63:D63) -> 30 | F63: 1590 | G63: 212 | H63: =F63*E63 -> 47700 | I63: =G63*E63 -> 6360
A64: b | B64: 375 x 375 MM (Neck Size) | C64: Nos | D64: 80 | E64: =SUM(D64:D64) -> 80 | F64: 1484 | G64: 212 | H64: =F64*E64 -> 118720 | I64: =G64*E64 -> 16960
A65: c | B65: 300 x 300 MM (Neck Size) | C65: Nos | D65: 5 | E65: =SUM(D65:D65) -> 5 | F65: 1431 | G65: 212 | H65: =F65*E65 -> 7155 | I65: =G65*E65 -> 1060
E66: =SUM(D66:D66) -> 0 | F66: 0 | G66: 0 | H66: =F66*E66 -> 0 | I66: =G66*E66 -> 0
A67: 4.05 | B67: Powder Coated grilles for supply and return distribution ( colour for the grill to b confirmed by Arch/ PMC team before placing the order) . Deflection of the grille shall be 0 / 15 / 30. same will be confirmed later. Single / 2 way / 4 way deflection shall be confirmed later. | C67: Sqm | D67: 2 | E67: =SUM(D67:D67) -> 2 | F67: 5035 | G67: 1272 | H67: =F67*E67 -> 10070 | I67: =G67*E67 -> 2544
A68: 4.06 | B68: Collar Dampers of opposed blade type made out of Aluminium alloy extrusion with anodised matt black finish (quantity including for diffusers & grills) | C68: Sqm | D68: 1 | E68: =SUM(D68:D68) -> 1 | F68: 6148 | G68: 1272 | H68: =F68*E68 -> 6148 | I68: =G68*E68 -> 1272
A69: 4.07 | B69: Powder Coated Curved grilles with collar damper for supply distribution in Oval duct ( colour for the grill to b confirmed by Arch/ PMC team before placing the order) . Deflection of the grille shall be 0 / 15 / 30. same will be confirmed later. | C69: Sqm | D69: 1 | E69: =SUM(D69:D69) -> 1 | F69: 15900 | G69: 1272 | H69: =F69*E69 -> 15900 | I69: =G69*E69 -> 1272
E70: =SUM(D70:D70) -> 0 | F70: 0 | G70: 0 | H70: =F70*E70 -> 0 | I70: =G70*E70 -> 0
A71: 4.08 | B71: Volume Control Dampers made out of 100 x 40 x 1.55 mm thick galavanised steel frame and blades of 1.55 mm galavanised sheet steel. For Rectangular & elliptical duct. | C71: Sqm | D71: 5 | E71: =SUM(D71:D71) -> 5 | F71: 6095 | G71: 1272 | H71: =F71*E71 -> 30475 | I71: =G71*E71 -> 6360
E72: =SUM(D72:D72) -> 0 | F72: 0 | G72: 0 | H72: =F72*E72 -> 0 | I72: =G72*E72 -> 0
A73: 4.09 | B73: Motorised On/off type volume Control Dampers made out of 100 x 40 x 1.55 mm thick galavanised steel frame and blades of 1.55 mm galavanised sheet steel | C73: Sqm | D73: QRO | E73: =SUM(D73:D73) -> 0 | F73: 0 | G73: 0 | H73: =F73*E73 -> 0 | I73: =G73*E73 -> 0
A74: 4.1 | B74: Actuators with control panel, panel should be compatible for third party BMS integration .necessary fire integrator should be consider in part HVA Cvendor scope | C74: Nos | D74: QRO | E74: =SUM(D74:D74) -> 0 | F74: 0 | G74: 0 | H74: =F74*E74 -> 0 | I74: =G74*E74 -> 0
E75: =SUM(D75:D75) -> 0 | F75: 0 | G75: 0 | H75: =F75*E75 -> 0 | I75: =G75*E75 -> 0
A76: 4.11 | B76: Motorized Modulating type low leakage air dampers for fresh air modulation with actuator complete with all accessories like Actuator,control panel etc and any necessary requirement which can perform the controlling the Damper. It shall be integrated with Co2 sensor and based on CO2 levels, damper shall be modulate. | C76: SQM | D76: QRO | E76: =SUM(D76:D76) -> 0 | F76: 0 | G76: 0 | H76: =F76*E76 -> 0 | I76: =G76*E76 -> 0
A77: 4.12 | B77: Supply & fixing of CO2 sensor for above fresh air same should be integrate with BMS system. | C77: NOS | D77: QRO | E77: =SUM(D77:D77) -> 0 | F77: 0 | G77: 0 | H77: =F77*E77 -> 0 | I77: =G77*E77 -> 0
A78: 4.13 | B78: ACTUATORS with control panel should be compatible for third party BMS integration .necessary fire integrator should be consider in part HVACvendor scope | C78: NOS | D78: QRO | E78: =SUM(D78:D78) -> 0 | F78: 0 | G78: 0 | H78: =F78*E78 -> 0 | I78: =G78*E78 -> 0
E79: =SUM(D79:D79) -> 0 | F79: 0 | G79: 0 | H79: =F79*E79 -> 0 | I79: =G79*E79 -> 0
A80: 4.14 | B80: Insulated Flexible Ducting | E80: =SUM(D80:D80) -> 0 | F80: 0 | G80: 0 | H80: =F80*E80 -> 0 | I80: =G80*E80 -> 0
B81: Factory Fabricated Insulated Flexible made out aluminium for connecting from main duct to diffuser box. The length of the flexible duct shall be around 1.0 to 1.5 mtr | E81: =SUM(D81:D81) -> 0 | F81: 0 | G81: 0 | H81: =F81*E81 -> 0 | I81: =G81*E81 -> 0
B82: The flexible duct shall me made of double lamination of aluminium foil, polyester and metalised polyester film permanently bonded to a coated spring steel wire helix. The exterior shal be wrapped with 25mm thick 16 kg / cum fibreglass insulation. The outer insulation jacket / vapour barrier made of fibreglass reinforced metalised polyester film laminate. (jubilee clamp at both end need to provide) | E82: =SUM(D82:D82) -> 0 | F82: 0 | G82: 0 | H82: =F82*E82 -> 0 | I82: =G82*E82 -> 0
A83: a | B83: 150 mm dia ( uninsulated flexible duct) | C83: Rmt | E83: =SUM(D83:D83) -> 0 | F83: 0 | G83: 0 | H83: =F83*E83 -> 0 | I83: =G83*E83 -> 0
A84: b | B84: 200 mm dia | C84: Rmt | D84: 10 | E84: =SUM(D84:D84) -> 10 | F84: 371 | G84: 143.1 | H84: =F84*E84 -> 3710 | I84: =G84*E84 -> 1431
A85: c | B85: 250 mm dia | C85: Rmt | D85: 75 | E85: =SUM(D85:D85) -> 75 | F85: 424 | G85: 143.1 | H85: =F85*E85 -> 31800 | I85: =G85*E85 -> 10732.5
A86: d | B86: 300 mm dia | C86: Rmt | D86: 25 | E86: =SUM(D86:D86) -> 25 | F86: 487.6 | G86: 143.1 | H86: =F86*E86 -> 12190 | I86: =G86*E86 -> 3577.5
A87: e | B87: 350 mm dia | C87: Rmt | E87: =SUM(D87:D87) -> 0 | F87: 0 | G87: 0 | H87: =F87*E87 -> 0 | I87: =G87*E87 -> 0
A88: f | B88: 150 mm dia uninsulated flexible duct | C88: Rmt | D88: 50 | E88: =SUM(D88:D88) -> 50 | F88: 667.8 | G88: 143.1 | H88: =F88*E88 -> 33390 | I88: =G88*E88 -> 7155
A89: 4.15 | B89: Butterfly Dampers-22 Guage | E89: =SUM(D89:D89) -> 0 | F89: 0 | G89: 0 | H89: =F89*E89 -> 0 | I89: =G89*E89 -> 0
A90: a | B90: 150 mm dia | C90: Nos | D90: 25 | E90: =SUM(D90:D90) -> 25 | F90: 583 | G90: 143.1 | H90: =F90*E90 -> 14575 | I90: =G90*E90 -> 3577.5
A91: b | B91: 200 mm dia | C91: Nos | D91: 5 | E91: =SUM(D91:D91) -> 5 | F91: 689 | G91: 143.1 | H91: =F91*E91 -> 3445 | I91: =G91*E91 -> 715.5
A92: c | B92: 250 mm dia | C92: Nos | D92: 45 | E92: =SUM(D92:D92) -> 45 | F92: 795 | G92: 143.1 | H92: =F92*E92 -> 35775 | I92: =G92*E92 -> 6439.5
A93: d | B93: 300 mm dia | C93: Nos | D93: 15 | E93: =SUM(D93:D93) -> 15 | F93: 901 | G93: 143.1 | H93: =F93*E93 -> 13515 | I93: =G93*E93 -> 2146.5
A94: e | B94: 350 mm dia | C94: Nos | E94: =SUM(D94:D94) -> 0 | F94: 0 | G94: 0 | H94: =F94*E94 -> 0 | I94: =G94*E94 -> 0
E95: =SUM(D95:D95) -> 0 | F95: 0 | G95: 0 | H95: =F95*E95 -> 0 | I95: =G95*E95 -> 0
A96: 4.16 | B96: Rigid round ducts fabricated out of 22 G sheets to be used as extention pieces at the diffuser boxes. | E96: =SUM(D96:D96) -> 0 | F96: 0 | G96: 0 | H96: =F96*E96 -> 0 | I96: =G96*E96 -> 0
A97: a | B97: 250mm dia | C97: Rmt | D97: 25 | E97: =SUM(D97:D97) -> 25 | F97: 848 | G97: 106 | H97: =F97*E97 -> 21200 | I97: =G97*E97 -> 2650
A98: b | B98: 300mm dia | C98: Rmt | D98: 5 | E98: =SUM(D98:D98) -> 5 | F98: 1007 | G98: 106 | H98: =F98*E98 -> 5035 | I98: =G98*E98 -> 530
E99: =SUM(D99:D99) -> 0 | F99: 0 | G99: 0 | H99: =F99*E99 -> 0 | I99: =G99*E99 -> 0
A100: 4.17 | B100: SPILL AIR BOXES | E100: =SUM(D100:D100) -> 0 | F100: 0 | G100: 0 | H100: =F100*E100 -> 0 | I100: =G100*E100 -> 0
A101: a | B101: Supply,installation,testing & comissioning of 525 x 525 x 450 mm High Sheet Metal Spill air boxes made out of 26 GI sheet for connecting the diffuser outlet & flexible connection from the main duct. (10 mm internal acoustic insullation to be provided) cost inclusive of the item | C101: Nos | D101: 45 | E101: =SUM(D101:D101) -> 45 | F101: 1961 | G101: 212 | H101: =F101*E101 -> 88245 | I101: =G101*E101 -> 9540
A102: b | B102: Supply,installation,testing & comissioning of 1200 x 150 x 450x250dia mm High Sheet Metal Spill air boxes made out of 26 GI sheet for connecting the diffuser outlet & flexible connection from the main duct.(10 mm internal acoustic insullation to be provided) cost inclusive of the item | C102: Nos | D102: 1 | E102: =SUM(D102:D102) -> 1 | F102: 2544 | G102: 212 | H102: =F102*E102 -> 2544 | I102: =G102*E102 -> 212
...

Sheet VAV
A1: VAF SYSTEM BOQ
A2: S.NO | B2: DESCRIPTION | C2: UNIT | D2: 1F | E2: Total Qty | F2: IN INR | H2: IN INR
F3: SUPPLY RATE | G3: INSTALLATION RATE | H3: SUPPLY AMOUNT | I3: INSTALLATION AMOUNT
A5: I | B5: Supply , Installation,testing & commsitioning of following including frieght, local transportation upto site , handing over
B6: VARIABLE AIR VOLUME BOXES (Damper Actuator Type)
A8: 1 | B8: Supply , Installation,testing & commsitioning Variable Air Volume (VAV) Units are fabricated out of heavy gauge steel, mechanically sealed with gasketed & leak resistance construction. Both supply & discharge shall be suitable for duct connections. VAV Boxes Shall be self addressable type. Temperature sensor for the Cabins should be provided with selector swtich which has a selection range from 18 deg C till 30 deg C & for workstations / open office areas, it shall be thermostat without any selector switch
B9: Boxes shall be of variable air volume at the inlet and variable at outlet and shall be fitted with air volume regulator of the fully proportional type.
B10: The boxes shall be supplied with all internal attenuation treatment and acoustical damped casing necessary to achieve the required noise criteria. Casing shall be 20 BG minimum fitted with a completely sealed, easily removable means of access to all internal parts. Access to all boxes must be from the underside only.
B11: Maximum allowable static pressure to the boxes for its satisfactory operation shall not exceed 0.20” WG
B12: Boxes shall be able to reset any air flow between zero and the maximum air quantity that the boxes can handle without changing orifices or other parts. Air quantity limiters will not be accepted.
B13: A suitable device shall be provided for the field adjustment of minimum air flow. All boxes shall be intially factory set at minimum air quantity of 50% of the design requirements. Under shut-off conditions, all boxes shall not have air leakage more than 20% of the maximum air quantity.
B14: VAV Unit shall be ceiling suspended with hanger brackets & vibration isolators.
B15: All accessories listed under specifications should be considered for pricing VAVs
B16: Direct Output temperature sensor comprising of high quality thermistor or platinum sensing element should be supplied with VAVs.
B17: The look of the sensor should be rectangular in shape as shown in our schedule drawings showing vav box quantities. Projection of the sensor should not exceed 27 mm .
B18: Necessary Hardware/ software for integrating the VAV Boxes to the third party system which shall be capable of transferring 4 points as specified in the technical specification for the quantity indicated below shall also be considered in the scope. BAcent protocol to be considered for VAV centralized integrator and cost of the same to be inclusive
B19: All thermostats shall be digital type.
B20: Cat 6 - Communication cable between VAV and thermostat to be considered along with 19 mm dia PVC conduits @ 12 mtr per VAV as part of this scope. Flexible conduits of 19 mm dia to be considered for either end conection
B21: In Open ceiling area powder coated tray support to be provided from ceiling 600mm for thermostat fixing coordinate with PMC before installations with necessary supporting materials.
A22: 1.1 | B22: Rectangular/Elliptical Unit shall be of the following sizes : Cost shold be quote accordinling as per tender drawing
A24: a | B24: 0-250 CFM
B25: Supply & Installation of VAV boxes | C25: Nos | E25: =SUM(D25:D25) -> 0 | H25: =E25*F25 -> 0 | I25: =G25*E25 -> 0
A27: b | B27: 251-500 CFM
B28: Supply & Installation of VAV boxes | C28: Nos | D28: 1 | E28: =SUM(D28:D28) -> 1 | F28: 22790 | G28: 1961 | H28: =E28*F28 -> 22790 | I28: =G28*E28 -> 1961
F29: 0 | G29: 0
A30: c | B30: 501-750 CFM | F30: 0 | G30: 0
B31: Supply & Installation of VAV boxes | C31: Nos | E31: =SUM(D31:D31) -> 0 | F31: 0 | G31: 0 | H31: =E31*F31 -> 0 | I31: =G31*E31 -> 0
F32: 0 | G32: 0
A33: d | B33: 751-1000Cfm | F33: 0 | G33: 0
B34: Supply & Installation of VAV boxes | C34: Nos | E34: =SUM(D34:D34) -> 0 | F34: 0 | G34: 0 | H34: =E34*F34 -> 0 | I34: =G34*E34 -> 0
F35: 0 | G35: 0
A36: e | B36: 1001-1250Cfm | F36: 0 | G36: 0
B37: Supply & Installation of VAV boxes | C37: Nos | E37: =SUM(D37:D37) -> 0 | F37: 0 | G37: 0 | H37: =E37*F37 -> 0 | I37: =G37*E37 -> 0
F38: 0 | G38: 0
A39: f | B39: 1251-1500Cfm | F39: 0 | G39: 0
B40: Supply & Installation of VAV boxes | C40: Nos | E40: =SUM(D40:D40) -> 0 | F40: 0 | G40: 0 | H40: =E40*F40 -> 0 | I40: =G40*E40 -> 0
F41: 0 | G41: 0
A42: g | B42: 1501-1750Cfm | F42: 0 | G42: 0
B43: Supply & Installation of VAV boxes | C43: Nos | E43: =SUM(D43:D43) -> 0 | F43: 0 | G43: 0 | H43: =E43*F43 -> 0 | I43: =G43*E43 -> 0
F44: 0 | G44: 0
A45: h | B45: 1751-2000Cfm | F45: 0 | G45: 0
B46: Supply & Installation of VAV boxes | C46: Nos | D46: 1 | E46: =SUM(D46:D46) -> 1 | F46: 26500 | G46: 1908 | H46: =E46*F46 -> 26500 | I46: =G46*E46 -> 1908
F47: 0 | G47: 0
A48: i | B48: 2001-2250Cfm | F48: 0 | G48: 0
B49: Supply & Installation of VAV boxes | C49: Nos | E49: =SUM(D49:D49) -> 0 | F49: 0 | G49: 0 | H49: =E49*F49 -> 0 | I49: =G49*E49 -> 0
F50: 0 | G50: 0
A51: j | B51: 2251-2500Cfm | F51: 0 | G51: 0
B52: Supply & Installation of VAV boxes | C52: Nos | E52: =SUM(D52:D52) -> 0 | F52: 0 | G52: 0 | H52: =E52*F52 -> 0 | I52: =G52*E52 -> 0
F53: 0 | G53: 0
A54: k | B54: 2501-2750Cfm | F54: 0 | G54: 0
B55: Supply & Installation of VAV boxes | C55: Nos | E55: =SUM(D55:D55) -> 0 | F55: 0 | G55: 0 | H55: =E55*F55 -> 0 | I55: =G55*E55 -> 0
F56: 0 | G56: 0
A57: l | B57: 2751-3000Cfm | F57: 0 | G57: 0
B58: Supply & Installation of VAV boxes | C58: Nos | E58: =SUM(D58:D58) -> 0 | F58: 0 | G58: 0 | H58: =E58*F58 -> 0 | I58: =G58*E58 -> 0
F59: 0 | G59: 0
A60: m | B60: 3001-3250Cfm | F60: 0 | G60: 0
B61: Supply & Installation of VAV boxes | C61: Nos | E61: =SUM(D61:D61) -> 0 | F61: 0 | G61: 0 | H61: =E61*F61 -> 0 | I61: =G61*E61 -> 0
F62: 0 | G62: 0
A63: n | B63: 3251-3500Cfm | F63: 0 | G63: 0
B64: Supply & Installation of VAV boxes | C64: Nos | E64: =SUM(D64:D64) -> 0 | F64: 0 | G64: 0 | H64: =E64*F64 -> 0 | I64: =G64*E64 -> 0
F65: 0 | G65: 0
A66: o | B66: 3501-3750Cfm | F66: 0 | G66: 0
B67: Supply & Installation of VAV boxes | C67: Nos | E67: =SUM(D67:D67) -> 0 | F67: 0 | G67: 0 | H67: =E67*F67 -> 0 | I67: =G67*E67 -> 0
F68: 0 | G68: 0
A69: s | B69: Supply , Installation,testing & commsitioning of 2core, 1.5 Sqmm, screened ATC/sheathed cable communication cable in PVC Conduit of 19 mm dia for looping between VAV’S & BMS necessary supporting materials link clamp & screw to be considered | C69: Rmt | D69: =SUM(D25:D67)*15 -> 30 | E69: =SUM(D69:D69) -> 30 | F69: 137.8 | G69: 53 | H69: =E69*F69 -> 4134 | I69: =G69*E69 -> 1590
F70: 0 | G70: 0
B71: NOTE:Looping all VAV's with communication cable & leaving the cable inside BMS room and coordinating with BMS vendor is part of HVAC vendor scope | F71: 0 | G71: 0
F72: 0 | G72: 0
A73: t | B73: Suplly, installation testing & commissioning of duct pressure sensor in the rang of 0 to 500 Pascal. | C73: Nos | E73: =SUM(D73:D73) -> 0 | F73: 0 | G73: 0 | H73: =E73*F73 -> 0 | I73: =G73*E73 -> 0
F74: 0 | G74: 0
A75: u | B75: Supply, laying & Termincation of 2C X 1sq.mm copper sheiled Control cable between VFD and Duct Temperature sensor | C75: Rmt | D75: 20 | E75: =SUM(D75:D75) -> 20 | F75: 137.8 | G75: 53 | H75: =E75*F75 -> 2756 | I75: =G75*E75 -> 1060
A76: v | B76: Supply & fixing of 16G M.S.Conduit for cable laid between VFD and Duct Temperature sensor | C76: Rmt | D76: 20 | E76: =SUM(D76:D76) -> 20 | F76: 137.8 | G76: 42.4 | H76: =E76*F76 -> 2756 | I76: =G76*E76 -> 848
F77: 0 | G77: 0
A78: y | B78: All necessary Network controller or Router, Interface to connect the proposed floor BACNET MS/TP VAV with the main BMS system via Native BACnet / IP. Network controller or Router - Shall automatic rout BACnet messages between BACnet IP, BACnet Ethernet, BACnet PTP, and BACnet MS/TP ports and sub-lan networks. It shall conformance to ANSI/ASHRAE standard 135-2008 for designated “router” functions. The controller shall support foreign device registration with BACnet Broadcast Management Devices (BBMD). Total no. of network controller shall be based on manufacturer requirement. 1 network controller / router panel shall not exceed integrating / connecting 30 VAV boxes. The Network controller or Router shall be housed in a suitable metal enclosure with proper power protection. Integrator to have necessary convertors for taking into BOS system | C78: Nos | E78: =SUM(D78:D78) -> 0 | F78: 0 | G78: 0 | H78: =E78*F78 -> 0 | I78: =G78*E78 -> 0
B80: Note1: VAV quantity will vary if any changes in architectural drawings
B82: SUB TOTAL | H82: =SUM(H22:H79) -> 58936 | I82: =SUM(I22:I79) -> 7367

Sheet VRF SYSTEM
A1: VRF SYSTEM BOQ
A2: SL NO | B2: Description | C2: Unit | D2: 1F | E2: TOTAL QTY | F2: IN INR | H2: IN INR | J2: Remarks
F3: SUPPLY RATE | G3: INSTALLATION RATE | H3: SUPPLY AMOUNT | I3: INSTALLATION AMOUNT
B4: Supply, Installation, Testing & Commissioning & Handing over of the following:
A6: A | B6: VRF AIR-CONDITIONING EQUIPMENTS:(100% INVERTER TYPE ONLY TO BE QUOTED) - R410A refrigerant
A7: 1 | B7: Supply & Installation of VRF airconditioning system comprising of Modular type high efficiency Twin Rotary Multiple Compressor with inverter, High efficiency heat transfer Cooling Coil suitable for Environment friendly R410a refrigerant,Air cooled propeller type condenser fan with DC motor drive,interconnecting piping, suction line insulation etc., Micro-processor control panel suitable for automatic operation,High speed calculation inverter control, active oil control mechanism incorporating all safety functions as per equipment specifications & other points as listed below:
B8: The unit mounted starter panel shall be complete with IP-55 protection consisting of power disconnecting switches with fuses, soft starters, for compressor motors, under/over voltage trip, single phase preventers, communication card which can accept 4-20 mA or 2-10 Vdc analog signal.
B9: All components shall be mounted on welded steel base frame, structural steel profiles/panels made out of galvanized sheet steel, protected with primary coat & finished with epoxy paint.
B10: Modular type outdoor units equipped with highly efficient scroll compressors, with inverter type compressor(s),special acryl precoated heat exchanger,low noise condenser fan,auto check function for connection error, auto address & UNIT Price shall be inclusive of outdoor stand price.Shifting & Installing of ODU as per shop drawing is part VRV vendor scope.(ODU Location & Capacity mentioned below).Shifting of Out door units from GF to Terrace floor is part of VRF vendor scope
B11: The unit shall be sized to deliver following rated capacities minimum including de-rated capacity due to ambient temperature of 36 Deg C DB
B12: All VRV units should be compatible for third party BMS integration .necessary fire and BMS integrator should be consider in part HVAC/VRF vendor scope
A13: 1.01 | B13: Outdoor Unit(ODU) : Cooling Capacity : 6HP SIDE/TOP DISCHARGE Based on site condition (Café) | C13: Set | D13: 1 | E13: =SUM(D13:D13) -> 1 | F13: 135680 | G13: 12720 | H13: =F13*E13 -> 135680 | I13: =G13*E13 -> 12720
A14: 1.02 | B14: Outdoor Unit(ODU) : Cooling Capacity : 8HP SIDE/TOP DISCHARGE Based on site condition(Crtical room working) | C14: Set | D14: 1 | E14: =SUM(D14:D14) -> 1 | F14: 174900 | G14: 16960 | H14: =F14*E14 -> 174900 | I14: =G14*E14 -> 16960
A15: 1.03 | B15: Outdoor Unit(ODU) : Cooling Capacity : 10HP SIDE/TOP DISCHARGE Based on site condition (critical room standby) | C15: Set | D15: 1 | E15: =SUM(D15:D15) -> 1 | F15: 188680 | G15: 21200 | H15: =F15*E15 -> 188680 | I15: =G15*E15 -> 21200
A16: B | B16: INDOOR UNITS | F16: 0 | G16: 0
B17: Indoor Unit(IDU): Cooling type : All the units should be supplied with Cordless remote control. The following Indoor unit capacities are required for each type of Room.Drycontact should be considered for Auto change over,failure status,overload sequencing etc.. | F17: 0 | G17: 0
A18: 1.04 | B18: Serving Area: CAFETERIA 4.1 TR Ductable unit | C18: Nos | D18: 1 | E18: =SUM(D18:D18) -> 1 | F18: 47170 | G18: 6360 | H18: =F18*E18 -> 47170 | I18: =G18*E18 -> 6360
A19: 1.05 | B19: Serving Area: UPS & BATTERY ROOM 3.0 TR Ductable unit | C19: Nos | D19: 2 | E19: =SUM(D19:D19) -> 2 | F19: 40810 | G19: 6360 | H19: =F19*E19 -> 81620 | I19: =G19*E19 -> 12720
A20: 1.06 | B20: Serving Area: SERVER ROOM 3.0 TR Ductable unit | C20: Nos | D20: 2 | E20: =SUM(D20:D20) -> 2 | F20: 40810 | G20: 6360 | H20: =F20*E20 -> 81620 | I20: =G20*E20 -> 12720
A21: 1.07 | B21: Serving Area: 2.0 TR Hi-wall unit | C21: Nos | D21: QRO | E21: =SUM(D21:D21) -> 0 | F21: 0 | G21: 0 | H21: =F21*E21 -> 0 | I21: =G21*E21 -> 0
A22: 1.08 | B22: Serving Area: 1.5 TR Hi-wall unit | C22: Nos | D22: QRO | E22: =SUM(D22:D22) -> 0 | F22: 0 | G22: 0 | H22: =F22*E22 -> 0 | I22: =G22*E22 -> 0
A23: 1.09 | B23: Serving Area: 1.0 TR Hi-wall unit | C23: Nos | D23: QRO | E23: =SUM(D23:D23) -> 0 | F23: 0 | G23: 0 | H23: =F23*E23 -> 0 | I23: =G23*E23 -> 0
A24: 1.1 | B24: Serving Area: BMS ROOM 1.65 TR Compact cassette unit | C24: Nos | D24: 1 | E24: =SUM(D24:D24) -> 1 | F24: 35722 | G24: 3498 | H24: =F24*E24 -> 35722 | I24: =G24*E24 -> 3498
A25: 1.11 | B25: Serving Area: 2.0 TR cassette unit | C25: Nos | D25: QRO | E25: =SUM(D25:D25) -> 0 | F25: 0 | G25: 0 | H25: =F25*E25 -> 0 | I25: =G25*E25 -> 0
A26: 1.1 | B26: Serving Area: Visitors meeting room 1 TR Compact cassette unit | C26: Nos | D26: 1 | E26: =SUM(D26:D26) -> 1 | F26: 33708 | G26: 3498 | H26: =F26*E26 -> 33708 | I26: =G26*E26 -> 3498
F27: 0 | G27: 0
A28: C | B28: REFRIGERANT PIPING | F28: 0 | G28: 0
A29: 1.12 | B29: Interconnecting copper refrigerant pipe work duly insulated with elastomeric nitrile rubber type tubular insulation between indoor & outdoor units as per specifications . All piping inside the room shall be properly supported with hanger and all piping should be run in perforated cably tray.Cable tray qty specified seperately.. MS supports for refrigerant piping & cables, using angles, channels, Tees, flats, etc should be considered as part of scope.All MS supports shall be given a coat of red-oxide primer and two coats of synthetic enamel paint of approved colour. | F29: 0 | G29: 0 | J29: Quantity updated as per builder input ODU located at terrace level.
B30: 41.3mm OD (insulation =19 mm thick) | C30: Rmt | E30: =SUM(D30:D30) -> 0 | F30: 0 | G30: 0 | H30: =F30*E30 -> 0 | I30: =G30*E30 -> 0
B31: 34.3mm OD (insulation =19 mm thick) | C31: Rmt | E31: =SUM(D31:D31) -> 0 | F31: 0 | G31: 0 | H31: =F31*E31 -> 0 | I31: =G31*E31 -> 0
B32: 28.6mm OD (insulation =19 mm thick) | C32: Rmt | D32: 5 | E32: =SUM(D32:D32) -> 5 | F32: 1272 | G32: 106 | H32: =F32*E32 -> 6360 | I32: =G32*E32 -> 530
B33: 22.2mm OD (insulation =13 mm thick) | C33: Rmt | D33: 75 | E33: =SUM(D33:D33) -> 75 | F33: 954 | G33: 106 | H33: =F33*E33 -> 71550 | I33: =G33*E33 -> 7950
B34: 19.1mm OD (insulation =13 mm thick) | C34: Rmt | D34: 150 | E34: =SUM(D34:D34) -> 150 | F34: 750 | G34: 106 | H34: =F34*E34 -> 112500 | I34: =G34*E34 -> 15900
B35: 15.9mm OD (insulation =13 mm thick) | C35: Rmt | D35: 50 | E35: =SUM(D35:D35) -> 50 | F35: 600 | G35: 106 | H35: =F35*E35 -> 30000 | I35: =G35*E35 -> 5300
B36: 12.7mm OD (insulation =13 mm thick) | C36: Rmt | D36: 60 | E36: =SUM(D36:D36) -> 60 | F36: 500 | G36: 106 | H36: =F36*E36 -> 30000 | I36: =G36*E36 -> 6360
B37: 9.5mm OD (insulation =13 mm thick) | C37: Rmt | D37: 280 | E37: =SUM(D37:D37) -> 280 | F37: 400 | G37: 106 | H37: =F37*E37 -> 112000 | I37: =G37*E37 -> 29680
B38: 6.4mm OD (insulation =13 mm thick) | C38: Rmt | D38: 10 | E38: =SUM(D38:D38) -> 10 | F38: 300 | G38: 106 | H38: =F38*E38 -> 3000 | I38: =G38*E38 -> 1060
A39: D | B39: DRAIN PIPE | F39: 0 | G39: 0
A40: 1.13 | B40: Insulated Condensate Drain Piping | F40: 0 | G40: 0
B41: Supply Insulated PVC Condensate Drain piping as per specification as mentioned in the document insulated same as chilled water piping but without polyshield covering.Consider drip pans with drian pipe .Entire draine pipe needs to be insulated with Nitrile rubber. | F41: 0 | G41: 0
B42: 40 mm dia | C42: Rmt | D42: 20 | E42: =SUM(D42:D42) -> 20 | F42: 450.5 | G42: 53 | H42: =F42*E42 -> 9010 | I42: =G42*E42 -> 1060
B43: 32 mm dia | C43: Rmt | D43: 35 | E43: =SUM(D43:D43) -> 35 | F43: 392.2 | G43: 53 | H43: =F43*E43 -> 13727 | I43: =G43*E43 -> 1855
B44: 25 mm dia | C44: Rmt | D44: 20 | E44: =SUM(D44:D44) -> 20 | F44: 339.2 | G44: 53 | H44: =F44*E44 -> 6784 | I44: =G44*E44 -> 1060
A45: 1.14 | B45: Electrical Cable between Isolator to ODU.Suitable size copper flexible cable with necessary earthing insulation | C45: Rmt | D45: 30 | E45: =SUM(D45:D45) -> 30 | F45: 265 | G45: 53 | H45: =F45*E45 -> 7950 | I45: =G45*E45 -> 1590
A46: 1.15 | B46: Providing & fixing of 2 Cx 1.5 sqmm cu. cable for control cum trans-mission between Indoor unit and Out Door Unit through PVC Conduit. | C46: Rmt | D46: 330 | E46: =SUM(D46:D46) -> 330 | F46: 118.72 | G46: 31.8 | H46: =F46*E46 -> 39177.6 | I46: =G46*E46 -> 10494 | J46: Quantity updated as per builder input ODU located at terrace level.
B47: Note:Cable from Electrical panel to isolator excluded in VRV vendor scope.same should capture in Electrical vendor scope. Cable from Isolator to ODU is part of VRV Vendorscope. | F47: 0 | G47: 0
A48: 1.16 | B48: Imported fittings like Y-Joints and headers etc as per the layout( additional supports should consider for both ends of the Y joint) | C48: Nos | D48: 4 | E48: =SUM(D48:D48) -> 4 | F48: 5406 | G48: 530 | H48: =F48*E48 -> 21624 | I48: =G48*E48 -> 2120
F49: 0 | G49: 0
A50: 1.17 | B50: Supply & providing of MS stand for VRV ODU along with proper supports-suitable for above configuration | C50: Set | D50: 3 | E50: =SUM(D50:D50) -> 3 | F50: 15900 | G50: 1590 | H50: =F50*E50 -> 47700 | I50: =G50*E50 -> 4770
F51: 0 | G51: 0
A52: 1.18 | B52: Filling, testing, commissioning including topping up of R410 A Refrigerant. | C52: Kg | D52: 35 | E52: =SUM(D52:D52) -> 35 | F52: 901 | G52: 106 | H52: =F52*E52 -> 31535 | I52: =G52*E52 -> 3710 | J52: Quantity updated as per builder input ODU located at terrace level.
F53: 0 | G53: 0
A54: E | B54: CABLE TRAY | F54: 0 | G54: 0
A55: 1.19 | B55: Supply & providing of GI Powder coaded cable tray (perforated type) of for routing copper pipes at terrace level. | F55: 0 | G55: 0 | J55: Quantity updated as per builder input ODU located at terrace level.
B56: size:150x 50mm(14 SWG grade)-2mm thick | C56: Rmt | D56: 120 | E56: =SUM(D56:D56) -> 120 | F56: 593.6 | G56: 143.1 | H56: =F56*E56 -> 71232 | I56: =G56*E56 -> 17172
B57: size:300x 100mm with cover (14 SWG grade)-2mm thick Only for Exposed & Vertical shaft area | C57: Rmt | D57: 90 | E57: =SUM(D57:D57) -> 90 | F57: 1113 | G57: 196.1 | H57: =F57*E57 -> 100170 | I57: =G57*E57 -> 17649
B58: size:450x 100mm with cover (14 SWG grade)-2mm thick Only for Exposed area | C58: Rmt | D58: 20 | E58: =SUM(D58:D58) -> 20 | F58: 1431 | G58: 222.6 | H58: =F58*E58 -> 28620 | I58: =G58*E58 -> 4452
B59: size:600x 100mm with cover (14 SWG grade)-2mm thick Only for Exposed area | C59: Rmt | E59: =SUM(D59:D59) -> 0 | F59: 1961 | G59: 254.4 | H59: =F59*E59 -> 0 | I59: =G59*E59 -> 0
F60: 0 | G60: 0
A61: F | B61: DRIP TRAY | F61: 0 | G61: 0
A62: 1.2 | B62: Supply & installation,testing & comissioning of Drip Tray with inner nitrile rubber insulation with necesssary supports | C62: Nos | D62: 6 | E62: =SUM(D62:D62) -> 6 | F62: 3975 | G62: 636 | H62: =F62*E62 -> 23850 | I62: =G62*E62 -> 3816
F63: 0 | G63: 0
A64: G | B64: CENTRAL CONTROLLER & REMOTE SYSTEM | F64: 0 | G64: 0
A65: 1.21 | B65: Supply & installation,testing & comissioning of Centarl controller integrating all floor Indoor units with necessary software & spare parts | C65: Lot | D65: 1 | E65: =SUM(D65:D65) -> 1 | F65: 117878 | G65: 2120 | H65: =F65*E65 -> 117878 | I65: =G65*E65 -> 2120
F66: 0 | G66: 0 | H66: =F66*E66 -> 0 | I66: =G66*E66 -> 0
A67: H | B67: DRAIN PUMP | F67: 0 | G67: 0
A68: a | B68: Supply installation testing & commissioning of 2 litre drain pump with all necessary supports | C68: QRO-Nos | D68: 0 | E68: =SUM(D68:D68) -> 0 | F68: 0 | G68: 0 | H68: =F68*E68 -> 0 | I68: =G68*E68 -> 0
F69: 0 | G69: 0 | H69: =F69*E69 -> 0 | I69: =G69*E69 -> 0
A70: b | B70: 2 Litre SS storage tank with 2 inbuilt drain pumps (1W+1S). Tank and pumps shall be housed in a tray and supported to wall/ceiling as per site conditions sholud be BMS compactabilit | C70: Set | D70: QRO | E70: =SUM(D70:D70) -> 0 | F70: 0 | G70: 0 | H70: =F70*E70 -> 0 | I70: =G70*E70 -> 0
B72: GRAND TOTAL EXCLUDING TAXES | H72: =SUM(H4:H71) -> 1663767.6 | I72: =SUM(I4:I71) -> 228324

Sheet HVAC-APPROVED MAKES
A1: LIST OF APPROVED MAKES - HVAC
A2: Sl.No | B2: Description | C2: Makes
A3: 1 | B3: EAU / VAUs / Ceiling Suspended units/ AHU’s | C3: VTS | D3: Zeco | E3: Flakwoods | F3: Systemair
A4: 2 | B4: Double Skin Plenum | C4: Zeco | D4: Seven star | E4: Shree venus | F4: Wester air dcut
A5: 3 | B5: Sound Attenuators | C5: Wester air dcut | D5: Seven star | E5: Shree venus
A6: 4 | B6: VRF System | C6: Daikin | D6: Blue Star
A7: 5 | B7: Dx-units | C7: Daikin | D7: Blue Star
A8: 6 | B8: Low Noise Exhaust Fans / Kitchen Exhaust Fans / Online Fans | C8: Green heck | D8: Dyanair | E8: Systemair | F8: Kruger
A9: 7 | B9: Combined Smoke & Fire Dampers | C9: Green heck | D9: Airmaster | E9: Systemair | F9: Cosmic | G9: Carriyare
A10: 8 | B10: Grilles ,diffusers & Disc valves | C10: Air Master | D10: Caryaire | E10: Systemair | F10: Cosmic | G10: Carriyare
A11: 9 | B11: Galvanised Sheet Steel | C11: SAIL | D11: Jindal | E11: Tata
A12: 10 | B12: MS Pipes | C12: Jindal | D12: Tata steel | E12: Sail
A13: 11 | B13: Wire support | C13: Hilti | D13: 3M
A14: 12 | B14: Duct Insulation / Acoustic Lining / Under Deck Insulation / Chilled Water Pipe Insulation | C14: Armaflex | D14: Aeroflex | E14: K flex
A15: 13 | B15: VAV | C15: JCI | D15: Honey well | E15: Siemens | F15: Belimo
A16: 14 | B16: Duct Fabrication | C16: Sevenstar | D16: Shree venus | E16: Zeco | F16: Wester air dcut | G16: Air Q
A17: 15 | B17: Butterfly Dampers | C17: Airmaster | D17: Caryaire | E17: Systemair | F17: Cosmic
A18: 16 | B18: Expansion Plenums (Acoustically Lined with ARMAFLEX Insulation) fabricated using CNC Machines | C18: Vedha duct | D18: Airmaster | E18: Caryaire
A19: 17 | B19: Fire Damper Actuators with Control Panel | C19: Belimo | D19: Siemens | E19: Sauter | F19: Airtech
A20: 18 | B20: Cable Trays | C20: Patni | D20: Profab | E20: Puspak
A21: 19 | B21: Insulated Flexible Ducting | C21: Caryaire | D21: Seven star | E21: Supaflex | F21: Uptwiga
A22: 20 | B22: Vibration isolators | C22: Dunlop | D22: Resistoflex
A23: 21 | B23: Sound attenuators | C23: Seven star | D23: Shree venus
A24: 22 | B24: Drain pipe | C24: Ashirvad | D24: Supreme | E24: Astral
A25: 23 | B25: Duct Supports | C25: Hilti | D25: Gripple
A26: 24 | B26: Fire sealent | C26: Hilti | D26: 3M
A27: 25 | B27: Spiral duct | C27: Sevenstar | D27: Spiral Tubes | E27: Karthila
A28: 26 | B28: Acoustic insullation | C28: UP Twiga
A29: 27 | B29: Copper pipes | C29: Nippon | D29: Rajco | E29: Mehta | F29: Uniflow
A30: 28 | B30: variable frequency drive | C30: Danfoss | D30: ABB
A31: 29 | B31: Bipolar Ionizers | C31: Plasma air

Sheet ELEC_Summary
A1: ELECTRICAL BOQ SUMMARY
A2: Sl.No | B2: DETAILS OF SPECIFICATION | C2: AMOUNT in INR
C3: SUPPLY | D3: ERECTION | E3: Total
A5: 1 | B5: SUPPLY & INSTALLATION OF LUMINAIRES | C5: =ELEC!G30 -> 2466832 | D5: =ELEC!H30 -> 103895.9 | E5: =D5+C5 -> 2570727.9
A7: 2 | B7: WIRING FOR LUMINAIRES | C7: =ELEC!G44 -> 768584.8 | D7: =ELEC!H44 -> 273024.2 | E7: =D7+C7 -> 1041609
A9: 3 | B9: POWER OUTLETS (SOCKETS) | C9: =ELEC!G64 -> 375464.18 | D9: =ELEC!H64 -> 67818.8 | E9: =D9+C9 -> 443282.98
A11: 4 | B11: CABLING FOR POWER OUTLETS | C11: =ELEC!G76 -> 817960.9 | D11: =ELEC!H76 -> 173840 | E11: =D11+C11 -> 991800.9
A13: 5 | B13: UNDER FLOOR CABLE MANAGEMENT SYSTEM | C13: =ELEC!G82 -> 227900 | D13: =ELEC!H82 -> 114480 | E13: =D13+C13 -> 342380
A15: 6 | B15: UNDER FLOOR JUNCTION BOXES | C15: =ELEC!G92 -> 53392.2 | D15: =ELEC!H92 -> 23807.6 | E15: =D15+C15 -> 77199.8
A17: 7 | B17: SECONDARY DISTRIBUTION SYSTEMS | C17: =ELEC!G169 -> 254203.9 | D17: =ELEC!H169 -> 21560.4 | E17: =D17+C17 -> 275764.3
A19: 8 | B19: PRIMARY DISTRIBUTION SYSTEM | C19: =ELEC!G204 -> 761080 | D19: =ELEC!H204 -> 63600 | E19: =D19+C19 -> 824680
A21: 9 | B21: POWER CABLES AND CABLE TERMINATION | C21: =ELEC!G295 -> 877227.38 | D21: =ELEC!H295 -> 325805.84 | E21: =D21+C21 -> 1203033.2
A23: 10 | B23: CEILING CABLE MANAGEMENT SYSTEM | C23: =ELEC!G337 -> 291166.1 | D23: =ELEC!H337 -> 47779.5 | E23: =D23+C23 -> 338945.6
A25: 11 | B25: EARTHING | C25: =ELEC!G345 -> 69960 | D25: =ELEC!H345 -> 14840 | E25: =D25+C25 -> 84800
A27: 12 | B27: EARTH FLAT BUS | C27: =ELEC!G356 -> 94013.52 | D27: =ELEC!H356 -> 15033.98 | E27: =D27+C27 -> 109047.5
A29: 13 | B29: SAFETY EQUIPMENTS | C29: =ELEC!G361 -> 4731.84 | D29: =ELEC!H361 -> 318 | E29: =D29+C29 -> 5049.84
A31: 14 | B31: ASSOCIATED ACCESSORIES | C31: =ELEC!G379 -> 78010.7 | D31: =ELEC!H379 -> 19154.2 | E31: =D31+C31 -> 97164.9
A33: 15 | B33: SHOP DRAWINGS, INSPECTION AND APPROVALS | C33: =ELEC!G382 -> 185000 | D33: =ELEC!H382 -> 5300 | E33: =D33+C33 -> 190300
B37: Sub total | C37: =SUM(C5:C36) -> 7325527.5 | D37: =SUM(D5:D36) -> 1270258.4 | E37: =SUM(E5:E36) -> 8595785.9
B39: Grand Total | C39: =D37+C37 -> 8595785.9

Sheet ELEC
A1: ELECTRICAL BOQ SUMMARY
A2: Sl.No | B2: DETAILS OF SPECIFICATION | C2: QTY | D2: UNIT | E2: RATE in INR | G2: AMOUNT in INR
E3: SUPPLY | F3: ERECTION | G3: SUPPLY | H3: ERECTION | J3: As per Measurement | K3: Amount
A4: 1 | B4: SUPPLY & INSTALLATION OF LUMINAIRES (UGR should be less than19), Warranty for LED light fixture should be 5 years. LED CCT and Luminaire Colour as per architect/client selection & CRI >80, THD <10 (CCT 4500K)
A6: a | B6: Supply, Installation, Testing & Commissioning of LED Suspended Continous LED Linear Profile Light. Minimum Guaranteed Technical Parameters should be: UGR <19 , System Luminous efficacy >90Lm/W, CRI >80, THD <10, SDCM<5, IP20. Wattage: ≈40W, LED CCT options: 5700/4000/3000 K. SPD should be provided with 3.5kV, Luminaire Dimension: L = 2385 mm X Width = 50 mm And its should be EXTRUDED AL Housing with Special grade low glare MPO diffuser. The supply of accessories like clamps, supporting brackets and hardwares as required and interconnecting with 3 core 1.5 sqmm PVC insulated FRLS copper wire with all accessories required as per site conditions, similar to Arraystorm Lighting Model No: ASCL5285SFXXIN040-8FT | C6: 10 | D6: Nos | E6: 3286 | F6: 291.5 | G6: =IFERROR(C6*E6,0) -> 32860 | H6: =IFERROR(C6*F6,0) -> 2915 | J6: 5 | K6: =J6*(E6) -> 16430
A7: b | B7: Supply, Installation, Testing & Commissioning of LED Suspended Continous LED Linear Profile Light. Minimum Guaranteed Technical Parameters should be: UGR <19 , System Luminous efficacy >90Lm/W, CRI >80, THD <10, SDCM<5, IP20. Wattage: ≈20W, LED CCT options: 5700/4000/3000 K. SPD should be provided with 3.5kV, Luminaire Dimension: L = 1195 mm X Width = 50 mm And its should be EXTRUDED AL Housing with Special grade low glare MPO diffuser. The supply of accessories like clamps, supporting brackets and hardwares as required and interconnecting with 3 core 1.5 sqmm PVC insulated FRLS copper wire with all accessories required as per site conditions similar to Arraystorm Lighting Model No: ASCL5285SFXXIN020-4FT | C7: 5 | D7: Nos | E7: 1727.8 | F7: 291.5 | G7: =IFERROR(C7*E7,0) -> 8639 | H7: =IFERROR(C7*F7,0) -> 1457.5 | J7: 1 | K7: =J7*(E7) -> 1727.8
A8: c | B8: Supply, Installation, Testing & Commissioning of LED Suspended Continous LED Linear Profile Light. Minimum Guaranteed Technical Parameters should be: UGR <19 , System Luminous efficacy >90Lm/W, CRI >80, THD <10, SDCM<5, IP20. Wattage: ≈30W, LED CCT options: 5700/4000/3000 K. SPD should be provided with 3.5kV, Luminaire Dimension: L = 1790 mm X Width = 50 mm And its should be EXTRUDED AL Housing with Special grade low glare MPO diffuser. The supply of accessories like clamps, supporting brackets and hardwares as required and interconnecting with 3 core 1.5 sqmm PVC insulated FRLS copper wire with all accessories required as per site conditions similar to Arraystorm Lighting Model No: ASCL5285SFXXIN030-6FT | C8: 0 | D8: Nos | E8: 5141 | F8: 291.5 | G8: =IFERROR(C8*E8,0) -> 0 | H8: =IFERROR(C8*F8,0) -> 0 | J8: 3 | K8: =J8*(E8) -> 15423
A9: d | B9: Supply, Installation, Testing & Commissioning of LED Recessed /Surface Troffer Light (2X2) Luminaire with a nominal system luminous efficacy >100 Lm/W and a Luminaire Wattage ≈ 30W with Electronic driver. Also Operating voltage of 140-270V with cut off and auto restart feature @325V. Power factor should be >0.95 & THD should be <10% & CRI>80. LED CCT options: 5700/4000/3000 K. LED Life should be 50,000Hrs. The luminaire should have Special low glare MPO diffuser. "Dimension :Length = 595 mm , Width = 595mm.The supply of accessories like clamps, supporting brackets and hardwares as required and interconnecting with 3 core 1.5 sqmm PVC insulated FRLS copper wire with all accessories required as per site conditions similiar to Arraystorm Lighting Model No: ASGL2016RFXXIN030 | C9: 115 | D9: Nos | E9: 1802 | F9: 212 | G9: =IFERROR(C9*E9,0) -> 207230 | H9: =IFERROR(C9*F9,0) -> 24380 | J9: 119 | K9: =J9*(E9) -> 214438
A10: e | B10: Supply, Installation, Testing & Commissioning of LED Recessed /Surface Troffer Light (2X2) Luminaire with a nominal system luminous efficacy >100 Lm/W and a Luminaire Wattage ≈ 30W . Provided with Analogue dimmable driver. Also Operating voltage of 140-270V with cut off and auto restart feature @325V. Power factor should be >0.95 & THD should be <10% & CRI>80. LED CCT options: 5700/4000/3000 K. LED Life should be 50,000Hrs. The luminaire should have Special low glare MPO diffuser. "Dimension :Length = 595 mm , Width = 595mm, Height= 50mm .The supply of accessories like clamps, supporting brackets and hardwares as required and interconnecting with 3 core 1.5 sqmm PVC insulated FRLS copper wire with all accessories required as per site conditions similiar to Arraystorm Lighting Model No: ASGL2015RFXXIN030-ANA | C10: 10 | D10: Nos | E10: 4558 | F10: 212 | G10: =IFERROR(C10*E10,0) -> 45580 | H10: =IFERROR(C10*F10,0) -> 2120 | J10: 10 | K10: =J10*(E10) -> 45580
A11: f | B11: Switching PIR Sensors Ceiling Mount 360 degree. Recess/Surface Mounting. Micro Detection - High Sensitivity Range 10 m Dia at height of 2.5 meter ( 7 m dia Micro Sensitivity 3 m macro) and Current Capacity 10A. Digital Remote IR based Commissioning with hand held programmer for following Programmable features: OFF delay time 10 Sec - 96 hrs, photocell and power up (status of luminaires when power is applied). It shall have provision to manually override luminary ON/OFF status using hand held remote control. 5 years Standard Warranty. Reference Model No. Honeywell LS3200RF (on/off) | C11: 18 | D11: Nos | E11: 3047.5 | F11: 212 | G11: =IFERROR(C11*E11,0) -> 54855 | H11: =IFERROR(C11*F11,0) -> 3816 | J11: 18 | K11: =J11*(E11) -> 54855
A12: g | B12: Digital PIR Regulating presence detection sensor. Recess/Surface Mounting. Micro Detection - High Sensitivity Range 10 m Dia at height of 2.5 meter ( 7 m dia Micro Sensitivity 3 m macro) to control 10A lighting load . Capable of dimming 15 dimmable (1-10 V Analogue Dimmable ) ballast. To be commissioned by hand held programmer with programmable features of delay time 10sec-96 hrs, photocell and power up (status of luminaires when power is applied). It shall have provision to manually override the luminaires’ ON / OFF / regulate lighting level status using hand held remote control and wired input for One switch control (push switch) to ON / OFF / regulate the lighting level. 5 years Standard Warranty. Reference Model No. Honeywell LS3000ARF (Analogue dimmable) | C12: 2 | D12: Nos | E12: 6704.5 | F12: 212 | G12: =IFERROR(C12*E12,0) -> 13409 | H12: =IFERROR(C12*F12,0) -> 424 | J12: 2 | K12: =J12*(E12) -> 13409
A13: h | B13: Supply, Installation, Testing & Commissioning of LED Recessed Downlighter with a nominal system luminous efficacy of >90Lm/W and Luminaire wattage of ≈ 15W. Also Safe operating voltage 140-270V AC. Power factor should be >0.95 & THD should be <10% & CRI>80. LED CCT Options 5700/4000/3000 K. LED Life should be 50,000Hrs with 2.5KV Surge Protection. Dimension: ø = 140 mm Cutout ø = 120 mm , H=40mm. Housing should be aluminium with special low glare MPO diffuser.The supply of accessories like clamps, supporting brackets and hardwares as required and interconnecting with 3 core 1.5 sqmm PVC insulated FRLS copper wire with all accessories required as per site conditions similar to Arraystorm Lighting Model No: ASDL1003RFXXIN015 | C13: 290 | D13: Nos | E13: 689 | F13: 119.78 | G13: =IFERROR(C13*E13,0) -> 199810 | H13: =IFERROR(C13*F13,0) -> 34736.2 | J13: 196 | K13: =J13*(E13) -> 135044
A14: i | B14: Supply, Installation, Testing & Commissioning of LED Recessed Downlighter with a nominal system luminous efficacy of >90Lm/W and Luminaire wattage of ≈ 15W. Provided with Analogue dimmable driver. Also Safe operating voltage 140-270V AC. Power factor should be >0.95 & THD should be <10% & CRI>80. LED CCT Options 5700/4000/3000 K. LED Life should be 50,000Hrs with 2.5KV Surge Protection. Dimension: ø = 140 mm Cutout ø = 120 mm , H=40mm. Housing should be aluminium with special low glare MPO diffuser.The supply of accessories like clamps, supporting brackets and hardwares as required and interconnecting with 3 core 1.5 sqmm PVC insulated FRLS copper wire with all accessories required as per site conditions similar to Arraystorm Lighting Model No: ASDL1003RFXXIN015-ANA | C14: 5 | D14: Nos | E14: 3445 | F14: 119.78 | G14: =IFERROR(C14*E14,0) -> 17225 | H14: =IFERROR(C14*F14,0) -> 598.9 | J14: 0 | K14: =J14*(E14) -> 0
A15: j | B15: Supplying, erecting, connecting and commissioning of 1 x 5watts per Mtrs 24V LED light fitting of approved make with necessary standard accessories. The supply of accessories like clamps, supporting brackets and hardwares as required and interconnecting with 3 core 1.5 sqmm PVC insulated FRLS copper wire with all accessories required as per site conditions | C15: 50 | D15: mtrs | E15: 477 | F15: 119.78 | G15: =IFERROR(C15*E15,0) -> 23850 | H15: =IFERROR(C15*F15,0) -> 5989 | J15: 50 | K15: =J15*(E15) -> 23850
A16: k | B16: Supplying, erecting, connecting and commissioning of LED light fitting of with necessary standard accessories Continuous Profile based lighting using Extruded aluminium deep profile of 17mm width with frosted diffuser. 24V LED short pitch strip light having power of 12W and 1200lm per metre to be used inside profile neatly pasted using high quality self-adhesive tape of 3M. 24V non integral driver to be used for the LED strip light. The profile and LED Strip should be cuttable as per site requirements. also. The supply of accessories like clamps, supporting brackets and hardwares as required and interconnecting with 3 core 1.5 sqmm PVC insulated FRLS copper wire with all accessories required as per site conditions | C16: 50 | D16: mtrs | E16: 1038.8 | F16: 119.78 | G16: =IFERROR(C16*E16,0) -> 51940 | H16: =IFERROR(C16*F16,0) -> 5989 | J16: 50 | K16: =J16*(E16) -> 51940
A17: l | B17: Supplying, erecting, connecting and commissioning of LED light fitting of with necessary standard accessories Continuous Profile based lighting using Extruded aluminium deep profile of 17mm width with frosted diffuser. 24V LED short pitch strip light having power of 12W and 1200lm per metre to be used inside profile neatly pasted using high quality self-adhesive tape of 3M. 24V non integral driver to be used for the LED strip light. The profile and LED Strip should be cuttable as per site requirements. also. The supply of accessories like clamps, supporting brackets and hardwares as required and interconnecting with 3 core 1.5 sqmm PVC insulated FRLS copper wire with all accessories required as per site conditions (Weather Proof) | C17: 10 | D17: mtrs | E17: 3392 | F17: 119.78 | G17: =IFERROR(C17*E17,0) -> 33920 | H17: =IFERROR(C17*F17,0) -> 1197.8 | J17: 10 | K17: =J17*(E17) -> 33920
... A20: o | B20: Supply,Installation, Testing and Commisioining of single 4 feet ceiling/surface mount 18/20W LED batten type fittings with electronic driver and all accessories as per the site conditions (Including the earthing of fixture) similar to Arraystorm Lighting Model No: ASTB9002FFXXIN020 | C20: 5 | D20: Nos | E20: 593.6 | F20: 119.78 | G20: =IFERROR(C20*E20,0) -> 2968 | H20: =IFERROR(C20*F20,0) -> 598.9 | J20: 5 | K20: =J20*(E20) -> 2968
A21: p | B21: Decorative Lights | E21: 0 | F21: 0 | G21: =SUM(G6:G20) -> 740516 | K21: =J21*(E21+F21) -> 0 | M21: =SUM(K6:K20) -> 700532.8
E22: 0 | F22: 0 | K22: =J22*(E22+F22) -> 0
A23: 1 | B23: Supply, Installation, Testing and Commisioining of 450mm dia 60w decorative type fittings. The supply of accessories like clamps, supporting brackets and hardwares as required and interconnecting with 3 core 1.5 sqmm PVC insulated FRLS copper wire with all accessories required as per site conditions approved by archeitech/consultant.Approx. Value of the fittings.Rs-5,000 | C23: 12 | D23: Nos | E23: 5300 | F23: 371 | G23: =IFERROR(C23*E23,0) -> 63600 | H23: =IFERROR(C23*F23,0) -> 4452 | J23: 3 | K23: =J23*(E23) -> 15900
A24: 2 | B24: Supply, Installation, Testing and Commisioining of 450mm dia 60w decorative type fittings. The supply of accessories like clamps, supporting brackets and hardwares as required and interconnecting with 3 core 1.5 sqmm PVC insulated FRLS copper wire with all accessories required as per site conditions approved by archeitech/consultant.Approx. Value of the fittings.Rs-10,000 | C24: 6 | D24: Nos | E24: 10600 | F24: 371 | G24: =IFERROR(C24*E24,0) -> 63600 | H24: =IFERROR(C24*F24,0) -> 2226 | J24: 0 | K24: =J24*(E24) -> 0
A25: 3 | B25: Supply, Installation, Testing & Commissioning of LED Suspended Continous LED Linear Profile Light. Minimum Guaranteed Technical Parameters should be: UGR <19 , System Luminous efficacy >90Lm/W, CRI >80, THD <10, SDCM<5, IP20. Wattage: ≈20W/meter, LED CCT options: 5700/4000/3000 K. SPD should be provided with 3.5kV, Luminaire Dimension: L = 1000 mm X Width = 75 mm And its should be EXTRUDED AL Housing with Special grade low glare MPO diffuser. The supply of accessories like clamps, supporting brackets and hardwares as required and interconnecting with 3 core 1.5 sqmm PVC insulated FRLS copper wire with all accessories required as per site conditions, | C25: 10 | D25: Mtr | E25: 6360 | F25: 265 | G25: =IFERROR(C25*E25,0) -> 63600 | H25: =IFERROR(C25*F25,0) -> 2650 | J25: 6 | K25: =J25*(E25) -> 38160
A26: 4 | B26: Supply, Installation, Testing and Commisioining of 4500 X 300mm Panel type fittings. The supply of accessories like clamps, supporting brackets and hardwares as required and interconnecting with 3 core 1.5 sqmm PVC insulated FRLS copper wire with all accessories required as per site conditions approved by archeitech/consultant.Approx. Value of the fittings is Rs 20,000 | C26: 1 | D26: Nos | E26: 21200 | F26: 795 | G26: =IFERROR(C26*E26,0) -> 21200 | H26: =IFERROR(C26*F26,0) -> 795 | J26: 0 | K26: =J26*(E26) -> 0
A27: 5 | B27: Supply, Installation, Testing and Commisioining of Linear type decarartive LED fittings. The supply of accessories like clamps, supporting brackets and hardwares as required and interconnecting with 3 core 1.5 sqmm PVC insulated FRLS copper wire with all accessories required as per site conditions approved by archeitech/consultant.Approx. Value of the fittings Minimum Guaranteed Technical Parameters should be: UGR <19 , System Luminous efficacy >90Lm/W, CRI >80, THD <10, SDCM<5, IP20. Wattage: ≈20W/meter, LED CCT options: 5700/4000/3000 K. SPD should be provided with 3.5kV, Luminaire Dimension: L = 5500 mm X Width = 75 mm | C27: 2 | D27: Nos | E27: 116600 | F27: 1590 | G27: =IFERROR(C27*E27,0) -> 233200 | H27: =IFERROR(C27*F27,0) -> 3180 | J27: 2 | K27: =J27*(E27) -> 233200
A28: 6 | B28: Supply, Installation, Testing and Commisioining of 12w twin light fittings. The supply of accessories like clamps, supporting brackets and hardwares as required and interconnecting with 3 core 1.5 sqmm PVC insulated FRLS copper wire with all accessories required as per site conditions approved by archeitech/consultant. | C28: 15 | D28: Nos | E28: 3180 | F28: 265 | G28: =IFERROR(C28*E28,0) -> 47700 | H28: =IFERROR(C28*F28,0) -> 3975 | J28: 0 | K28: =J28*(E28) -> 0
E29: 0 | F29: 0 | G29: =SUM(G23:G28) -> 492900 | M29: =SUM(K23:K28) -> 287260
B30: Sub Total | C30: =SUM(C4:C29)-(C17+C16+C15+C12+C11) -> 506 | E30: 0 | F30: 0 | G30: =SUM(G4:G29) -> 2466832 | H30: =SUM(H4:H29) -> 103895.9
E31: 0 | F31: 0
A32: 2 | B32: WIRING FOR LUMINAIRES | E32: 0 | F32: 0
B33: MS Conduits only for the closed ceiling only, open office area wiring through powder coated closed tray | E33: 0 | F33: 0
A34: I | B34: MAIN LIGHT WIRING (PP) | E34: 0 | F34: 0
A35: a | B35: Supply, Laying, Testing and Commissioning of 3R 1.5Sq.mm PVC insulated FRLS copper wire with 20mm dia MS conduit along with Modular 6A one way switch with moulded front plate GI anodized enclosure and other associated accessories as required as per the site conditions. | C35: 150 | D35: Nos | E35: 1280.48 | F35: 479.12 | G35: =IFERROR(C35*E35,0) -> 192072 | H35: =IFERROR(C35*F35,0) -> 71868
A36: b | B36: Supply, Laying, Testing and Commisiosning of 3C 1.5sqmm PVC insulated unarmoured sheathed FRLS flexible multistrand copper cable(BLACK) in existing trays/raceways with Modular 6A one way switch with moulded front plate GI anodised enclosure and other associated accessories as required as per the site conditions. | C36: 10 | D36: Nos | E36: 1296.38 | F36: 479.12 | G36: =IFERROR(C36*E36,0) -> 12963.8 | H36: =IFERROR(C36*F36,0) -> 4791.2
E37: 0 | F37: 0
A38: II | B38: SECONDARY LIGHT WIRING (SP) | E38: 0 | F38: 0
A39: a | B39: Supply, Laying, Testing and Commissioning of 3R 1.5Sqmm PVC insulated FRLS copper wire with 20mm dia MS conduit along with other associated accessories as required as per the site conditions. | C39: =488-(C35+C36) -> 328 | D39: Nos | E39: 503.5 | F39: 185.5 | G39: =IFERROR(C39*E39,0) -> 165148 | H39: =IFERROR(C39*F39,0) -> 60844
A40: b | B40: Supply, Laying, Testing and Commissioning of 2R 2.5Sqmm + 1R 1.5Sq.mm PVC insulated FRLS multistrand copper wire with 20mm dia MS conduit with all accessories as required as per site conditions.(lighting circuit mains) | C40: 1500 | D40: Mtrs | E40: 193.98 | F40: 66.78 | G40: =IFERROR(C40*E40,0) -> 290970 | H40: =IFERROR(C40*F40,0) -> 100170
A41: c | B41: Supply, Laying, Testing and Commissioning of 2R 2.5Sqmm + 1R 1.5S.mm PVC insulated FRLS multistrand copper wire in existing MS conduit with all accessories as required as per site conditions. | C41: 350 | D41: Mtrs | E41: 89.04 | F41: 25.44 | G41: =IFERROR(C41*E41,0) -> 31164 | H41: =IFERROR(C41*F41,0) -> 8904
A42: d | B42: Supply, Laying, Testing and Commissioning of 2R 1.5Sqmm + 1R 1.5Sq.mm PVC insulated FRLS Grey color multistrand copper wire with 25mm dia MS conduit with all accessories as required as per site conditions.(EL lighting circuit ) | C42: 300 | D42: Mtrs | E42: 228.96 | F42: 78.44 | G42: =IFERROR(C42*E42,0) -> 68688 | H42: =IFERROR(C42*F42,0) -> 23532
A43: e | B43: Supply, Laying, Testing and Commissioning of 2C 1.5sqmm PVC insulated unarmored sheathed FRLS flexible multistrand copper cable with MS conduit with all suitable accessories as reqd. | C43: 50 | D43: Mtrs | E43: 151.58 | F43: 58.3 | G43: =IFERROR(C43*E43,0) -> 7579 | H43: =IFERROR(C43*F43,0) -> 2915
B44: Sub Total | E44: 0 | F44: 0 | G44: =SUM(G34:G43) -> 768584.8 | H44: =SUM(H34:H43) -> 273024.2
A45: 3 | B45: POWER OUTLETS (SOCKETS) The UPS Modular are with white colour front plate & Black/Grey colour for rawpower | E45: 0 | F45: 0
A46: a | B46: Supply, Fixing, Testing and Commisiosning of 3 nos 16A socket and 1 no 16A switch with moulded front plate GI anodised enclosure and other associated accessories in the work station as required as per the site conditions.(for UPS POWER) | C46: 186 | D46: Nos | E46: 654.02 | F46: 159 | G46: =IFERROR(C46*E46,0) -> 121647.72 | H46: =IFERROR(C46*F46,0) -> 29574
A47: b | B47: Supply, Fixing, Testing and Commisiosning of 2 nos 16A socket and 1 no 16A switch with moulded front plate GI anodised enclosure and other associated accessories in the work station as required as per the site conditions. | C47: 46 | D47: Nos | E47: 491.84 | F47: 137.8 | G47: =IFERROR(C47*E47,0) -> 22624.64 | H47: =IFERROR(C47*F47,0) -> 6338.8
A48: c | B48: Supply, Fixing, Testing and Commisiosning of 1 nos 6A 3/5 pin shurtred Type socket and 1 no 6A switch with moulded front plate GI anodised enclosure and other associated accessories in the work station as required as per the site conditions.(for RAW POWER) | C48: 30 | D48: Nos | E48: 399.62 | F48: 106 | G48: =IFERROR(C48*E48,0) -> 11988.6 | H48: =IFERROR(C48*F48,0) -> 3180
A49: d | B49: Supply, Fixing, Testing and Commisiosning of 1 no 16/6A switched socket with moulded front plate GI anodised enclosure and other associated accessories as per the site conditions. | C49: 35 | D49: Nos | E49: 399.62 | F49: 106 | G49: =IFERROR(C49*E49,0) -> 13986.7 | H49: =IFERROR(C49*F49,0) -> 3710
A50: e | B50: Supply, Fixing, Testing and Commisiosning of 1 no 16/6A switched socket with moulded front plate GI anodised enclosure and other associated accessories including chasing embedding rough plastering as required as per the site conditions. (with indicator) | C50: 60 | D50: Nos | E50: 411.28 | F50: 106 | G50: =IFERROR(C50*E50,0) -> 24676.8 | H50: =IFERROR(C50*F50,0) -> 6360
A51: f | B51: Supply, Fixing, Testing and Commisiosning of 1 no 16/6A spalsh proof switched socket with moulded front plate GI anodised enclosure and other associated accessories as per the site conditions.(for RAW POWER) | C51: 5 | D51: Nos | E51: 657.2 | F51: 106 | G51: =IFERROR(C51*E51,0) -> 3286 | H51: =IFERROR(C51*F51,0) -> 530
A52: g | B52: Supply, Fixing, Testing and Commissioning of 1 no 6A switched socket with moulded front plate GI anodized enclosure and other associated accessories as per the site conditions.(for RAW POWER) | C52: 10 | D52: Nos | E52: 295.74 | F52: 106 | G52: =IFERROR(C52*E52,0) -> 2957.4 | H52: =IFERROR(C52*F52,0) -> 1060
A53: h | B53: Supply, Fixing, Testing and Commissioning of 32A, 3 pin industrial type interlocked switched socket outlet with 32A DP MCB- D Curve and accessories and surface mounting box of IP 44 degree of protection with plug top and other associated accessories as required as per the site conditions. To be fixed in Ceiling trays or in the floor near server/hub rack | C53: 6 | D53: Nos | E53: 3392 | F53: 371 | G53: =IFERROR(C53*E53,0) -> 20352 | H53: =IFERROR(C53*F53,0) -> 2226
A54: i | B54: Supply, Fixing, Testing and Commissioning of 32A, 5 pin industrial type interlocked switched socket outlet with 32A TP+2N RCBO with supporting accessories and surface mounting box of IP 44 degree of protection with plug top and other associated accessories as required as per the site conditions. | C54: 1 | D54: Nos | E54: 9010 | F54: 371 | G54: =IFERROR(C54*E54,0) -> 9010 | H54: =IFERROR(C54*F54,0) -> 371 | N54: =13000/6 -> 2166.6667
A55: j | B55: Supply, Fixing, Testing and Commissioning of 32A, 3pin industrial type metal socket outlet controlled by a 32A DP RCBO enclosed in MS Enclosure with plug top and other associated accessories as required as per the site conditions. | C55: 4 | D55: Nos | E55: 4770 | F55: 371 | G55: =IFERROR(C55*E55,0) -> 19080 | H55: =IFERROR(C55*F55,0) -> 1484
A56: k | B56: Supply, Fixing, Testing and Commissioning of 63A 4P 100mA RCBO enclosed in weather proof Enclosure with and other associated accessories as required as per the site conditions. | C56: 1 | D56: Nos | E56: 5384.8 | F56: 371 | G56: =IFERROR(C56*E56,0) -> 5384.8 | H56: =IFERROR(C56*F56,0) -> 371
A57: l | B57: Supply, Fixing, Testing and Commissioning of 40A 4P 100mA RCBO enclosed in weather proof Enclosure with and other associated accessories as required as per the site conditions. | C57: 5 | D57: Nos | E57: 5384.8 | F57: 371 | G57: =IFERROR(C57*E57,0) -> 26924 | H57: =IFERROR(C57*F57,0) -> 1855
A58: m | B58: Supply, Fixing, Testing and Commissioning of 63A TPN MCB enclosed in weather proof Enclosure with and other associated accessories as required as per the site conditions. | C58: 1 | D58: Nos | E58: 3116.4 | F58: 371 | G58: =IFERROR(C58*E58,0) -> 3116.4 | H58: =IFERROR(C58*F58,0) -> 371
A59: n | B59: Supply, Fixing, Testing and Commissioning of 40A TPN MCB enclosed in weather proof Enclosure with and other associated accessories as required as per the site conditions. | C59: 1 | D59: Nos | E59: 3116.4 | F59: 371 | G59: =IFERROR(C59*E59,0) -> 3116.4 | H59: =IFERROR(C59*F59,0) -> 371
A60: o | B60: Supply, Fixing, Testing and Commissioning of 20/32A DP MCB enclosed in Enclosure with and other associated accessories as required as per the site conditions. | C60: 1 | D60: Nos | E60: 2556.72 | F60: 371 | G60: =IFERROR(C60*E60,0) -> 2556.72 | H60: =IFERROR(C60*F60,0) -> 371
A61: p | B61: Supply and Fixing of 3Module Data/Voice PVC Enclosure box with other associated accessories as required as per the site conditions. | C61: 40 | D61: Nos | E61: 68.9 | F61: 15.9 | G61: =IFERROR(C61*E61,0) -> 2756 | H61: =IFERROR(C61*F61,0) -> 636
A62: q | B62: Supply and Fixing of 250A 4PMCCB with MFM along with suitable CTs Breaker In the Exisitng Panel with other all associated accessories as required as per the site conditions. | C62: 1 | D62: Nos | E62: 82000 | F62: 9010 | G62: =IFERROR(C62*E62,0) -> 82000 | H62: =IFERROR(C62*F62,0) -> 9010
E63: 0 | F63: 0
B64: Sub Total | E64: 0 | F64: 0 | G64: =SUM(G46:G63) -> 375464.18 | H64: =SUM(H46:H63) -> 67818.8
E65: 0 | F65: 0
A66: 4 | B66: CABLING FOR POWER OUTLETS | E66: 0 | F66: 0
B67: UPS/RAW POWER WIRING | E67: 0 | F67: 0
A68: a | B68: Supply, Laying, Testing and Commissioning of 3C 2.5sqmm PVC insulated unarmored sheathed FRLS flexible multistrand copper cable(WHITE) in trays / raceways with all accessories as reqd.(6/16A Ups socket) | C68: 3400 | D68: Mtrs | E68: 94 | F68: 15.9 | G68: =IFERROR(C68*E68,0) -> 319600 | H68: =IFERROR(C68*F68,0) -> 54060
A69: b | B69: Supply, Laying, Testing and Commissioning of 3C 2.5sqmm PVC insulated unarmored sheathed FRLS flexible multistrand copper cable (WHITE) with suitable MS conduits with all accessories as reqd.(16A Ups socket) | C69: 1000 | D69: Mtrs | E69: 190 | F69: 53 | G69: =IFERROR(C69*E69,0) -> 190000 | H69: =IFERROR(C69*F69,0) -> 53000
A70: c | B70: Supply, Laying, Testing and Commissioning of 3C 2.5sqmm PVC insulated unarmored sheathed FRLS flexible multistrand copper cable(BLACK) in trays/raceways with all suitable accessories as reqd. (Raw power socket) | C70: 1500 | D70: Mtrs | E70: 94 | F70: 15.9 | G70: =IFERROR(C70*E70,0) -> 141000 | H70: =IFERROR(C70*F70,0) -> 23850
A71: d | B71: Supply, Laying, Testing and Commissioning of 3C 2.5sqmm PVC insulated unarmored sheathed FRLS flexible multistrand copper cable(BLACK) with MS conduit with all suitable accessories as reqd.( 6A Raw power socket) | C71: 500 | D71: Mtrs | E71: 190 | F71: 53 | G71: =IFERROR(C71*E71,0) -> 95000 | H71: =IFERROR(C71*F71,0) -> 26500
A72: e | B72: Supply, Laying, Testing and Commissioning of 3C 4sqmm PVC insulated unarmored sheathed FRLS flexible multistrand copper cable with MS conduit with all suitable accessories as reqd. | C72: 250 | D72: Mtrs | E72: 254.4 | F72: 59.36 | G72: =IFERROR(C72*E72,0) -> 63600 | H72: =IFERROR(C72*F72,0) -> 14840
A73: f | B73: Supply, Laying, Testing and Commissioning of 3C4sqmm PVC insulated unarmored sheathed FRLS flexible multistrand copper cable in trays / raceways with all accessories as reqd. | C73: 50 | D73: Mtrs | E73: 148.4 | F73: 23.32 | G73: =IFERROR(C73*E73,0) -> 7420 | H73: =IFERROR(C73*F73,0) -> 1166
A74: g | B74: Supply, Laying, Testing and Commissioning of 3C 1.5sqmm PVC insulated unarmored sheathed FRLS flexible multistrand copper cable with FR PVC conduit with all suitable accessories as reqd. | C74: 20 | D74: Mtrs | E74: 67.045 | F74: 21.2 | G74: =IFERROR(C74*E74,0) -> 1340.9 | H74: =IFERROR(C74*F74,0) -> 424
E75: 0 | F75: 0
B76: Sub Total | E76: 0 | F76: 0 | G76: =SUM(G66:G74) -> 817960.9 | H76: =SUM(H66:H74) -> 173840
A77: 5 | B77: UNDER FLOOR CABLE MANAGEMENT SYSTEM | E77: 0 | F77: 0 | G77: =C77*E77 -> 0 | H77: =C77*F77 -> 0
A78: I | B78: Supply, Fixing of Aluminium Trunking box of 1.6mm thick and should be earthed every 3meters with 2.5sqmm copper wire, 60MM floor cutting, removing the debris, plastering with propoer checkan mesh Clamps and all other accessories as required as per the site condition for fixing the same. (the proper couplers to be used in between the joining of raceways) | E78: 0 | F78: 0 | G78: =C78*E78 -> 0 | H78: =C78*F78 -> 0
A79: a | B79: 50 x 25 mm Aluminium Channel | C79: 10 | D79: Mtrs | E79: 530 | F79: 318 | G79: =IFERROR(C79*E79,0) -> 5300 | H79: =IFERROR(C79*F79,0) -> 3180
A80: b | B80: 100 x 45mm Aluminium Channel | C80: 350 | D80: Mtrs | E80: 636 | F80: 318 | G80: =IFERROR(C80*E80,0) -> 222600 | H80: =IFERROR(C80*F80,0) -> 111300
E81: 0 | F81: 0
B82: Sub Total | E82: 0 | F82: 0 | G82: =SUM(G78:G81) -> 227900 | H82: =SUM(H78:H81) -> 114480
A83: 6 | B83: UNDER FLOOR JUNCTION BOXES | E83: 0 | F83: 0 | G83: =C83*E83 -> 0 | H83: =C83*F83 -> 0
A84: II | B84: Supply, Fixing, Erection of Powder coated MS Junction box of following sizes.The MS junction box shall be earthed with 2.5sqmm copper wire with all hard wares and accessories as required including all clamps and hard wares for fixing the same. The proper supporting to be provided in the centre of the Junction Boxes. The Junction to be covered all other sides, excluding the entry side. The junction thickness is 2mm and top cover 3mm. | E84: 0 | F84: 0 | G84: =C84*E84 -> 0 | H84: =C84*F84 -> 0
A85: a | B85: 150 x 150 x 50mm | C85: 115 | D85: Nos | E85: 275.6 | F85: 159 | G85: =IFERROR(C85*E85,0) -> 31694 | H85: =IFERROR(C85*F85,0) -> 18285
A86: b | B86: 250 x 250 x 50mm | C86: 13 | D86: Nos | E86: 318 | F86: 159 | G86: =IFERROR(C86*E86,0) -> 4134 | H86: =IFERROR(C86*F86,0) -> 2067
A87: c | B87: 350 x 350 x 50mm | C87: 6 | D87: Nos | E87: 477 | F87: 159 | G87: =IFERROR(C87*E87,0) -> 2862 | H87: =IFERROR(C87*F87,0) -> 954
A88: d | B88: 450 x 450 x 50mm | C88: 6 | D88: Nos | E88: 948.7 | F88: 328.6 | G88: =IFERROR(C88*E88,0) -> 5692.2 | H88: =IFERROR(C88*F88,0) -> 1971.6
E89: 0 | F89: 0
A90: f | B90: Supply, Fixing, Erection of following size EGA Junction box with all hard wares and accessories as required including all clamps and hard wares for fixing the same. the unused side of the junction box to be covered with 14SWG sheet. | E90: 0 | F90: 0
B91: 350 x 350 x 50mm | C91: 1 | D91: Nos | E91: 9010 | F91: 530 | G91: =IFERROR(C91*E91,0) -> 9010 | H91: =IFERROR(C91*F91,0) -> 530
B92: Sub Total | E92: 0 | F92: 0 | G92: =SUM(G84:G91) -> 53392.2 | H92: =SUM(H84:H91) -> 23807.6
A93: 7 | B93: SECONDARY DISTRIBUTION SYSTEMS | E93: 0 | F93: 0
A94: a | B94: Supply, Installation, Testing and Commissioning of three phase, phase segregated, compartmentalized 8 way MCBDB Double door type, IP 42 powder coated comprising of "C" curve MCB's for LIGHTING DB. | E94: 0 | F94: 0
B95: Incommer - 40A TPN MCB - 1 No | E95: 0 | F95: 0
B96: Phase Incommer - 40A 30mA DP RCBO- 3Nos | E96: 0 | F96: 0
B97: Outgoings - 6A SP MCB - 24 Nos | E97: 0 | F97: 0
B98: Blank Plates - 0 | E98: 0 | F98: 0
B99: Including all interconnections and other associated fixing accessories etc as reqd as per the site conditions. | C99: 0 | D99: Nos | E99: 0 | F99: 0 | G99: =IFERROR(C99*E99,0) -> 0 | H99: =IFERROR(C99*F99,0) -> 0
E100: 0 | F100: 0
A101: b | B101: Supply, Installation, Testing and Commissioning of three phase, phase segregated, compartmentalized 12way MCBDB Double door type, IP 42 powder coated comprising of "C" curve MCB's for LIGHTING DB. | E101: 0 | F101: 0
B102: Incommer - 40A TPN MCB - 1 No | E102: 0 | F102: 0
B103: Phase Incommer - 40A 30mA DP RCBO- 3Nos | E103: 0 | F103: 0
...

Sheet Elec-APPROVED MAKES
A1: LIST OF APPROVED MAKES
A2: SL. NO. | B2: DESCRIPTION | C2: BRAND 1 | D2: BRAND 2 | E2: BRAND 3 | F2: BRAND CONSIDERED BY THE CONTRACTOR
A3: 1 | B3: DISTRIBUTION BOARDS | C3: SCHNEIDER | D3: LEGRAND/L&T/ABB | E3: HAGER/HAVELLS
A4: =A3+1 -> 2 | B4: MCB / ELCB/RCBO | C4: SCHNEIDER | D4: LEGRAND/L&T/ABB | E4: HAGER/HAVELLS
A5: =A4+1 -> 3 | B5: LIGHT FITTINGS | C5: ARRAY STORM/WIPRO | D5: REGENT/DIVINITY | E5: PHILIPS/LT/PANASONIC
A6: =A5+1 -> 4 | B6: LIGHT FITTINGS ( Decorative) | C6: RIPPL Lighting /POLORIS | D6: Radical/NEXUS | E6: PURPLE-TURTLE/LUNARK
A7: =A6+1 -> 5 | B7: SWITCHES & SOCKETS | C7: LEGRAND/HONEYWELL/ANCHOR ROMA | D7: GREATWHITE/SCHNEIDER | E7: CRABTREE/NORTHWEST
A8: =A7+1 -> 6 | B8: LT CABLES | C8: POLYCAB | D8: HAVELLS | E8: KEI
A9: =A8+1 -> 7 | B9: WIRES | C9: HAVELLS/POLYCAB | D9: POWER FLEX/ASMON | E9: KEI/ANCHOR
A10: =A9+1 -> 8 | B10: GLANDS | C10: COMET | D10: DOWELL’s
A11: =A10+1 -> 9 | B11: TERMINAL BLOCKS | C11: ELMAX | D11: WAGO
A12: =A11+1 -> 10 | B12: MCCB's | C12: LEGRAND | D12: SCHNEIDER / L&T | E12: HAGER/ABB
A13: =A12+1 -> 11 | B13: ISOLATOR / STARTERS | C13: LEGRAND | D13: SCHNEIDER | E13: HAGER/ABB
A14: =A13+1 -> 12 | B14: LT PANEL FABRICATION | C14: CPRI APPROVED VENDORS
A15: =A14+1 -> 13 | B15: CT/PT'S | C15: AE | D15: KAPPA/KALAIVANI | E15: TRANSTECH
A16: =A15+1 -> 14 | B16: INSTRUMENTS & PQA | C16: EL MEASURE | D16: RISHUB/L&T | E16: SCHNEIDER
A17: =A16+1 -> 15 | B17: BUS BAR SUPPORTS | C17: POWERMAT | D17: SARAVANA | E17: LMAX
A18: =A17+1 -> 16 | B18: INDICATION LAMPS (LED) | C18: TECHNIC | D18: L & T | E18: ALTOS
A19: =A18+1 -> 17 | B19: SELECTOR SWITCHES | C19: SALZER | D19: L & T
A20: =A19+1 -> 18 | B20: INDUSTRIAL SOCKETS | C20: SCAME / LEGRAND | D20: HENSEL / MK/CAPE | E20: MENNEKES/BALS
A21: =A20+1 -> 19 | B21: CRIMPING SOCKETS | C21: COMET | D21: DOWELL’s | E21: HEX/HMI
A22: =A21+1 -> 20 | B22: MS CONDUITS | C22: VIMCO | D22: BEC / JAVERI | E22: GUPTA (GB)
A23: =A22+1 -> 21 | B23: PVC CONDUITS | C23: VASIVI/ANCHOR/SUN | D23: AVONPLAST | E23: PRECISION
A24: =A23+1 -> 22 | B24: GI ANODISED METAL BOX | C24: MK | D24: CRABTREE | E24: LEGRAND
A25: =A24+1 -> 23 | B25: CABLE TRAYS / RACEWAYS | C25: OBO | D25: PROFAB/CLASSIC/AEROSTAR | E25: NIEDAX/JKR
A26: =A25+1 -> 24 | B26: BALLASTS | C26: PHILIPS | D26: WIPRO | E26: BAJAJ/ARRAY STORM
A27: =A26+1 -> 25 | B27: EARTHING | C27: ASHLOK | D27: GRAVIN
A28: =A27+1 -> 26 | B28: EXHAUST FANS | C28: GEC | D28: ALMONARD | E28: USHA
A29: =A28+1 -> 27 | B29: SENSORS | C29: HONEYWELL/GRIDSENSE | D29: LUTRON | E29: CRESTRON
A30: =A29+1 -> 28 | B30: EGA BOX | C30: HONEYWELL/CONNECTWELL | D30: MG/CJ INFRA | E30: LEGRAND
A31: =A30+1 -> 29 | B31: UPS System & conveters | C31: APC/FUJI | D31: NUMERIC/ABB | E31: SOCOMEC/RELIO
A32: =A31+1 -> 30 | B32: BATTERY | C32: AMARRAJ | D32: ROCKET | E32: HBL

Sheet FAS AND PA SUMMARY
A1: FAS AND PA SUMMARY | F1: JLL Summary
A2: S.NO | B2: DESCRIPTION | C2: SUPPLY | D2: ERECTION | E2: TOTAL | F2: SUPPLY | G2: ERECTION | H2: TOTAL
C3: AMOUNT INR | D3: AMOUNT INR | F3: AMOUNT INR | G3: AMOUNT INR
A4: 1 | B4: ADDRESSABLE FIRE ALARM SYSTEM | C4: =FA!G26 -> 1272964.6 | D4: =FA!I26 -> 121894.7 | E4: =D4+C4 -> 1394859.3 | F4: =FA!L26 -> 688322.39 | G4: =FA!M26 -> 90194.075 | H4: =F4+G4 -> 778516.47
A5: =A4+1 -> 2 | B5: PUBLIC ADDRESS SYSTEM | C5: =PA!G15 -> 405110.8 | D5: =PA!I15 -> 57187 | E5: =D5+C5 -> 462297.8 | F5: {=PA!L15:M15} -> 363507.92 | G5: 46353.8 | H5: =F5+G5 -> 409861.72
A6: =A5+1 -> 3 | B6: SPRINKLER SYSTEM | C6: =FPS!G43 -> 1113848 | D6: =FPS!I43 -> 404782.2 | E6: =D6+C6 -> 1518630.2 | F6: =FPS!L43 -> 1143927.7 | G6: =FPS!M43 -> 257719.92 | H6: =F6+G6 -> 1401647.6
A7: =A6+1 -> 4 | B7: SIGNAGE SYSTEM | C7: =SIGNAGE!G9 -> 33496 | D7: =SIGNAGE!I9 -> 8511.8 | E7: =D7+C7 -> 42007.8 | F7: =SIGNAGE!L9 -> 23108 | G7: =SIGNAGE!M9 -> 4653.4 | H7: =F7+G7 -> 27761.4
A8: =A7+1 -> 5 | B8: FIRE EXTINGUISHER SYSTEM | C8: =FE!G9 -> 107643 | D8: =FE!I9 -> 3816 | E8: =D8+C8 -> 111459 | F8: =FE!L9 -> 107643 | G8: =FE!M9 -> 3816 | H8: =F8+G8 -> 111459
A9: =A8+1 -> 6 | B9: ACCESS CONTROL SYSTEM | C9: =ACCESS!G28 -> 901095.4 | D9: =ACCESS!I28 -> 278027.4 | E9: =D9+C9 -> 1179122.8 | F9: =ACCESS!L28 -> 701720 | G9: =ACCESS!M28 -> 211682 | H9: =F9+G9 -> 913402
A10: =A9+1 -> 7 | B10: CCTV SYSTEM | C10: =CCTV!G15 -> 474032 | D10: =CCTV!I15 -> 73882 | E10: =D10+C10 -> 547914 | F10: =CCTV!M15 -> 392624 | G10: =CCTV!N15 -> 39538 | H10: =F10+G10 -> 432162
A11: =A10+1 -> 8 | B11: RODENT REPELLENT SYSTEM | C11: =RODENT!I9 -> 51304 | D11: =RODENT!K9 -> 11230.7 | E11: =D11+C11 -> 62534.7 | F11: =RODENT!N9 -> 23320 | G11: =RODENT!O9 -> 4028 | H11: =F11+G11 -> 27348
A12: =A11+1 -> 9 | B12: WATER LEAK DETECTION SYSTEM | C12: =WLD!I8 -> 58088 | D12: =WLD!K8 -> 6508.4 | E12: =D12+C12 -> 64596.4 | F12: =WLD!N8 -> 57293 | G12: =WLD!O8 -> 6211.6 | H12: =F12+G12 -> 63504.6
A13: 10 | B13: GAS SUPPRESSION SYSTEM | C13: =GSS!H29 -> 744757.03 | D13: =GSS!J29 -> 230397.8 | E13: =D13+C13 -> 975154.83 | F13: =GSS!M29 -> 645275 | G13: =GSS!N29 -> 68677.4 | H13: =F13+G13 -> 713952.4
B14: TOTAL WITHOUT TAX | C14: =SUM(C4:C13) -> 5162338.8 | D14: =SUM(D4:D13) -> 1196238 | E14: =SUM(E4:E13) -> 6358576.8 | F14: =SUM(F4:F13) -> 4146741 | G14: =SUM(G4:G13) -> 732874.19 | H14: =SUM(H4:H13) -> 4879615.2 | I14: =E14-H14 -> 1478961.7

Sheet FA
A1: ADDRESSABLE FIRE ALARAM SYSTEM BOQ
A2: SI.No | B2: Descriptions | C2: Unit | D2: 1F | E2: Total Qty | F2: SUPPLY | H2: ERECTION | J2: Makes
F3: RATE INR | G3: AMOUNT INR | H3: RATE INR | I3: AMOUNT INR
B4: SITC OF ADDRESSABLE FIRE ALARM SYSTEM
A5: 1 | B5: Analogue Addressable Intelligent 2 loop Fire alarm control panel including loop card, provision to make with a minimum capacity of 125 devices + 125 modules per loop, with battery back up for 48 Hrs during normal operation and 15 minutes alarm operation, with minimum 160 Character LCD display, necessary interface card to connect a repeater panel and all hardware & software as per specification. | C5: Nos | D5: 1 | E5: =SUM(D5:D5) -> 1 | F5: 282172 | G5: =F5*E5 -> 282172 | H5: 5300 | I5: =H5*E5 -> 5300 | J5: NOTIFIER
A6: =A5+1 -> 2 | B6: SITC of Bacnet card for BMS integration | C6: Nos | E6: 1 | F6: 159000 | G6: =F6*E6 -> 159000 | H6: 5300 | I6: =H6*E6 -> 5300 | J6: NOTIFIER
A7: =A6+1 -> 3 | B7: Supply Installation Testing & Commissioning of multi sensor detector (photo+heat) with base,powder coated back box and other accessories as required and Detectors shall be UL listed, - (ABOVE FALSE CEILING & FALSE FLOOR) with dust level indication | C7: Nos | D7: 68 | E7: =SUM(D7:D7) -> 68 | F7: 2448.6 | G7: =F7*E7 -> 166504.8 | H7: 265 | I7: =H7*E7 -> 18020 | J7: NOTIFIER | K7: 69 | L7: =K7*F7 -> 168953.4 | M7: =K7*H7 -> 18285
A8: =A7+1 -> 4 | B8: Supply Installation Testing & Commissioning of multi sensor detector (photo+heat) with base and other accessories as required and Detectors shall be UL listed, - (BELOW FALSE CEILING)with dust level indication | C8: Nos | D8: 68 | E8: =SUM(D8:D8) -> 68 | F8: 2448.6 | G8: =F8*E8 -> 166504.8 | H8: 265 | I8: =H8*E8 -> 18020 | J8: NOTIFIER | K8: 69 | L8: =K8*F8 -> 168953.4 | M8: =K8*H8 -> 18285
A9: =A8+1 -> 5 | B9: Supply Installation Testing & Commissioning of Analog Addressable Smoke Detector with programmable for timed automatic sensitivity selection with Standard base, powder coated backbox and other accessories as required and Detectors shall be UL Listed. (TRUE CEILING / ABOVE FALSE CEILING)with dust level indication | C9: Nos | D9: 12 | E9: =SUM(D9:D9) -> 12 | F9: 2448.6 | G9: =F9*E9 -> 29383.2 | H9: 265 | I9: =H9*E9 -> 3180 | J9: NOTIFIER | L9: =K9*F9 -> 0 | M9: =K9*H9 -> 0
A10: =A9+1 -> 6 | B10: Supply Installation Testing & Commissioning of Analog Addressable Smoke Detector with programmable for timed automatic sensitivity selection with Standard base and other accessories as required and Detectors shall be UL Listed. (BELOW FALSE CEILING)with dust level indication | C10: Nos | E10: =SUM(D10:D10) -> 0 | F10: 0 | G10: =F10*E10 -> 0 | H10: 0 | I10: =H10*E10 -> 0 | J10: NOTIFIER | L10: =K10*F10 -> 0 | M10: =K10*H10 -> 0
A11: 8 | B11: Analogue Addressable Duct sensor detector with multiple sensitivity levels, programmable for timed automatic sensitivity selection and with base, UL listed,with dust level indication | C11: Nos | D11: 4 | E11: =SUM(D11:D11) -> 4 | F11: 11448 | G11: =F11*E11 -> 45792 | H11: 265 | I11: =H11*E11 -> 1060 | J11: NOTIFIER | L11: =K11*F11 -> 0 | M11: =K11*H11 -> 0
A12: 10 | B12: Supply Installation Testing & Commissioning of heat detector with base, Junction box and other accessories as required and Detectors shall be UL listed, | C12: Nos | E12: =SUM(D12:D12) -> 0 | F12: 0 | G12: =F12*E12 -> 0 | H12: 0 | I12: =H12*E12 -> 0 | J12: NOTIFIER | L12: =K12*F12 -> 0 | M12: =K12*H12 -> 0
A13: 11 | B13: SITC of Response indicator | C13: Nos | D13: 59 | E13: =SUM(D13:D13) -> 59 | F13: 90.1 | G13: =F13*E13 -> 5315.9 | H13: 42.4 | I13: =H13*E13 -> 2501.6 | J13: RAVEL/C SYSTEM/AGNI | K13: 61 | L13: =K13*F13 -> 5496.1 | M13: =K13*H13 -> 2586.4
A14: 12 | B14: Analogue Addressable Fault isolator module capable of monitoring shorted loop circuit and automatically restore communications when shorted conditions are corrected. (FIM's are used for every 20 detectors/devices) | C14: Nos | D14: =SUM(D7:D12,D15,D16,D17,D19)/20 -> 9.1 | E14: =SUM(D14:D14) -> 9.1 | F14: 3127 | G14: =F14*E14 -> 28455.7 | H14: 371 | I14: =H14*E14 -> 3376.1 | J14: NOTIFIER | K14: 10 | L14: =K14*F14 -> 31270 | M14: =K14*H14 -> 3710
A15: =A14+1 -> 13 | B15: Supply, installation, fixing, testing and commissioning of Analogue Addressable Monitor module with back box(1.6mm thick RED colour) operating at 24V DC, 2A, rated at 230V, provided with DPDT contact. (FLOW SWITCH#1 BB INTEGRATION#1 WLD#2, GSS#2, FIRE DOOR#2) with required fixing accessories | C15: Nos | D15: 5 | E15: =SUM(D15:D15) -> 5 | F15: 2915 | G15: =F15*E15 -> 14575 | H15: 265 | I15: =H15*E15 -> 1325 | J15: NOTIFIER | K15: 8 | L15: =K15*F15 -> 23320 | M15: =K15*H15 -> 2120
A16: =A15+1 -> 14 | B16: Supply, installation, fixing, testing and commissioning of Analogue Addressable Control module with back box (1.6mm thick RED colour) operating at 24V DC, 2A, rated at 230V, provided with DPDT contact,with required fixing accessories Access Control #1 BB INTEGRATION#1 PA INTEGRATION#1, Hooter#1 | C16: Nos | D16: 8 | E16: =SUM(D16:D16) -> 8 | F16: 3354.9 | G16: =F16*E16 -> 26839.2 | H16: 265 | I16: =H16*E16 -> 2120 | J16: NOTIFIER | K16: 2 | L16: =K16*F16 -> 6709.8 | M16: =K16*H16 -> 530
A17: =A16+1 -> 15 | B17: Supply, installation, fixing, testing and commissioning of Analogue Addressable Control relay module with back box(1.6mm thick RED colour) operating at 24V DC, 2A, rated at 230V, provided with DPDT contact. with required fixing accessories, AC/FD/UPS/BAT/SERV/ELE TRIPPING | C17: Nos | D17: 8 | E17: =SUM(D17:D17) -> 8 | F17: 3354.9 | G17: =F17*E17 -> 26839.2 | H17: 265 | I17: =H17*E17 -> 2120 | J17: NOTIFIER | K17: 12 | L17: =K17*F17 -> 40258.8 | M17: =K17*H17 -> 3180
A18: =A17+1 -> 16 | B18: Addressable Electronic Hooter cum Strobe ceiling mounted. The hooters shall be made of ABS plastic, and have a DB level of 65dbA and a multi tone facility. Addressable Control Module shall be fitted in a junction box. | C18: Nos | D18: 9 | E18: =SUM(D18:D18) -> 9 | F18: 9010 | G18: =F18*E18 -> 81090 | H18: 265 | I18: =H18*E18 -> 2385 | J18: NOTIFIER | K18: 8 | L18: =K18*F18 -> 72080 | M18: =K18*H18 -> 2120
A19: =A18+1 -> 17 | B19: SITC of Addressable Manual call point having an integrally mounted addressable module that monitors and reports contact status. (PULL TYPE) with back box(1.6mm thick RED colour) along with required fixing accessories. The device shall have an LED which shall blink in normal state & get steady on activation to monitor the heath status of the device. | C19: Nos | D19: 9 | E19: =SUM(D19:D19) -> 9 | F19: 4542.1 | G19: =F19*E19 -> 40878.9 | H19: 265 | I19: =H19*E19 -> 2385 | J19: NOTIFIER | K19: 8 | L19: =K19*F19 -> 36336.8 | M19: =K19*H19 -> 2120
A20: =A19+1 -> 18 | B20: 2C x 1.5 mm2, Stranded Copper conductor,Type A ST1 PVC insulated,Armoured FRLS CU Cable 1100 V as per IS 1554, with GI saddle spacers every 0.3 mtr with Single compression Cable Glands,ABS Junction Boxes (wherever required), terminals,Ferruling complete. | C20: Rmt | D20: =(D7+D8+D9+D10+D11+D12)*12 -> 1824 | E20: =SUM(D20:D20) -> 1824 | F20: 90.1 | G20: =F20*E20 -> 164342.4 | H20: 26.5 | I20: =H20*E20 -> 48336 | J20: POLYCAB / VARSHA/ KEI/DATA FLEX | K20: =2.4+2.2+1+4.8+5.9+3.4+11.4+6.15+3.7+8.6+5.5+11.7+5.5+12.1+5.5+9.9+4.1+9.4+4.3+6.9+4.3+10.6+4.3+8.5+4.8+2.4+5.9+4.3+8.2+11+2.5+10+4.8+10.6+4.8+11.4+4.8+11.6+4.6+7.7+4.7+6+4.8+6.1+4.8+9+13.8+4.8+4.5+11+13.5+14+2.2+5.2+4.8+5.8+4.8+4.6+6.3+6.3+4.8+5.3+4.8+5.9+2.5+6.7+5.3+4.8+5.3+4.8+7.4+4.8+4.6+0.5+4.8+5.3+4.8+7.7+4.8+14.3+4.8+8.3+4.8+4.8+3+13.5+4.9+9.3+14+39.4+23.7+13.8+3.6+4.3+5.8+4.3+7.8+2.1+7.8+2.1+7.3+2.2+11.3+4.3+9.2+5.3+9.2+8+4.3+11.1+4.3+3.4+8.8+4.3+9.1+4.3+7.2+4.3+8.9+4.3+11+4.3+7.3+4.3+10.3+4.3+10.9+4.3+9.7+5.2+4.1+5.1+6.7+6.3+1.3+5.9+6.6+7.2+5.8+4.3+3.5+4.3+3.8+9.3+4.3+1.1+0.5+2.9+4.3+13.7+4.3+8.5+4.3+6.8+1.5+1.5+4.4+8.5+9.5+6+1.9+1.5+10.5+10.5+7.5+8.5+7+6+1.3+4.7+5.6+4.3+6.4+5.9+4.3+4+4.3+18.3+12.8+42.75+25.25+20.05+23.75 -> 1285.95 | L20: =K20*F20 -> 115864.09 | M20: =K20*H20 -> 34077.675
A21: =A20+1 -> 19 | B21: Supplying, installing, testing and commissioning of approved make FRLS PVC conduits on ceiling / wall / floor etc. complete with accessories like, Junction boxes, Collars, Bends, clamps, saddles etc. (for MCP) | F21: 0 | H21: 0 | J21: VIP/ PRECISION/ASTRA/ANCHOR | L21: =K21*F21 -> 0 | M21: =K21*H21 -> 0
A22: a | B22: 25 mm dia. | C22: Rmt | D22: =D19*5 -> 45 | E22: =SUM(D22:D22) -> 45 | F22: 47.7 | G22: =F22*E22 -> 2146.5 | H22: 21.2 | I22: =H22*E22 -> 954 | L22: =K22*F22 -> 0 | M22: =K22*H22 -> 0
A23: =A21+1 -> 20 | B23: Supply and laying of MS Powder coated Trunking 300 x 50 mm x 1.6mm with cover & fixing suppports etc as required (Cable dressing for Fire & PA panel ) | C23: Rmt | D23: 5 | E23: =SUM(D23:D23) -> 5 | F23: 901 | G23: =F23*E23 -> 4505 | H23: 148.4 | I23: =H23*E23 -> 742 | J23: REPUTED | L23: =K23*F23 -> 0 | M23: =K23*H23 -> 0
A24: =A23+1 -> 21 | B24: Supply and laying of GI enclosed raceway 300 x 50 mm x 1.6mm with cover & fixing suppports etc as required (Cable dressing inside the shaft ) | C24: Rmt | D24: RO | E24: =SUM(D24:D24) -> 0 | F24: 0 | H24: 0 | J24: REPUTED | K24: 8 | L24: =K24*F24 -> 0 | M24: =K24*H24 -> 0
A25: =A24+1 -> 22 | B25: SITC of PSU for hooters & AHU tripping (inclusive of Battery ckt & battery) | C25: Set | D25: 3 | E25: =SUM(D25:D25) -> 3 | F25: 9540 | G25: =F25*E25 -> 28620 | H25: 1590 | I25: =H25*E25 -> 4770 | J25: Battery : Panasonic/Exide/Amaron PSU : CTEC/CSYSTEM/INSYIN | K25: 2 | L25: =K25*F25 -> 19080 | M25: =K25*H25 -> 3180
B26: TOTAL | G26: =SUM(G5:G25) -> 1272964.6 | I26: =SUM(I4:I25) -> 121894.7 | L26: =SUM(L5:L25) -> 688322.39 | M26: =SUM(M5:M25) -> 90194.075

Sheet PA
A1: PUBLIC ADDRESS SYSTEM BOQ
A2: SI.No | B2: Descriptions | C2: Unit | D2: 1F | E2: Total Qty | F2: SUPPLY | H2: ERECTION | J2: Makes
F3: RATE INR | G3: AMOUNT INR | H3: RATE INR | I3: AMOUNT INR
A4: 1 | B4: SITC of 6W RMS False Ceiling Mount Speakers with inbuilt 100V Line Matching Transformer, wide opening angle, optimized for music & speech applications with mounting clamps as per specifications | C4: Nos | D4: 68 | E4: =SUM(D4:D4) -> 68 | F4: 848 | G4: =F4*E4 -> 57664 | H4: 212 | I4: =H4*E4 -> 14416 | J4: Honeywell | K4: 64 | L4: =K4*F4 -> 54272 | M4: =K4*H4 -> 13568
A5: 2 | B5: SITC of 6W RMS True Ceiling Mount Speakers with inbuilt 100V Line Matching Transformer, wide opening angle, optimized for music & speech applications with powder coated back box, supports as per specifications Speakers shll have the tappings at 1.5/3/6 watts | C5: Nos | D5: 12 | E5: =SUM(D5:D5) -> 12 | F5: 1219 | G5: =F5*E5 -> 14628 | H5: 212 | I5: =H5*E5 -> 2544 | J5: Honeywell | K5: 14 | L5: =K5*F5 -> 17066 | M5: =K5*H5 -> 2968
A6: =A5+1 -> 3 | B6: SITC of 6 W Wall Mounted Speakers with line matching transformers as specified as per specifications | C6: Nos | D6: 4 | E6: =SUM(D6:D6) -> 4 | F6: 1537 | G6: =F6*E6 -> 6148 | H6: 212 | I6: =H6*E6 -> 848 | J6: Honeywell | K6: 1 | L6: =K6*F6 -> 1537 | M6: =K6*H6 -> 212
A7: =A6+1 -> 4 | B7: SITC of System Controller complete with Microprocessor based 4 Zone Call Station, Stem Type Microphone, Dual Tone Control for Speech & Music,etc. | C7: Nos. | D7: 1 | E7: =SUM(D7:D7) -> 1 | F7: 132500 | G7: =F7*E7 -> 132500 | H7: 3180 | I7: =H7*E7 -> 3180 | J7: Honeywell | K7: 1 | L7: =K7*F7 -> 132500 | M7: =K7*H7 -> 3180
A8: =A7+1 -> 5 | B8: SITC of 6 zone call station keypad with accessories | C8: Nos. | D8: 1 | E8: =SUM(D8:D8) -> 1 | F8: 18550 | G8: =F8*E8 -> 18550 | H8: 1272 | I8: =H8*E8 -> 1272 | J8: Honeywell | K8: 1 | L8: =K8*F8 -> 18550 | M8: =K8*H8 -> 1272
A9: =A8+1 -> 6 | B9: SITC of Rack Mounted 120 W Power Amplifier | C9: Nos | D9: 1 | E9: 1 | F9: 26500 | G9: =F9*E9 -> 26500 | H9: 3180 | I9: =H9*E9 -> 3180 | J9: Honeywell | K9: 1 | L9: =K9*F9 -> 26500 | M9: =K9*H9 -> 3180
A10: =A9+1 -> 7 | B10: SITC of Rack Mounted 240 W Power Amplifier | C10: Nos | F10: 0 | G10: =F10*E10 -> 0 | H10: 0 | I10: =H10*E10 -> 0 | J10: Honeywell | L10: =K10*F10 -> 0 | M10: =K10*H10 -> 0
A11: =A10+1 -> 8 | B11: SITC of Rack Mounted 480 W Power Amplifier | C11: Nos | D11: 1 | E11: =SUM(D11:D11) -> 1 | F11: 44520 | G11: =F11*E11 -> 44520 | H11: 3180 | I11: =H11*E11 -> 3180 | J11: Honeywell | K11: 1 | L11: =K11*F11 -> 44520 | M11: =K11*H11 -> 3180
A12: =A11+1 -> 9 | B12: 2C x 1.5 mm2, Stranded Copper conductor,Type A ST1 PVC insulated,Armoured FRLS Cable 1100 V as per IS 1554, with GI saddle spacers every 0.3 mtr with Single compression Cable Glands,ABS Junction Boxes (wherever required), terminals,Ferruling complete. | C12: Rmt. | D12: =(D4+D5+D6)*12 -> 1008 | E12: =SUM(D12:D12) -> 1008 | F12: 90.1 | G12: =F12*E12 -> 90820.8 | H12: 26.5 | I12: =H12*E12 -> 26712 | J12: POLYCAB / VARSHA/ KEI/DATA FLEX | K12: =14.7+7.7+9.9+10.7+8.7+9.9+8.1+7.7+9.8+12.9+6.6+5.9+7.2+8.4+10.2+6.9+8.5+12.9+6+11.1+7.3+11.9+9+4.2+6.7+8.5+6.1+6.4+5.9+4.6+9.5+5+5.9+5.3+7.4+9.6+3+7+8+5+10.7+9.6+6.6+9+1+7.6+12.4+8.2+6.4+5.2+8.7+10.2+9+8.4+10.5+9+7.8+6+10.2+9.6+10.2+9.6+10.2+7.8+8.4+7.8+7.9+18.6+7.8+9.6+6.4+8.8+9+2.7+8.4+9+6.6+7.2+6+1 -> 649.2 | L12: =K12*F12 -> 58492.92 | M12: =K12*H12 -> 17203.8
A13: =A12+1 -> 10 | B13: SITC of Volume controller for one speaker (near reciption) | C13: Nos | D13: 1 | E13: =SUM(D13:D13) -> 1 | F13: 3710 | G13: =F13*E13 -> 3710 | H13: 265 | I13: =H13*E13 -> 265 | J13: Heinrich/ Bosch / Honeywell | L13: =K13*F13 -> 0 | M13: =K13*H13 -> 0
A14: =A13+1 -> 11 | B14: SITC OF Suitable size 9U rack as per following specification, Conforms to DIN 41494 Or Equivalent EIA/ISO/EN/CEA Standard Finish - Powder coated finish with Seven tank pretreatment process meeting ASTM standard Color - Black/off white/grey Fan module on top of the rack Welded frame with vented top cover with fan , perforated Metal Door with lock & Key and Back vented / Perforated metal door with lock & key and partially vented side panels, free standing on floor with 4 No. casters wheels with 2 no with brakes & 2 No. without brakes, cable oraginesers, Levelers with required 16A/5A power strips including accessories. Number of racks shall be as per the design requirement. vendor to consider required number of racks as per their requirement | C14: Lot | D14: 1 | E14: =SUM(D14:D14) -> 1 | F14: 10070 | G14: =F14*E14 -> 10070 | H14: 1590 | I14: =H14*E14 -> 1590 | J14: VALL RACK / MASS RACK | K14: 1 | L14: =K14*F14 -> 10070 | M14: =K14*H14 -> 1590
B15: TOTAL | G15: =SUM(G4:G14) -> 405110.8 | I15: =SUM(I4:I14) -> 57187 | L15: =SUM(L4:L14) -> 363507.92 | M15: =SUM(M4:M14) -> 46353.8

Sheet FPS
A1: FIRE PROTECTION SYSTEM BOQ
A2: SI.No | B2: Descriptions | C2: Unit | D2: 1F | E2: Total Qty | F2: SUPPLY | H2: ERECTION | J2: Makes
F3: RATE INR | G3: AMOUNT INR | H3: RATE INR | I3: AMOUNT INR
B4: SPRINKLER SYSTEM:
A5: 1 | B5: Supplying, installing,hydraulic testing and commissioning of Heavy grade MS Pipes confirming to IS :1239 part - I with malleable specials confirming to IS:1239 part - II, such as Tees, elbows, check nuts, unions, flanges, nipples etc. Including cutting, fixing in / on walls / on Floors, ceiling by using suitable supports such as MS channels ,angles,flats,rods as required at site with anchor fasteners,clamps,threaded rods,nuts,bolts,washers etc...complete. Painting the exposed with one coat of metal zinc chromate primer with two coats of synthetic enamel paint of approved colour / shade etc., complete.The pipe fittings shall be welded type up to 50 mm dia and grooved type for 65 mm dia & above. | J5: PIPE:JINDAL STAR / TATA SOCKET FITTINGS: B&M/ VS/ BHARATH FORGE
A6: a | B6: 25mm nominal dia | C6: Rmt | D6: 360 | E6: =SUM(D6:D6) -> 360 | F6: 445.2 | G6: =F6*E6 -> 160272 | H6: 148.4 | I6: =E6*H6 -> 53424 | K6: 312.5 | L6: =K6*F6 -> 139125 | M6: =K6*H6 -> 46375
A7: b | B7: 32mm nominal dia | C7: Rmt | D7: 56 | E7: =SUM(D7:D7) -> 56 | F7: 572.4 | G7: =F7*E7 -> 32054.4 | H7: 180.2 | I7: =E7*H7 -> 10091.2 | K7: 56.5 | L7: =K7*F7 -> 32340.6 | M7: =K7*H7 -> 10181.3
A8: c | B8: 40mm nominal dia | C8: Rmt | D8: 48 | E8: =SUM(D8:D8) -> 48 | F8: 699.6 | G8: =F8*E8 -> 33580.8 | H8: 212 | I8: =E8*H8 -> 10176 | K8: 49.4 | L8: =K8*F8 -> 34560.24 | M8: =K8*H8 -> 10472.8
A9: d | B9: 50mm nominal dia | C9: Rmt | D9: 56 | E9: =SUM(D9:D9) -> 56 | F9: 901 | G9: =F9*E9 -> 50456 | H9: 296.8 | I9: =E9*H9 -> 16620.8 | K9: 55.8 | L9: =K9*F9 -> 50275.8 | M9: =K9*H9 -> 16561.44
A10: e | B10: 65mm nominal dia | C10: Rmt | D10: 54 | E10: =SUM(D10:D10) -> 54 | F10: 2094.666 | G10: =F10*E10 -> 113111.96 | H10: 339.2 | I10: =E10*H10 -> 18316.8 | K10: 63.9 | L10: =K10*F10 -> 133849.16 | M10: =K10*H10 -> 21674.88
A11: f | B11: 80mm nominal dia | C11: Rmt | D11: 48 | E11: =SUM(D11:D11) -> 48 | F11: 2416.8 | G11: =F11*E11 -> 116006.4 | H11: 477 | I11: =E11*H11 -> 22896 | K11: 52.2 | L11: =K11*F11 -> 126156.96 | M11: =K11*H11 -> 24899.4
A12: g | B12: 100mm nominal dia | C12: Rmt | D12: 18 | E12: =SUM(D12:D12) -> 18 | F12: 3403.872 | G12: =F12*E12 -> 61269.696 | H12: 583 | I12: =E12*H12 -> 10494 | K12: 24 | L12: =K12*F12 -> 81692.928 | M12: =K12*H12 -> 13992
A13: h | B13: 150mm nominal dia | C13: Rmt | D13: 36 | E13: =SUM(D13:D13) -> 36 | F13: 4199.19 | G13: =F13*E13 -> 151170.84 | H13: 901 | I13: =E13*H13 -> 32436 | K13: 44.3 | L13: =K13*F13 -> 186024.12 | M13: =K13*H13 -> 39914.3
F14: 0 | H14: 0
A15: 2 | B15: Supply testing and commissioning of 15 mm gunmetal/chrome quartzoid bulb, quick response sprinkler heads suitable for 68 deg. C, K 80 | F15: 0 | H15: 0 | J15: TYCO/ VIKING/ VICTUALIC
B16: a) Pendent- 68deg C | C16: Nos | D16: 195 | E16: =SUM(D16:D16) -> 195 | F16: 254.4 | G16: =F16*E16 -> 49608 | H16: 132.5 | I16: =E16*H16 -> 25837.5 | K16: 193 | L16: =K16*F16 -> 49099.2 | M16: =K16*H16 -> 25572.5
B17: a) Pendent- 79deg C | C17: Nos | E17: =SUM(D17:D17) -> 0 | F17: 0 | G17: =F17*E17 -> 0 | H17: 0 | I17: =E17*H17 -> 0 | L17: =K17*F17 -> 0 | M17: =K17*H17 -> 0
B18: b) Upright - 68deg C | C18: Nos | D18: RO | E18: =SUM(D18:D18) -> 0 | F18: 0 | G18: =F18*E18 -> 0 | H18: 0 | I18: =E18*H18 -> 0 | K18: 34 | L18: =K18*F18 -> 0 | M18: =K18*H18 -> 0
B19: c)Upright - 79deg C | C19: Nos | E19: =SUM(D19:D19) -> 0 | F19: 0 | G19: =F19*E19 -> 0 | H19: 0 | I19: =E19*H19 -> 0 | L19: =K19*F19 -> 0 | M19: =K19*H19 -> 0
A20: 3 | B20: Dial type pressure guage for (0-16 Kg/cm2) with necessary nipple & other fittings, mounting arrangements and with a 15 mm ball valve | C20: Nos | D20: 1 | E20: =SUM(D20:D20) -> 1 | F20: 1749 | G20: =F20*E20 -> 1749 | H20: 174.9 | I20: =E20*H20 -> 174.9 | J20: H. GURU / WAREE / FIEBIG | K20: 1 | L20: =K20*F20 -> 1749 | M20: =K20*H20 -> 174.9
A21: =A20+1 -> 4 | B21: Supply, Installation, Testing & Commissioning of 25mm Ball valve with sight glass for Sprinkler test line | C21: Nos | E21: =SUM(D21:D21) -> 0 | F21: 0 | G21: =F21*E21 -> 0 | H21: 0 | I21: =E21*H21 -> 0 | J21: ZOLOTO/ LEADER/ LB | L21: =K21*F21 -> 0 | M21: =K21*H21 -> 0
A22: =A21+1 -> 5 | B22: Supply, Installation, Testing & Commissioning of 25mm Ball valve with sprinkler bulb for Sprinkler test line | C22: Nos | D22: 1 | E22: =SUM(D22:D22) -> 1 | F22: 1961 | G22: =F22*E22 -> 1961 | H22: 159 | I22: =E22*H22 -> 159 | J22: ZOLOTO/ LEADER/ LB | L22: =K22*F22 -> 0 | M22: =K22*H22 -> 0
A23: =A22+1 -> 6 | B23: Supply, Installation, Testing & Commissioning of 50mm Ball valve for Sprinkler drain line | C23: Nos | D23: 1 | E23: =SUM(D23:D23) -> 1 | F23: 2332 | G23: =F23*E23 -> 2332 | H23: 159 | I23: =E23*H23 -> 159 | J23: ZOLOTO/ LEADER/ LB | L23: =K23*F23 -> 0 | M23: =K23*H23 -> 0
A24: =A23+1 -> 7 | B24: Supply, Installation, Testing & Commissioning of Flow Switches with two NO and two NC contacts with necessary nipple & other fittings, Flow switch shall be suitable for 150 dia | C24: Nos | D24: 1 | E24: =SUM(D24:D24) -> 1 | F24: 6890 | G24: =F24*E24 -> 6890 | H24: 848 | I24: =E24*H24 -> 848 | J24: SYSTEM SENSOR/ HONEYWELL/ POTER | K24: 1 | L24: =K24*F24 -> 6890 | M24: =K24*H24 -> 848
A25: =A24+1 -> 8 | B25: Providing and fixing C.I. butterfly valves to IS:13095 with operating lever, bolts, nuts, washers and companion flanges complete. (PN-16) | E25: =SUM(D25:D25) -> 0 | F25: 0 | H25: 0 | J25: AUDCO/ KEYSTONE/ INTTERVALVE | L25: =K25*F25 -> 0 | M25: =K25*H25 -> 0
A26: a | B26: 50mm dia | C26: Nos | D26: RO | E26: =SUM(D26:D26) -> 0 | F26: 0 | G26: =F26*E26 -> 0 | H26: 0 | I26: =E26*H26 -> 0 | L26: =K26*F26 -> 0 | M26: =K26*H26 -> 0
A27: b | B27: 80mm dia | C27: Nos | D27: RO | E27: =SUM(D27:D27) -> 0 | F27: 0 | G27: =F27*E27 -> 0 | H27: 0 | I27: =E27*H27 -> 0 | L27: =K27*F27 -> 0 | M27: =K27*H27 -> 0
A28: c | B28: 100mm dia | C28: Nos | D28: RO | E28: =SUM(D28:D28) -> 0 | F28: 0 | G28: =F28*E28 -> 0 | H28: 0 | I28: =E28*H28 -> 0 | L28: =K28*F28 -> 0 | M28: =K28*H28 -> 0
A29: d | B29: 150mm dia | C29: Nos | D29: 1 | E29: =SUM(D29:D29) -> 1 | F29: 9010 | G29: =F29*E29 -> 9010 | H29: 848 | I29: =E29*H29 -> 848 | L29: =K29*F29 -> 0 | M29: =K29*H29 -> 0
A30: =A25+1 -> 9 | B30: Supply, installation, testing & commissioning of Non Return Valve of 150mm dia IS:5312( PN 16) along with connection flanges, bolts / nuts etc. | C30: Nos | E30: =SUM(D30:D30) -> 0 | F30: 0 | G30: =F30*E30 -> 0 | H30: 0 | I30: =E30*H30 -> 0 | J30: INTERVALVE / ADUCO / ZOLOTO | L30: =K30*F30 -> 0 | M30: =K30*H30 -> 0
A31: =A30+1 -> 10 | B31: Supply & fixing of approved type rosette plates ( Recessed type, in two piece) for Sprinklers below false ceiling area. | E31: =SUM(D31:D31) -> 0 | F31: 0 | H31: 0 | J31: FABRICATED(SAMPLE APPROVAL TO BE TAKEN) | L31: =K31*F31 -> 0 | M31: =K31*H31 -> 0
A32: a | B32: The Rosette shall be fabricated by M.S. plate of 2mm thick and the finish shall be powder coated and color shall be as approved by architects / clients. | C32: Nos | D32: =D16+D17 -> 195 | E32: =SUM(D32:D32) -> 195 | F32: 81.62 | G32: =F32*E32 -> 15915.9 | H32: 31.8 | I32: =E32*H32 -> 6201 | K32: 193 | L32: =K32*F32 -> 15752.66 | M32: =K32*H32 -> 6137.4
A33: =A31+1 -> 11 | B33: Stainless steel corrugated flexible pipe(hose) for dropping sprinklers below false ceiling, pipe shall be UL Listed, 16 bar pressure rating and 1800 mm long 25 mm dia with union / reducer collar, clamps etc. as required. (BRAIDED) | C33: Nos | D33: 0 | E33: =SUM(D33:D33) -> 0 | F33: 0 | G33: =F33*E33 -> 0 | H33: 0 | I33: =E33*H33 -> 0 | J33: TYCO/ VIKING/ VICTUALIC | L33: =K33*F33 -> 0 | M33: =K33*H33 -> 0
A34: =A33+1 -> 12 | B34: Stainless steel corrugated flexible pipe(hose) for dropping sprinklers below false ceiling, pipe shall be UL Listed, 16 bar pressure rating and 1500 mm long 25 mm dia with union / reducer collar, clamps etc. as required. (BRAIDED) | C34: Nos | D34: =D16+D17 -> 195 | E34: =SUM(D34:D34) -> 195 | F34: 1484 | G34: =F34*E34 -> 289380 | H34: 212 | I34: =E34*H34 -> 41340 | J34: TYCO/ VIKING/ VICTUALIC | K34: 193 | L34: =K34*F34 -> 286412 | M34: =K34*H34 -> 40916
A35: =A34+1 -> 13 | B35: Stainless steel corrugated flexible pipe(hose) for dropping sprinklers below false ceiling, pipe shall be UL Listed, 16 bar pressure rating and 1000 mm long 25 mm dia with union / reducer collar, clamps etc. as required.(BRAIDED) | C35: Nos | D35: RO | E35: =SUM(D35:D35) -> 0 | F35: 0 | G35: =F35*E35 -> 0 | H35: 0 | I35: =E35*H35 -> 0 | J35: TYCO/ VIKING/ VICTUALIC | L35: =K35*F35 -> 0 | M35: =K35*H35 -> 0
